Workbook
Name Categorie: Ressources!$K$2:$K$5
Name Catégories: #REF!
Name Num_Compte: Ressources!$A$2:$A$6
Name Segment_Compte: #N/A
Name Type_Compte: Ressources!$B$2:$B$6

Sheet Tableau de bord - Portefeuille
B1: Vue globale de mon portefeuille
D2: Tous les comptes sont convertis en CAD
B3: Notes | D3: Marge (CA) | G3: Valeur total | J3: =E4+E12+E20+E28+E36+B38 -> 677602.59 | O3: Plus grande variation du jour
B4: Prochain achat US : PPL JD TCEHY Remplir mon REER (PRIORITÉ) | D4: Valeur au marché | E4: =SUMIF(Titres[Compte],"Marge (CAD)",Titres[Valeur au marché ($ local)]) -> 253641.8 | G4: Coût total | J4: ='Titre et dividendes'!L79 -> 388303.04 | N4: 1 | O4: Gagnant : | P4: =_xlfn.XLOOKUP(MAX(Titres[Variation du jour ($)]),Titres[Variation du jour ($)],Titres[Action]) -> #VALUE!
D5: Gain ($) | E5: =SUMIF(Titres[Compte],"Marge (CAD)",Titres[Gain non réalisé ($)]) -> 86721.65 | G5: Gain ($) | J5: ='Titre et dividendes'!R79 -> 238690.98 | P5: =_xlfn.XLOOKUP(P4,Titres[Action],Titres[Variation du jour ($)]) -> 383.94
D6: Gain (%) | E6: =SUMIF(Titres[Compte],"Marge (CAD)",Titres[Gain non réalisé ($)])/SUMIF(Titres[Compte],"Marge (CAD)",Titres[Coût total]) -> 0.51953973 | G6: Gain (%) | J6: =J5/J3 -> 0.35225807 | P6: =_xlfn.XLOOKUP(P4,Titres[Action],Titres[Variation du jour (%)]) -> 0.019260492
D7: Revenu annuel anticipé | E7: =SUMIF(Titres[Compte],"Marge (CAD)",Titres[Revenu annuel anticipé]) -> 5793.84 | G7: Variation du jour ($) | J7: ='Titre et dividendes'!P79 -> -4389.715 | N7: -1 | O7: Perdant : | P7: =_xlfn.XLOOKUP(MIN(Titres[Variation du jour ($)]),Titres[Variation du jour ($)],Titres[Action]) -> #VALUE!
D8: Rendement | E8: =E7/E4 -> 0.022842607 | G8: Variation du jour (%) | J8: ='Titre et dividendes'!Q79 -> -0.0069525311 | P8: =_xlfn.XLOOKUP(P7,Titres[Action],Titres[Variation du jour ($)]) -> -1957
D9: Liquidité | E9: 0 | P9: =_xlfn.XLOOKUP(P7,Titres[Action],Titres[Variation du jour (%)]) -> -0.014021236
G10: #VALUE!
D11: Marge (US) | G11: Prix | I11: {=_FV(G10,"Prix")} -> 33808.3
D12: Valeur au marché | E12: =Ressources!I3*SUMIF(Titres[Compte],"Marge (USD)",Titres[Valeur au marché ($ local)]) -> 8747.864 | G12: Variation du jour ($) | I12: {=I11-_FV(G10,"Clôture précédente",TRUE)} -> -551.73
D13: Gain ($) | E13: =Ressources!I3*SUMIF(Titres[Compte],"Marge (USD)",Titres[Gain non réalisé ($)]) -> -213.096 | G13: Variation du jour (%) | I13: =I12/(I11-I12) -> -0.01605732
D14: Gain (%) | E14: =SUMIF(Titres[Compte],"Marge (USD)",Titres[Gain non réalisé ($)])/SUMIF(Titres[Compte],"Marge (USD)",Titres[Coût total]) -> -0.023780488
D15: Revenu annuel anticipé | E15: =SUMIF(Titres[Compte],"Marge (USD)",Titres[Revenu annuel anticipé]) -> 324 | G15: #VALUE!
D16: Rendement | E16: =E15/E12 -> 0.037037613 | G16: Prix | I16: {=_FV(G15,"Prix")} -> 7064.01
D17: Liquidité | E17: =Ressources!I3*-3144.92 -> -4295.9607 | G17: Variation du jour ($) | I17: {=I16-_FV(G15,"Clôture précédente",TRUE)} -> -45.13
G18: Variation du jour (%) | I18: =I17/(I16-I17) -> -0.0063481659
D19: CELI
D20: Valeur au marché | E20: =SUMIF(Titres[Compte],"CELI (CAD)",Titres[Valeur au marché ($ local)]) -> 262273.61 | G20: Dividende annuel estimé | I20: Dividende mensuel moyen | K20: ="Dividendes "&RIGHT(M20,4)-1 -> Dividendes 2025 | M20: Dividendes 2026
D21: Gain ($) | E21: =SUMIF(Titres[Compte],"CELI (CAD)",Titres[Gain non réalisé ($)]) -> 112596.91 | G21: =Titres[[#Totals],[Revenu annuel anticipé]] -> 17184.78 | I21: =G21/12 -> 1432.065 | K21: =SUMIF('Titre et dividendes'!$AB$5:$XFD$5,_xlfn.CONCAT("*",RIGHT(M20,4)-1),'Titre et dividendes'!$AB$79:$XFD$79) -> 13549.22 | M21: =SUMIF('Titre et dividendes'!$AB$5:$XFD$5,_xlfn.CONCAT("*",RIGHT(M20,4)),'Titre et dividendes'!$AB$79:$XFD$79) -> 2910.24
D22: Gain (%) | E22: =SUMIF(Titres[Compte],"CELI (CAD)",Titres[Gain non réalisé ($)])/SUMIF(Titres[Compte],"CELI (CAD)",Titres[Coût total]) -> 0.75226749
D23: Revenu annuel anticipé | E23: =SUMIF(Titres[Compte],"CELI (CAD)",Titres[Revenu annuel anticipé]) -> 8092.58 | M23: ="MaJ de "&LOOKUP("zz",'Titre et dividendes'!5:5) -> MaJ de Février 2026
D24: Rendement | E24: =E23/E20 -> 0.030855487 | G24: Projections de mon portefeuille
D25: Liquidité | E25: 1386.72 | G25: Réinvestissement | H25: Dividendes mensuels | J25: Dividendes à venir | L25: Valeur du portefeuille
G26: ="Dans 5 ans ("&YEAR(TODAY())-1984+5&" ans)" -> Dans 5 ans (47 ans) | H26: =IF($G$25="Réinvestissement",_xlfn.XLOOKUP(DATE(YEAR(TODAY())+5,MONTH(TODAY()),1),Projection!$F$12:$F$503,Projection!$M$12:$M$503),_xlfn.XLOOKUP(DATE(YEAR(TODAY())+5,MONTH(TODAY()),1),Projection!$F$12:$F$503,Projection!$L$12:$L$503)) -> 3034.9346 | J26: =IF($G$25="Réinvestissement",_xlfn.XLOOKUP(DATE(YEAR(TODAY())+5,MONTH(TODAY()),1),Projection!$F$12:$F$503,Projection!$P$12:$P$503),_xlfn.XLOOKUP(DATE(YEAR(TODAY())+5,MONTH(TODAY()),1),Projection!$F$12:$F$503,Projection!$O$12:$O$503)) -> 151912.25 | L26: =IF($G$25="Réinvestissement",_xlfn.XLOOKUP(DATE(YEAR(TODAY())+5,MONTH(TODAY()),1),Projection!$F$12:$F$503,Projection!$S$12:$S$503),_xlfn.XLOOKUP(DATE(YEAR(TODAY())+5,MONTH(TODAY()),1),Projection!$F$12:$F$503,Projection!$R$12:$R$503)) -> 1093830.8
D27: REER | G27: ="Dans 10 ans ("&YEAR(TODAY())-1984+10&" ans)" -> Dans 10 ans (52 ans) | H27: =+IF($G$25="Réinvestissement",_xlfn.XLOOKUP(DATE(YEAR(TODAY())+10,MONTH(TODAY()),1),Projection!$F$12:$F$503,Projection!$M$12:$M$503),_xlfn.XLOOKUP(DATE(YEAR(TODAY())+10,MONTH(TODAY()),1),Projection!$F$12:$F$503,Projection!$L$12:$L$503)) -> 4292.9861 | J27: =IF($G$25="Réinvestissement",_xlfn.XLOOKUP(DATE(YEAR(TODAY())+10,MONTH(TODAY()),1),Projection!$F$12:$F$503,Projection!$P$12:$P$503),_xlfn.XLOOKUP(DATE(YEAR(TODAY())+10,MONTH(TODAY()),1),Projection!$F$12:$F$503,Projection!$O$12:$O$503)) -> 371315.15 | L27: =IF($G$25="Réinvestissement",_xlfn.XLOOKUP(DATE(YEAR(TODAY())+10,MONTH(TODAY()),1),Projection!$F$12:$F$503,Projection!$S$12:$S$503),_xlfn.XLOOKUP(DATE(YEAR(TODAY())+10,MONTH(TODAY()),1),Projection!$F$12:$F$503,Projection!$R$12:$R$503)) -> 1626476.9
D28: Valeur au marché | E28: =SUMIF(Titres[Compte],"REER (USD)",Titres[Valeur au marché (CAD)]) -> 142985.51 | G28: ="Dans 15 ans ("&YEAR(TODAY())-1984+15&" ans)" -> Dans 15 ans (57 ans) | H28: =+IF($G$25="Réinvestissement",_xlfn.XLOOKUP(DATE(YEAR(TODAY())+15,MONTH(TODAY()),1),Projection!$F$12:$F$503,Projection!$M$12:$M$503),_xlfn.XLOOKUP(DATE(YEAR(TODAY())+15,MONTH(TODAY()),1),Projection!$F$12:$F$503,Projection!$L$12:$L$503)) -> 5777.948 | J28: =IF($G$25="Réinvestissement",_xlfn.XLOOKUP(DATE(YEAR(TODAY())+15,MONTH(TODAY()),1),Projection!$F$12:$F$503,Projection!$P$12:$P$503),_xlfn.XLOOKUP(DATE(YEAR(TODAY())+15,MONTH(TODAY()),1),Projection!$F$12:$F$503,Projection!$O$12:$O$503)) -> 672979.58 | L28: =IF($G$25="Réinvestissement",_xlfn.XLOOKUP(DATE(YEAR(TODAY())+15,MONTH(TODAY()),1),Projection!$F$12:$F$503,Projection!$S$12:$S$503),_xlfn.XLOOKUP(DATE(YEAR(TODAY())+15,MONTH(TODAY()),1),Projection!$F$12:$F$503,Projection!$R$12:$R$503)) -> 2301175.2
D29: Gain ($) | E29: =SUMIF(Titres[Compte],"REER (USD)",Titres[Gain non réalisé ($)]) -> 39528.415 | G29: ="Dans 20 ans ("&YEAR(TODAY())-1984+20&" ans)" -> Dans 20 ans (62 ans) | H29: =IF($G$25="Réinvestissement",_xlfn.XLOOKUP(DATE(YEAR(TODAY())+20,MONTH(TODAY()),1),Projection!$F$12:$F$503,Projection!$M$12:$M$503),_xlfn.XLOOKUP(DATE(YEAR(TODAY())+20,MONTH(TODAY()),1),Projection!$F$12:$F$503,Projection!$L$12:$L$503)) -> 7519.3 | J29: =IF($G$25="Réinvestissement",_xlfn.XLOOKUP(DATE(YEAR(TODAY())+20,MONTH(TODAY()),1),Projection!$F$12:$F$503,Projection!$P$12:$P$503),_xlfn.XLOOKUP(DATE(YEAR(TODAY())+20,MONTH(TODAY()),1),Projection!$F$12:$F$503,Projection!$O$12:$O$503)) -> 1071409.3 | L29: =IF($G$25="Réinvestissement",_xlfn.XLOOKUP(DATE(YEAR(TODAY())+20,MONTH(TODAY()),1),Projection!$F$12:$F$503,Projection!$S$12:$S$503),_xlfn.XLOOKUP(DATE(YEAR(TODAY())+20,MONTH(TODAY()),1),Projection!$F$12:$F$503,Projection!$R$12:$R$503)) -> 3148046
B30: Nb de titres | D30: Gain (%) | E30: =SUMIF(Titres[Compte],"REER (USD)",Titres[Gain non réalisé ($)])/SUMIF(Titres[Compte],"REER (USD)",Titres[Coût total]) -> 0.6067648 | G30: ="Dans 25 ans ("&YEAR(TODAY())-1984+25&" ans)" -> Dans 25 ans (67 ans) | H30: =IF($G$25="Réinvestissement",_xlfn.XLOOKUP(DATE(YEAR(TODAY())+25,MONTH(TODAY()),1),Projection!$F$12:$F$503,Projection!$M$12:$M$503),_xlfn.XLOOKUP(DATE(YEAR(TODAY())+25,MONTH(TODAY()),1),Projection!$F$12:$F$503,Projection!$L$12:$L$503)) -> 9548.5011 | J30: =IF($G$25="Réinvestissement",_xlfn.XLOOKUP(DATE(YEAR(TODAY())+25,MONTH(TODAY()),1),Projection!$F$12:$F$503,Projection!$P$12:$P$503),_xlfn.XLOOKUP(DATE(YEAR(TODAY())+25,MONTH(TODAY()),1),Projection!$F$12:$F$503,Projection!$O$12:$O$503)) -> 1582937.4 | L30: =IF($G$25="Réinvestissement",_xlfn.XLOOKUP(DATE(YEAR(TODAY())+25,MONTH(TODAY()),1),Projection!$F$12:$F$503,Projection!$S$12:$S$503),_xlfn.XLOOKUP(DATE(YEAR(TODAY())+25,MONTH(TODAY()),1),Projection!$F$12:$F$503,Projection!$R$12:$R$503)) -> 4202294.5
B31: =Titres[[#Totals],[Symbole]] -> 73 | D31: Revenu annuel anticipé | E31: =SUMIF(Titres[Compte],"REER (USD)",Titres[Revenu annuel anticipé]) -> 2974.36 | G31: ="Dans 30 ans ("&YEAR(TODAY())-1984+30&" ans)" -> Dans 30 ans (72 ans) | H31: =IF($G$25="Réinvestissement",_xlfn.XLOOKUP(DATE(YEAR(TODAY())+30,MONTH(TODAY()),1),Projection!$F$12:$F$503,Projection!$M$12:$M$503),_xlfn.XLOOKUP(DATE(YEAR(TODAY())+30,MONTH(TODAY()),1),Projection!$F$12:$F$503,Projection!$L$12:$L$503)) -> 11898.93 | J31: =IF($G$25="Réinvestissement",_xlfn.XLOOKUP(DATE(YEAR(TODAY())+30,MONTH(TODAY()),1),Projection!$F$12:$F$503,Projection!$P$12:$P$503),_xlfn.XLOOKUP(DATE(YEAR(TODAY())+30,MONTH(TODAY()),1),Projection!$F$12:$F$503,Projection!$O$12:$O$503)) -> 2225843.4 | L31: =IF($G$25="Réinvestissement",_xlfn.XLOOKUP(DATE(YEAR(TODAY())+30,MONTH(TODAY()),1),Projection!$F$12:$F$503,Projection!$S$12:$S$503),_xlfn.XLOOKUP(DATE(YEAR(TODAY())+30,MONTH(TODAY()),1),Projection!$F$12:$F$503,Projection!$R$12:$R$503)) -> 5504866.9
D32: Rendement | E32: =E31/E28 -> 0.020801828 | G32: ="À "&H36&" ans (Retraite)" -> À 55 ans (Retraite) | H32: =IF($G$25="Réinvestissement",_xlfn.XLOOKUP(DATE(1984+H36,6,1),Projection!$F$12:$F$503,Projection!$M$12:$M$503),_xlfn.XLOOKUP(DATE(1984+H36,6,1),Projection!$F$12:$F$503,Projection!$L$12:$L$503)) -> 5205.2948 | J32: =IF($G$25="Réinvestissement",_xlfn.XLOOKUP(DATE(1984+H36,6,1),Projection!$F$12:$F$503,Projection!$P$12:$P$503),_xlfn.XLOOKUP(DATE(1984+H36,6,1),Projection!$F$12:$F$503,Projection!$O$12:$O$503)) -> 551939.24 | L32: =IF($G$25="Réinvestissement",_xlfn.XLOOKUP(DATE(1984+H36,6,1),Projection!$F$12:$F$503,Projection!$S$12:$S$503),_xlfn.XLOOKUP(DATE(1984+H36,6,1),Projection!$F$12:$F$503,Projection!$R$12:$R$503)) -> 2035491.3
D33: Liquidité | E33: =Ressources!I3*724.4 -> 989.5304
G34: Planification du revenu à la retraite
D35: CRCD | G35: Objectifs | I35: RRMD | K35: Placements | M35: Total
D36: Valeur au marché | E36: =Tableau4[[#Totals],[Valeur marchande]] -> 11873.511 | G36: Âge de la retraite | H36: 55 | I36: =_xlfn.XLOOKUP(H36,RRMD!B:B,RRMD!G:G) -> 46454.641 | K36: =(IF($G$25="Réinvestissement",_xlfn.XLOOKUP(DATE(1984+H36,6,1),Projection!$F$12:$F$503,Projection!$M$12:$M$503),_xlfn.XLOOKUP(DATE(1984+H36,6,1),Projection!$F$12:$F$503,Projection!$L$12:$L$503)))*12 -> 62463.538 | M36: =I36+K36 -> 108918.18
B37: Liquidités | D37: Gain ($) | E37: =Tableau4[[#Totals],[Gain ($)]] -> 873.51599 | G37: % du salaire actuel | H37: 0.7
B38: =E9+E17+E25+E33 -> -1919.7103 | D38: Gain (%) | E38: =Tableau4[[#Totals],[Gain (%)]] -> 0.079410579 | G38: =H37*Ressources!G2 -> 90380.843 | H38: ↙ | M38: =M36/G38 -> 1.2051025
F44: TSX : | G44: {=TRANSPOSE(_xlfn.STOCKHISTORY(G10,TODAY()-365,TODAY(),0,0,1))} -> 24008.86 | H44: 24305.98 | I44: 24472.68 | J44: 24727.53 | K44: 24710.51 | L44: 24798.59 | M44: 24874.48 | N44: 24841.68 | O44: 24795.55 | P44: 25031.51 | Q44: 24953.52 | R44: 24974.72 | S44: 25161.18 | T44: 25254.06 | U44: 25357.74 | V44: 25532.18 | W44: 25616.86 | X44: 25692.45 | Y44: 25897.48 | Z44: 25971.93 | AA44: 26055.63 | AB44: 25839.17 | AC44: 25854.01 | AD44: 25879.95 | AE44: 26073.13 | AF44: 26269 | AG44: 26283.45 | AH44: 26210.56 | AI44: 26175.05 | AJ44: 26388.96 | AK44: 26426.64 | AL44: 26329 | AM44: 26342.29 | AN44: 26429.13 | AO44: 26375.8 | AP44: 26426.31 | AQ44: 26524.16 | AR44: 26615.75 | AS44: 26504.35 | AT44: 26568.61 | AU44: 26541.39 | AV44: 26559.85 | AW44: 26506 | AX44: 26497.57 | AY44: 26609.36 | AZ44: 26718.62 | BA44: 26566.32 | BB44: 26751.95 | BC44: 26692.32 | BD44: 26857.11 | BE44: 26869.66 | BF44: 27034.26 | BG44: 27036.16 | BH44: 27020.28 | BI44: 26903.57 | BJ44: 26972.32 | BK44: 27082.3 | BL44: 27023.25 | BM44: 27198.85 | BN44: 27054.14 | BO44: 27152.97 | BP44: 27386.93 | BQ44: 27314.01 | BR44: 27317 | BS44: 27364.43 | BT44: 27416.41 | BU44: 27372.26 | BV44: 27494.35 | BW44: 27405.42 | BX44: 27539.88 | BY44: 27369.96 | BZ44: 27259.78 | CA44: 27020.43 | CB44: 27570.08 | CC44: 27920.87 | CD44: 27761.27 | CE44: 27758.68 | CF44: 27775.23 | CG44: 27921.26 | CH44: 27993.43 | CI44: 27915.99 | CJ44: 27905.49 | CK44: 27922.85 | CL44: 27823.88 | CM44: 27878.76 | CN44: 28055.43 | CO44: 28333.13 | CP44: 28169.94 | CQ44: 28339.88 | CR44: 28433 | CS44: 28434.8 | CT44: 28564.45 | CU44: 28615.62 | CV44: 28751.36 | CW44: 28915.89 | CX44: 29050.63 | CY44: 29027.73 | CZ44: 29063.01 | DA44: 29179.39 | DB44: 29407.89 | DC44: 29283.82 | DD44: 29431.02 | DE44: 29315.23 | DF44: 29321.66 | DG44: 29453.53 | DH44: 29768.36 | DI44: 29958.98 | DJ44: 29815.63 | DK44: 29756.95 | DL44: 29731.98 | DM44: 29761.28 | DN44: 29971.91 | DO44: 30022.81 | DP44: 30107.67 | DQ44: 30160.59 | DR44: 30471.68 | DS44: 30531.88 | DT44: 30351.72 | DU44: 30501.99 | DV44: 30269.98 | DW44: 29850.89 | DX44: 30353.61 | DY44: 30637.12 | DZ44: 30458.8 | EA44: 30108.48 | EB44: 30416.44 | EC44: 29888.82 | ED44: 29982.98 | EE44: 30186.28 | EF44: 30353.07 | EG44: 30275.76 | EH44: 30419.68 | EI44: 30144.78 | EJ44: 30178.98 | EK44: 30260.74 | EL44: 30275.06 | EM44: 29777.82 | EN44: 30103.48 | EO44: 29868.59 | EP44: 29912.19 | EQ44: 30316.63 | ER44: 30409.25 | ES44: 30827.58 | ET44: 30253.64 | EU44: 30326.46 | EV44: 30076.21 | EW44: 30036.46 | EX44: 30278.41 | EY44: 29906.55 | EZ44: 30160.65 | FA44: 30604.35 | FB44: 30900.65 | FC44: 31180.25 | FD44: 31196.71 | FE44: 31382.78 | FF44: 31101.78 | FG44: 31049.28 | FH44: 31160.54 | FI44: 31477.57 | FJ44: 31311.41 | FK44: 31169.97 | FL44: 31244.37 | FM44: 31490.85 | FN44: 31660.73 | FO44: 31527.39 | FP44: 31483.44 | FQ44: 31263.93 | FR44: 31250.02 | FS44: 31440.85 | FT44: 31755.77 | FU44: 32000.1 | FV44: 32058.73 | FW44: 31999.76 | FX44: 31896.59 | FY44: 31866.26 | FZ44: 31712.76 | GA44: 31883.37 | GB44: 32219.95 | GC44: 32407.02 | GD44: 32135.49 | GE44: 32378.64 | GF44: 32612.93 | GG44: 32874.7 | GH44: 32870.36 | GI44: 32916.47 | GJ44: 33028.92 | GK44: 33040.55 | GL44: 33090.96 | GM44: 32750.28 | GN44: 32851.53 | GO44: 33002.7 | GP44: 33144.98 | GQ44: 33093.32 | GR44: 33096.4 | GS44: 33176.07 | GT44: 33016.13 | GU44: 31923.52 | GV44: 32183.88 | GW44: 32388.6 | GX44: 32571.55 | GY44: 31994.6 | GZ44: 32470.98 | HA44: 33023.32 | HB44: 33256.83 | HC44: 33254.19 | HD44: 32465.28 | HE44: 33073.71 | HF44: 32896.55 | HG44: 33389.73 | HH44: 33594.98 | HI44: 33817.51 | HJ44: 33776.5 | HK44: 33970.38 | HL44: 34127.33 | HM44: 34501.96 | HN44: 34339.99 | HO44: 34541.27 | HP44: 33784.94 | HQ44: 33942.86 | HR44: 33609.97 | HS44: 33083.72 | HT44: 33189.32 | HU44: 33270.65 | HV44: 33119.83 | HW44: 32840.6 | HX44: 32541.93 | HY44: 32876.65 | HZ44: 32929.09 | IA44: 32312.67 | IB44: 31854.98 | IC44: 31317.41 | ID44: 31883.81 | IE44: 31941.59 | IF44: 32382.6 | IG44: 31887.52 | IH44: 31960.65 | II44: 31934.94 | IJ44: 32768.04 | IK44: 32957.95 | IL44: 33108.22 | IM44: #N/A | IN44: 33181.97 | IO44: 33237.52 | IP44: 33620.57 | IQ44: 33477.71 | IR44: 33695.76 | IS44: 33879.24 | IT44: 34102.36 | IU44: 34155.99 | IV44: 34052.23 | IW44: 34346.29 | IX44: 34360.03
F45: S&P : | G45: {=TRANSPOSE(_xlfn.STOCKHISTORY(G15,TODAY()-365,TODAY(),0,0,1))} -> 5158.2 | H45: 5287.76 | I45: 5375.86 | J45: 5484.77 | K45: 5525.21 | L45: 5528.75 | M45: 5560.83 | N45: 5569.06 | O45: 5604.14 | P45: 5686.67 | Q45: 5650.38 | R45: 5606.91 | S45: 5631.28 | T45: 5663.94 | U45: 5659.91 | V45: 5844.19 | W45: 5886.55 | X45: 5892.58 | Y45: 5916.93 | Z45: 5958.38 | AA45: 5963.6 | AB45: 5940.46 | AC45: 5844.61 | AD45: 5842.01 | AE45: 5802.82 | AF45: 5921.54 | AG45: 5888.55 | AH45: 5912.17 | AI45: 5911.69 | AJ45: 5935.94 | AK45: 5970.37 | AL45: 5970.81 | AM45: 5939.3 | AN45: 6000.36 | AO45: 6005.88 | AP45: 6038.81 | AQ45: 6022.24 | AR45: 6045.26 | AS45: 5976.97 | AT45: 6033.11 | AU45: 5982.72 | AV45: 5980.87 | AW45: 5967.84 | AX45: 6025.17 | AY45: 6092.18 | AZ45: 6092.16 | BA45: 6141.02 | BB45: 6173.07 | BC45: 6204.95 | BD45: 6198.01 | BE45: 6227.42 | BF45: 6279.35 | BG45: 6229.98 | BH45: 6225.52 | BI45: 6263.26 | BJ45: 6280.46 | BK45: 6259.75 | BL45: 6268.56 | BM45: 6243.76 | BN45: 6263.7 | BO45: 6297.36 | BP45: 6296.79 | BQ45: 6305.6 | BR45: 6309.62 | BS45: 6358.91 | BT45: 6363.35 | BU45: 6388.64 | BV45: 6389.77 | BW45: 6370.86 | BX45: 6362.9 | BY45: 6339.39 | BZ45: 6238.01 | CA45: 6329.94 | CB45: 6299.19 | CC45: 6345.06 | CD45: 6340 | CE45: 6389.45 | CF45: 6373.45 | CG45: 6445.76 | CH45: 6466.58 | CI45: 6468.54 | CJ45: 6449.8 | CK45: 6449.15 | CL45: 6411.37 | CM45: 6395.78 | CN45: 6370.17 | CO45: 6466.91 | CP45: 6439.32 | CQ45: 6465.94 | CR45: 6481.4 | CS45: 6501.86 | CT45: 6460.26 | CU45: 6415.54 | CV45: 6448.26 | CW45: 6502.08 | CX45: 6481.5 | CY45: 6495.15 | CZ45: 6512.61 | DA45: 6532.04 | DB45: 6587.47 | DC45: 6584.29 | DD45: 6615.28 | DE45: 6606.76 | DF45: 6600.35 | DG45: 6631.96 | DH45: 6664.36 | DI45: 6693.75 | DJ45: 6656.92 | DK45: 6637.97 | DL45: 6604.72 | DM45: 6643.7 | DN45: 6661.21 | DO45: 6688.46 | DP45: 6711.2 | DQ45: 6715.35 | DR45: 6715.79 | DS45: 6740.28 | DT45: 6714.59 | DU45: 6753.72 | DV45: 6735.11 | DW45: 6552.51 | DX45: 6654.72 | DY45: 6644.31 | DZ45: 6671.06 | EA45: 6629.07 | EB45: 6664.01 | EC45: 6735.13 | ED45: 6735.35 | EE45: 6699.4 | EF45: 6738.44 | EG45: 6791.69 | EH45: 6875.16 | EI45: 6890.89 | EJ45: 6890.59 | EK45: 6822.34 | EL45: 6840.2 | EM45: 6851.97 | EN45: 6771.55 | EO45: 6796.29 | EP45: 6720.32 | EQ45: 6728.8 | ER45: 6832.43 | ES45: 6846.61 | ET45: 6850.92 | EU45: 6737.49 | EV45: 6734.11 | EW45: 6672.41 | EX45: 6617.32 | EY45: 6642.16 | EZ45: 6538.76 | FA45: 6602.99 | FB45: 6705.12 | FC45: 6765.88 | FD45: 6812.61 | FE45: 6849.09 | FF45: 6812.63 | FG45: 6829.37 | FH45: 6849.72 | FI45: 6857.12 | FJ45: 6870.4 | FK45: 6846.51 | FL45: 6840.51 | FM45: 6886.68 | FN45: 6901 | FO45: 6827.41 | FP45: 6816.51 | FQ45: 6800.26 | FR45: 6721.43 | FS45: 6774.76 | FT45: 6834.5 | FU45: 6878.49 | FV45: 6909.79 | FW45: 6932.05 | FX45: 6929.94 | FY45: 6905.74 | FZ45: 6896.24 | GA45: 6845.5 | GB45: 6858.47 | GC45: 6902.05 | GD45: 6944.82 | GE45: 6920.93 | GF45: 6921.46 | GG45: 6966.28 | GH45: 6977.27 | GI45: 6963.74 | GJ45: 6926.6 | GK45: 6944.47 | GL45: 6940.01 | GM45: 6796.86 | GN45: 6875.62 | GO45: 6913.35 | GP45: 6915.61 | GQ45: 6950.23 | GR45: 6978.6 | GS45: 6978.03 | GT45: 6969.01 | GU45: 6939.03 | GV45: 6976.44 | GW45: 6917.81 | GX45: 6882.72 | GY45: 6798.4 | GZ45: 6932.3 | HA45: 6964.82 | HB45: 6941.81 | HC45: 6941.47 | HD45: 6832.76 | HE45: 6836.17 | HF45: 6843.22 | HG45: 6881.31 | HH45: 6861.89 | HI45: 6909.51 | HJ45: 6837.75 | HK45: 6890.07 | HL45: 6946.13 | HM45: 6908.86 | HN45: 6878.88 | HO45: 6881.62 | HP45: 6816.63 | HQ45: 6869.5 | HR45: 6830.71 | HS45: 6740.02 | HT45: 6795.99 | HU45: 6781.48 | HV45: 6775.8 | HW45: 6672.62 | HX45: 6632.19 | HY45: 6699.38 | HZ45: 6716.09 | IA45: 6624.7 | IB45: 6606.49 | IC45: 6506.48 | ID45: 6581 | IE45: 6556.37 | IF45: 6591.9 | IG45: 6477.16 | IH45: 6368.85 | II45: 6343.72 | IJ45: 6528.52 | IK45: 6575.32 | IL45: 6582.69 | IM45: 6611.83 | IN45: 6616.85 | IO45: 6782.81 | IP45: 6824.66 | IQ45: 6816.89 | IR45: 6886.24 | IS45: 6967.38 | IT45: 7022.95 | IU45: 7041.28 | IV45: 7126.06 | IW45: 7109.14

Sheet Titre et dividendes
B1: Liste de suivi des titres et des dividendes mensuels
B5: # de compte | C5: Compte | D5: Action | E5: Symbole | F5: Bourse | G5: Industrie | H5: Catégorie | I5: Devise | J5: Nb d'actions | K5: Coût moyen | L5: Coût total | M5: Prix actuel | N5: Valeur au marché ($ local) | O5: Valeur au marché (CAD) | P5: Variation du jour ($) | Q5: Variation du jour (%) | R5: Gain non réalisé ($) | S5: Gain non réalisé (%) | T5: Dividende trimestriel | U5: Dividende annuel | V5: Revenu annuel anticipé | W5: Rendement des dividendes | X5: $ de dividendes par $ investi | Y5: Croissance (années) | Z5: Retour total | AA5: Total - dividendes reçus | AB5: Janvier 2019 | AC5: Février 2019 | AD5: Mars 2019 | AE5: Avril 2019 | AF5: Mai 2019 | AG5: Juin 2019 | AH5: Juillet 2019 | AI5: Août 2019 | AJ5: Septembre 2019 | AK5: Octobre 2019 | AL5: Novembre 2019 | AM5: Décembre 2019 | AN5: Janvier 2020 | AO5: Février 2020 | AP5: Mars 2020 | AQ5: Avril 2020 | AR5: Mai 2020 | AS5: Juin 2020 | AT5: Juillet 2020 | AU5: Août 2020 | AV5: Septembre 2020 | AW5: Octobre 2020 | AX5: Novembre 2020 | AY5: Décembre 2020 | AZ5: Janvier 2021 | BA5: Février 2021 | BB5: Mars 2021 | BC5: Avril 2021 | BD5: Mai 2021 | BE5: Juin 2021 | BF5: Juillet 2021 | BG5: Août 2021 | BH5: Septembre 2021 | BI5: Octobre 2021 | BJ5: Novembre 2021 | BK5: Décembre 2021 | BL5: Janvier 2022 | BM5: Février 2022 | BN5: Mars 2022 | BO5: Avril 2022 | BP5: Mai 2022 | BQ5: Juin 2022 | BR5: Juillet 2022 | BS5: Août 2022 | BT5: Septembre 2022 | BU5: Octobre 2022 | BV5: Novembre 2022 | BW5: Décembre 2022 | BX5: Janvier 2023 | BY5: Février 2023 | BZ5: Mars 2023 | CA5: Avril 2023 | CB5: Mai 2023 | CC5: .Juin 2023 | CD5: Juillet 2023 | CE5: Août 2023 | CF5: Septembre 2023 | CG5: Octobre 2023 | CH5: Novembre 2023 | CI5: Décembre 2023 | CJ5: Janvier 2024 | CK5: Février 2024 | CL5: Mars 2024 | CM5: Avril 2024 | CN5: Mai 2024 | CO5: Juin 2024 | CP5: Juillet 2024 | CQ5: Août 2024 | CR5: Septembre 2024 | CS5: Octobre 2024 | CT5: Novembre 2024 | CU5: Décembre 2024 | CV5: Janvier 2025 | CW5: Février 2025 | CX5: Mars 2025 | CY5: Avril 2025 | CZ5: Mai 2025 | DA5: Juin 2025 | DB5: Juillet 2025 | DC5: Août 2025 | DD5: Septembre 2025 | DE5: Octobre 2025 | DF5: Novembre 2025 | DG5: Décembre 2025 | DH5: Janvier 2026 | DI5: Février 2026
B6: =IF(C6="","",_xlfn.XLOOKUP(C6,Type_Compte,Num_Compte)) -> 20K6HU7 | C6: REER (USD) | D6: #VALUE! | E6: {=_FV(Titres[[#This Row],[Action]],"Code mnémonique",TRUE)} -> MMM | F6: {=_FV(D6,"Change")} -> New York Stock Exchange | G6: {=IFERROR(_FV(Titres[[#This Row],[Action]],"Industrie"),"")} -> Consumer Goods Conglomerates | H6: Actions américaines | I6: {=_FV(D6,"Devise")} -> USD | J6: 30 | K6: 89.96 | L6: =J6*K6 -> 2698.8 | M6: {=_FV(D6,"Prix")} -> 148.48 | N6: =J6*M6 -> 4454.4 | O6: =IF(Titres[[#This Row],[Devise]]="CAD",Titres[[#This Row],[Valeur au marché ($ local)]],Titres[[#This Row],[Valeur au marché ($ local)]]*Ressources!$I$3) -> 6084.7104 | P6: {=(Titres[[#This Row],[Prix actuel]]-_FV(Titres[[#This Row],[Action]],"Clôture précédente",TRUE))*Titres[[#This Row],[Nb d''actions]]} -> -87.6 | Q6: =Titres[[#This Row],[Variation du jour ($)]]/(Titres[[#This Row],[Valeur au marché ($ local)]]-Titres[[#This Row],[Variation du jour ($)]]) -> -0.019286658 | R6: =Titres[[#This Row],[Valeur au marché ($ local)]]-Titres[[#This Row],[Coût total]] -> 1755.6 | S6: =Titres[[#This Row],[Gain non réalisé ($)]]/Titres[[#This Row],[Coût total]] -> 0.65051134 | T6: 0.78 | U6: =4*Titres[[#This Row],[Dividende trimestriel]] -> 3.12 | V6: =Titres[[#This Row],[Dividende annuel]]*Titres[[#This Row],[Nb d''actions]] -> 93.6 | W6: =Titres[[#This Row],[Dividende annuel]]/Titres[[#This Row],[Prix actuel]] -> 0.021012931 | X6: =Titres[[#This Row],[Dividende annuel]]/Titres[[#This Row],[Coût moyen]] -> 0.034682081 | Y6: 64 | Z6: =(((Titres[[#This Row],[Valeur au marché ($ local)]]-Titres[[#This Row],[Coût total]])+Titres[[#This Row],[Total - dividendes reçus]])/Titres[[#This Row],[Coût total]]) -> 0.69979991 | AA6: =SUM(Titres[[#This Row],[Janvier 2019]:[Août 2024]]) -> 133.02 | CE6: =25.55-3.83 -> 21.72 | CI6: 45 | CL6: 45.3 | CO6: 21 | CR6: 21 | CU6: 21 | CX6: 21.9 | DA6: 21.9 | DD6: 21.9 | DG6: 21.9
B7: =IF(C7="","",_xlfn.XLOOKUP(C7,Type_Compte,Num_Compte)) -> 20K6HZ6 | C7: CELI (CAD) | D7: #VALUE! | E7: {=_FV(Titres[[#This Row],[Action]],"Code mnémonique",TRUE)} -> AQN | F7: {=_FV(D7,"Change")} -> Toronto Stock Exchange | G7: {=IFERROR(_FV(Titres[[#This Row],[Action]],"Industrie"),"")} -> Multiline Utilities | H7: Actions canadiennes | I7: {=_FV(D7,"Devise")} -> CAD | J7: 400 | K7: 11.48 | L7: =J7*K7 -> 4592 | M7: {=_FV(D7,"Prix")} -> 8.5 | N7: =J7*M7 -> 3400 | O7: =IF(Titres[[#This Row],[Devise]]="CAD",Titres[[#This Row],[Valeur au marché ($ local)]],Titres[[#This Row],[Valeur au marché ($ local)]]*Ressources!$I$3) -> 3400 | P7: {=(Titres[[#This Row],[Prix actuel]]-_FV(Titres[[#This Row],[Action]],"Clôture précédente",TRUE))*Titres[[#This Row],[Nb d''actions]]} -> -48 | Q7: =Titres[[#This Row],[Variation du jour ($)]]/(Titres[[#This Row],[Valeur au marché ($ local)]]-Titres[[#This Row],[Variation du jour ($)]]) -> -0.013921114 | R7: =Titres[[#This Row],[Valeur au marché ($ local)]]-Titres[[#This Row],[Coût total]] -> -1192 | S7: =Titres[[#This Row],[Gain non réalisé ($)]]/Titres[[#This Row],[Coût total]] -> -0.25958188 | T7: 0.092 | U7: =4*Titres[[#This Row],[Dividende trimestriel]] -> 0.368 | V7: =Titres[[#This Row],[Dividende annuel]]*Titres[[#This Row],[Nb d''actions]] -> 147.2 | W7: =Titres[[#This Row],[Dividende annuel]]/Titres[[#This Row],[Prix actuel]] -> 0.043294118 | X7: =Titres[[#This Row],[Dividende annuel]]/Titres[[#This Row],[Coût moyen]] -> 0.032055749 | Y7: 10 | Z7: =(((Titres[[#This Row],[Valeur au marché ($ local)]]-Titres[[#This Row],[Coût total]])+Titres[[#This Row],[Total - dividendes reçus]])/Titres[[#This Row],[Coût total]]) -> -0.080060976 | AA7: =SUM(Titres[[#This Row],[Janvier 2019]:[Août 2024]]) -> 824.36 | AH7: 34.38 | AK7: 35.69 | AN7: 35.31 | AQ7: 35.65 | AT7: 41.62 | AW7: 39.06 | AZ7: 38.36 | BC7: 37.22 | BF7: 39.78 | BI7: 40.54 | BL7: 40.36 | BO7: 41.06 | BR7: 44.56 | BU7: 43.93 | BX7: 46.31 | CA7: 28.4 | CD7: 27.6 | CG7: 27.74 | CJ7: 28.44 | CM7: 58.74 | CP7: 59.61 | CS7: 35.72 | CV7: 36.02 | CY7: 37.36 | DB7: 35.87 | DE7: 35.74 | DH7: 36.71
B8: =IF(C8="","",_xlfn.XLOOKUP(C8,Type_Compte,Num_Compte)) -> 20K6HZ6 | C8: CELI (CAD) | D8: #VALUE! | E8: {=_FV(Titres[[#This Row],[Action]],"Code mnémonique",TRUE)} -> ALA | F8: {=_FV(D8,"Change")} -> Toronto Stock Exchange | G8: {=IFERROR(_FV(Titres[[#This Row],[Action]],"Industrie"),"")} -> Natural Gas Utilities | H8: Actions canadiennes | I8: {=_FV(D8,"Devise")} -> CAD | J8: 90 | K8: 29.14 | L8: =J8*K8 -> 2622.6 | M8: {=_FV(D8,"Prix")} -> 48.82 | N8: =J8*M8 -> 4393.8 | O8: =IF(Titres[[#This Row],[Devise]]="CAD",Titres[[#This Row],[Valeur au marché ($ local)]],Titres[[#This Row],[Valeur au marché ($ local)]]*Ressources!$I$3) -> 4393.8 | P8: {=(Titres[[#This Row],[Prix actuel]]-_FV(Titres[[#This Row],[Action]],"Clôture précédente",TRUE))*Titres[[#This Row],[Nb d''actions]]} -> -37.8 | Q8: =Titres[[#This Row],[Variation du jour ($)]]/(Titres[[#This Row],[Valeur au marché ($ local)]]-Titres[[#This Row],[Variation du jour ($)]]) -> -0.0085296507 | R8: =Titres[[#This Row],[Valeur au marché ($ local)]]-Titres[[#This Row],[Coût total]] -> 1771.2 | S8: =Titres[[#This Row],[Gain non réalisé ($)]]/Titres[[#This Row],[Coût total]] -> 0.67536033 | T8: 0.334 | U8: =4*Titres[[#This Row],[Dividende trimestriel]] -> 1.336 | V8: =Titres[[#This Row],[Dividende annuel]]*Titres[[#This Row],[Nb d''actions]] -> 120.24 | W8: =Titres[[#This Row],[Dividende annuel]]/Titres[[#This Row],[Prix actuel]] -> 0.027365834 | X8: =Titres[[#This Row],[Dividende annuel]]/Titres[[#This Row],[Coût moyen]] -> 0.045847632 | Y8: 0 | Z8: =(((Titres[[#This Row],[Valeur au marché ($ local)]]-Titres[[#This Row],[Coût total]])+Titres[[#This Row],[Total - dividendes reçus]])/Titres[[#This Row],[Coût total]]) -> 0.86405094 | AA8: =SUM(Titres[[#This Row],[Janvier 2019]:[Août 2024]]) -> 494.86 | AB8: 7.2 | AC8: 7.2 | AD8: 7.2 | AE8: 7.2 | AF8: 7.2 | AG8: 7.2 | AH8: 7.2 | AI8: 7.2 | AJ8: 7.2 | AK8: 7.2 | AL8: 7.2 | AM8: 7.2 | AN8: 7.2 | AO8: 7.2 | AP8: 7.2 | AQ8: 7.2 | AR8: 7.2 | AS8: 7.2 | AT8: 7.2 | AU8: 7.2 | AV8: 7.2 | AW8: 7.2 | AX8: 7.2 | AY8: 7.2 | AZ8: 7.5 | BA8: 7.5 | BB8: 7.5 | BC8: 7.5 | BD8: 7.5 | BE8: 7.5 | BF8: 7.5 | BG8: 7.5 | BH8: 7.5 | BI8: 7.5 | BJ8: 7.5 | BK8: 15 | BN8: 23.85 | BQ8: 23.85 | BT8: 23.85 | BW8: 23.85 | CC8: 25.2 | CF8: 25.2 | CI8: 25.2 | CL8: 26.78 | CP8: 26.78 | CR8: 26.78 | CU8: 26.78 | CX8: 28.35 | DA8: 28.35 | DD8: 28.35 | DG8: 28.35
B9: =IF(C9="","",_xlfn.XLOOKUP(C9,Type_Compte,Num_Compte)) -> 20K6HU7 | C9: REER (USD) | D9: #VALUE! | E9: {=_FV(Titres[[#This Row],[Action]],"Code mnémonique",TRUE)} -> MO | F9: {=_FV(D9,"Change")} -> New York Stock Exchange | G9: {=IFERROR(_FV(Titres[[#This Row],[Action]],"Industrie"),"")} -> Food & Tobacco | H9: Actions américaines | I9: {=_FV(D9,"Devise")} -> USD | J9: 65 | K9: 50.26 | L9: =J9*K9 -> 3266.9 | M9: {=_FV(D9,"Prix")} -> 64.67 | N9: =J9*M9 -> 4203.55 | O9: =IF(Titres[[#This Row],[Devise]]="CAD",Titres[[#This Row],[Valeur au marché ($ local)]],Titres[[#This Row],[Valeur au marché ($ local)]]*Ressources!$I$3) -> 5742.0493 | P9: {=(Titres[[#This Row],[Prix actuel]]-_FV(Titres[[#This Row],[Action]],"Clôture précédente",TRUE))*Titres[[#This Row],[Nb d''actions]]} -> 3.9 | Q9: =Titres[[#This Row],[Variation du jour ($)]]/(Titres[[#This Row],[Valeur au marché ($ local)]]-Titres[[#This Row],[Variation du jour ($)]]) -> 0.00092864882 | R9: =Titres[[#This Row],[Valeur au marché ($ local)]]-Titres[[#This Row],[Coût total]] -> 936.65 | S9: =Titres[[#This Row],[Gain non réalisé ($)]]/Titres[[#This Row],[Coût total]] -> 0.28670911 | T9: 1.06 | U9: =4*Titres[[#This Row],[Dividende trimestriel]] -> 4.24 | V9: =Titres[[#This Row],[Dividende annuel]]*Titres[[#This Row],[Nb d''actions]] -> 275.6 | W9: =Titres[[#This Row],[Dividende annuel]]/Titres[[#This Row],[Prix actuel]] -> 0.065563631 | X9: =Titres[[#This Row],[Dividende annuel]]/Titres[[#This Row],[Coût moyen]] -> 0.084361321 | Y9: 53 | Z9: =(((Titres[[#This Row],[Valeur au marché ($ local)]]-Titres[[#This Row],[Coût total]])+Titres[[#This Row],[Total - dividendes reçus]])/Titres[[#This Row],[Coût total]]) -> 0.61301234 | AA9: =SUM(Titres[[#This Row],[Janvier 2019]:[Août 2024]]) -> 1066 | AQ9: 54.6 | AT9: 54.6 | AW9: 55.9 | AZ9: 55.9 | BC9: 55.9 | BF9: 55.9 | BI9: 58.5 | BL9: 58.5 | BO9: 58.5 | BR9: 58.5 | BU9: 61.1 | BX9: 61.1 | CA9: 61.1 | CD9: 61.1 | CG9: 63.7 | CJ9: 63.7 | CM9: 63.7 | CP9: 63.7 | CS9: 66.3 | CV9: 66.3 | CY9: 66.3 | DB9: 66.3 | DE9: 68.9 | DH9: 68.9
B10: =IF(C10="","",_xlfn.XLOOKUP(C10,Type_Compte,Num_Compte)) -> 20K6HU7 | C10: REER (USD) | D10: #VALUE! | E10: {=_FV(Titres[[#This Row],[Action]],"Code mnémonique",TRUE)} -> T | F10: {=_FV(D10,"Change")} -> New York Stock Exchange | G10: {=IFERROR(_FV(Titres[[#This Row],[Action]],"Industrie"),"")} -> Telecommunications Services | H10: Actions américaines | I10: {=_FV(D10,"Devise")} -> USD | J10: 124 | K10: 24.44 | L10: =J10*K10 -> 3030.56 | M10: {=_FV(D10,"Prix")} -> 25.88 | N10: =J10*M10 -> 3209.12 | O10: =IF(Titres[[#This Row],[Devise]]="CAD",Titres[[#This Row],[Valeur au marché ($ local)]],Titres[[#This Row],[Valeur au marché ($ local)]]*Ressources!$I$3) -> 4383.6579 | P10: {=(Titres[[#This Row],[Prix actuel]]-_FV(Titres[[#This Row],[Action]],"Clôture précédente",TRUE))*Titres[[#This Row],[Nb d''actions]]} -> -37.2 | Q10: =Titres[[#This Row],[Variation du jour ($)]]/(Titres[[#This Row],[Valeur au marché ($ local)]]-Titres[[#This Row],[Variation du jour ($)]]) -> -0.011459129 | R10: =Titres[[#This Row],[Valeur au marché ($ local)]]-Titres[[#This Row],[Coût total]] -> 178.56 | S10: =Titres[[#This Row],[Gain non réalisé ($)]]/Titres[[#This Row],[Coût total]] -> 0.058919804 | T10: 0.278 | U10: =4*Titres[[#This Row],[Dividende trimestriel]] -> 1.112 | V10: =Titres[[#This Row],[Dividende annuel]]*Titres[[#This Row],[Nb d''actions]] -> 137.888 | W10: =Titres[[#This Row],[Dividende annuel]]/Titres[[#This Row],[Prix actuel]] -> 0.042967543 | X10: =Titres[[#This Row],[Dividende annuel]]/Titres[[#This Row],[Coût moyen]] -> 0.045499182 | Y10: 0 | Z10: =(((Titres[[#This Row],[Valeur au marché ($ local)]]-Titres[[#This Row],[Coût total]])+Titres[[#This Row],[Total - dividendes reçus]])/Titres[[#This Row],[Coût total]]) -> 0.19677551 | AA10: =SUM(Titres[[#This Row],[Janvier 2019]:[Août 2024]]) -> 417.78 | AC10: 22.44 | AF10: 22.44 | AI10: 22.44 | AL10: 22.44 | AO10: 22.88 | AR10: 22.88 | AU10: 22.88 | AX10: 22.88 | BA10: 22.88 | BD10: 22.88 | BG10: 22.88 | BJ10: 22.88 | BM10: 22.88 | BP10: 12.21 | BS10: 12.21 | BV10: 12.21 | BY10: 12.21 | CB10: 12.21 | CE10: 12.21 | CH10: 12.21 | CK10: 12.21 | CN10: 12.21 | CQ10: 12.21 | CT10: 34.41 | CW10: 34.41 | CZ10: 34.41 | DC10: 34.41 | DF10: 34.41 | DI10: 34.41
B11: =IF(C11="","",_xlfn.XLOOKUP(C11,Type_Compte,Num_Compte)) -> 20K6HU7 | C11: REER (USD) | D11: #VALUE! | E11: {=_FV(Titres[[#This Row],[Action]],"Code mnémonique",TRUE)} -> BAC | F11: {=_FV(D11,"Change")} -> New York Stock Exchange | G11: {=IFERROR(_FV(Titres[[#This Row],[Action]],"Industrie"),"")} -> Banking Services | H11: Actions américaines | I11: {=_FV(D11,"Devise")} -> USD | J11: 150 | K11: 48.57 | L11: =J11*K11 -> 7285.5 | M11: {=_FV(D11,"Prix")} -> 53.465 | N11: =J11*M11 -> 8019.75 | O11: =IF(Titres[[#This Row],[Devise]]="CAD",Titres[[#This Row],[Valeur au marché ($ local)]],Titres[[#This Row],[Valeur au marché ($ local)]]*Ressources!$I$3) -> 10954.979 | P11: {=(Titres[[#This Row],[Prix actuel]]-_FV(Titres[[#This Row],[Action]],"Clôture précédente",TRUE))*Titres[[#This Row],[Nb d''actions]]} -> -72.75 | Q11: =Titres[[#This Row],[Variation du jour ($)]]/(Titres[[#This Row],[Valeur au marché ($ local)]]-Titres[[#This Row],[Variation du jour ($)]]) -> -0.0089898054 | R11: =Titres[[#This Row],[Valeur au marché ($ local)]]-Titres[[#This Row],[Coût total]] -> 734.25 | S11: =Titres[[#This Row],[Gain non réalisé ($)]]/Titres[[#This Row],[Coût total]] -> 0.10078238 | T11: 0.28 | U11: =4*Titres[[#This Row],[Dividende trimestriel]] -> 1.12 | V11: =Titres[[#This Row],[Dividende annuel]]*Titres[[#This Row],[Nb d''actions]] -> 168 | W11: =Titres[[#This Row],[Dividende annuel]]/Titres[[#This Row],[Prix actuel]] -> 0.020948284 | X11: =Titres[[#This Row],[Dividende annuel]]/Titres[[#This Row],[Coût moyen]] -> 0.023059502 | Y11: 9 | Z11: =(((Titres[[#This Row],[Valeur au marché ($ local)]]-Titres[[#This Row],[Coût total]])+Titres[[#This Row],[Total - dividendes reçus]])/Titres[[#This Row],[Coût total]]) -> 0.14278361 | AA11: =SUM(Titres[[#This Row],[Janvier 2019]:[Août 2024]]) -> 306 | BN11: 31.5 | BQ11: 31.5 | BT11: 33 | BW11: 33 | CC11: 33 | CF11: 36 | CI11: 36 | CL11: 36 | CP11: 36 | CR11: 39 | CU11: 39 | CX11: 39 | DA11: 39 | DD11: 42 | DG11: 42
B12: =IF(C12="","",_xlfn.XLOOKUP(C12,Type_Compte,Num_Compte)) -> 20K6HZ6 | C12: CELI (CAD) | D12: #VALUE! | E12: {=_FV(Titres[[#This Row],[Action]],"Code mnémonique",TRUE)} -> CM | F12: {=_FV(D12,"Change")} -> Toronto Stock Exchange | G12: {=IFERROR(_FV(Titres[[#This Row],[Action]],"Industrie"),"")} -> Banking Services | H12: Actions canadiennes | I12: {=_FV(D12,"Devise")} -> CAD | J12: 88 | K12: 52.81 | L12: =J12*K12 -> 4647.28 | M12: {=_FV(D12,"Prix")} -> 148.48 | N12: =J12*M12 -> 13066.24 | O12: =IF(Titres[[#This Row],[Devise]]="CAD",Titres[[#This Row],[Valeur au marché ($ local)]],Titres[[#This Row],[Valeur au marché ($ local)]]*Ressources!$I$3) -> 13066.24 | P12: {=(Titres[[#This Row],[Prix actuel]]-_FV(Titres[[#This Row],[Action]],"Clôture précédente",TRUE))*Titres[[#This Row],[Nb d''actions]]} -> -168.08 | Q12: =Titres[[#This Row],[Variation du jour ($)]]/(Titres[[#This Row],[Valeur au marché ($ local)]]-Titres[[#This Row],[Variation du jour ($)]]) -> -0.012700313 | R12: =Titres[[#This Row],[Valeur au marché ($ local)]]-Titres[[#This Row],[Coût total]] -> 8418.96 | S12: =Titres[[#This Row],[Gain non réalisé ($)]]/Titres[[#This Row],[Coût total]] -> 1.8115887 | T12: 1.07 | U12: =4*Titres[[#This Row],[Dividende trimestriel]] -> 4.28 | V12: =Titres[[#This Row],[Dividende annuel]]*Titres[[#This Row],[Nb d''actions]] -> 376.64 | W12: =Titres[[#This Row],[Dividende annuel]]/Titres[[#This Row],[Prix actuel]] -> 0.028825431 | X12: =Titres[[#This Row],[Dividende annuel]]/Titres[[#This Row],[Coût moyen]] -> 0.081045257 | Y12: 0 | Z12: =(((Titres[[#This Row],[Valeur au marché ($ local)]]-Titres[[#This Row],[Coût total]])+Titres[[#This Row],[Total - dividendes reçus]])/Titres[[#This Row],[Coût total]]) -> 2.0794701 | AA12: =SUM(Titres[[#This Row],[Janvier 2019]:[Août 2024]]) -> 1244.92 | AB12: 19.04 | AE12: 19.6 | AH12: 19.6 | AK12: 20.16 | AN12: 20.16 | AQ12: 20.44 | AT12: 20.44 | AW12: 20.44 | AZ12: 64.24 | BC12: 64.24 | BF12: 64.24 | BI12: 64.24 | BL12: 70.84 | BO12: 70.84 | BR12: 73.04 | BU12: 73.04 | BX12: 74.8 | CA12: 74.8 | CD12: 76.56 | CG12: 76.56 | CJ12: 79.2 | CM12: 79.2 | CP12: 79.2 | CS12: 79.2 | CV12: 85.36 | CY12: 85.36 | DB12: 85.36 | DE12: 85.36 | DH12: 94.16
B13: =IF(C13="","",_xlfn.XLOOKUP(C13,Type_Compte,Num_Compte)) -> 20K6HZ6 | C13: CELI (CAD) | D13: #VALUE! | E13: {=_FV(Titres[[#This Row],[Action]],"Code mnémonique",TRUE)} -> BMO | F13: {=_FV(D13,"Change")} -> Toronto Stock Exchange | G13: {=IFERROR(_FV(Titres[[#This Row],[Action]],"Industrie"),"")} -> Banking Services | H13: Actions canadiennes | I13: {=_FV(D13,"Devise")} -> CAD | J13: 65 | K13: 127.78 | L13: =J13*K13 -> 8305.7 | M13: {=_FV(D13,"Prix")} -> 207.25 | N13: =J13*M13 -> 13471.25 | O13: =IF(Titres[[#This Row],[Devise]]="CAD",Titres[[#This Row],[Valeur au marché ($ local)]],Titres[[#This Row],[Valeur au marché ($ local)]]*Ressources!$I$3) -> 13471.25 | P13: {=(Titres[[#This Row],[Prix actuel]]-_FV(Titres[[#This Row],[Action]],"Clôture précédente",TRUE))*Titres[[#This Row],[Nb d''actions]]} -> -153.4 | Q13: =Titres[[#This Row],[Variation du jour ($)]]/(Titres[[#This Row],[Valeur au marché ($ local)]]-Titres[[#This Row],[Variation du jour ($)]]) -> -0.011259005 | R13: =Titres[[#This Row],[Valeur au marché ($ local)]]-Titres[[#This Row],[Coût total]] -> 5165.55 | S13: =Titres[[#This Row],[Gain non réalisé ($)]]/Titres[[#This Row],[Coût total]] -> 0.62192831 | T13: 1.67 | U13: =4*Titres[[#This Row],[Dividende trimestriel]] -> 6.68 | V13: =Titres[[#This Row],[Dividende annuel]]*Titres[[#This Row],[Nb d''actions]] -> 434.2 | W13: =Titres[[#This Row],[Dividende annuel]]/Titres[[#This Row],[Prix actuel]] -> 0.032231604 | X13: =Titres[[#This Row],[Dividende annuel]]/Titres[[#This Row],[Coût moyen]] -> 0.052277352 | Y13: 1 | Z13: =(((Titres[[#This Row],[Valeur au marché ($ local)]]-Titres[[#This Row],[Coût total]])+Titres[[#This Row],[Total - dividendes reçus]])/Titres[[#This Row],[Coût total]]) -> 0.7168872 | AA13: =SUM(Titres[[#This Row],[Janvier 2019]:[Août 2024]]) -> 788.7 | AF13: 30 | AI13: 30.9 | AL13: 30.9 | AO13: 31.8 | AR13: 31.8 | AU13: 31.8 | BA13: 31.8 | BD13: 31.8 | BG13: 31.8 | BJ13: 31.8 | BM13: 39.9 | BP13: 39.9 | BS13: 41.7 | BV13: 41.7 | BY13: 42.9 | CB13: 42.9 | CE13: 44.1 | CH13: 44.1 | CK13: 45.3 | CN13: 45.3 | CQ13: 46.5 | CT13: 46.5 | CW13: 47.7 | CZ13: 103.35 | DC13: 105.95 | DF13: 105.95 | DI13: 108.55
B14: =IF(C14="","",_xlfn.XLOOKUP(C14,Type_Compte,Num_Compte)) -> 20K6HZ6 | C14: CELI (CAD) | D14: #VALUE! | E14: {=_FV(Titres[[#This Row],[Action]],"Code mnémonique",TRUE)} -> NA | F14: {=_FV(D14,"Change")} -> Toronto Stock Exchange | G14: {=IFERROR(_FV(Titres[[#This Row],[Action]],"Industrie"),"")} -> Banking Services | H14: Actions canadiennes | I14: {=_FV(D14,"Devise")} -> CAD | J14: 81 | K14: 69.48 | L14: =J14*K14 -> 5627.88 | M14: {=_FV(D14,"Prix")} -> 201.79 | N14: =J14*M14 -> 16344.99 | O14: =IF(Titres[[#This Row],[Devise]]="CAD",Titres[[#This Row],[Valeur au marché ($ local)]],Titres[[#This Row],[Valeur au marché ($ local)]]*Ressources!$I$3) -> 16344.99 | P14: {=(Titres[[#This Row],[Prix actuel]]-_FV(Titres[[#This Row],[Action]],"Clôture précédente",TRUE))*Titres[[#This Row],[Nb d''actions]]} -> -153.09 | Q14: =Titres[[#This Row],[Variation du jour ($)]]/(Titres[[#This Row],[Valeur au marché ($ local)]]-Titres[[#This Row],[Variation du jour ($)]]) -> -0.0092792616 | R14: =Titres[[#This Row],[Valeur au marché ($ local)]]-Titres[[#This Row],[Coût total]] -> 10717.11 | S14: =Titres[[#This Row],[Gain non réalisé ($)]]/Titres[[#This Row],[Coût total]] -> 1.904289 | T14: 1.24 | U14: =4*Titres[[#This Row],[Dividende trimestriel]] -> 4.96 | V14: =Titres[[#This Row],[Dividende annuel]]*Titres[[#This Row],[Nb d''actions]] -> 401.76 | W14: =Titres[[#This Row],[Dividende annuel]]/Titres[[#This Row],[Prix actuel]] -> 0.024580009 | X14: =Titres[[#This Row],[Dividende annuel]]/Titres[[#This Row],[Coût moyen]] -> 0.07138745 | Y14: 8 | Z14: =(((Titres[[#This Row],[Valeur au marché ($ local)]]-Titres[[#This Row],[Coût total]])+Titres[[#This Row],[Total - dividendes reçus]])/Titres[[#This Row],[Coût total]]) -> 2.0401839 | AA14: =SUM(Titres[[#This Row],[Janvier 2019]:[Août 2024]]) -> 764.8 | AC14: 26 | AF14: 26 | AI14: 27.2 | AL14: 27.2 | AO14: 28.4 | AR14: 28.4 | AU14: 28.4 | AX14: 28.4 | BA14: 28.4 | BD14: 28.4 | BG14: 28.4 | BJ14: 28.4 | BM14: 34.8 | BP14: 34.8 | BS14: 36.8 | BV14: 36.8 | BY14: 38.8 | CB14: 38.8 | CE14: 40.8 | CH14: 40.8 | CK14: 42.4 | CN14: 42.4 | CQ14: 44 | CT14: 44 | CW14: 45.6 | CZ14: 92.34 | DC14: 95.58 | DF14: 95.58 | DI14: 100.44
B15: =IF(C15="","",_xlfn.XLOOKUP(C15,Type_Compte,Num_Compte)) -> 20K6HZ6 | C15: CELI (CAD) | D15: Canadian Western Bank (merge avec Banque Nationale) | E15: CWB | G15: {=IFERROR(_FV(Titres[[#This Row],[Action]],"Industrie"),"")} | H15: Actions canadiennes | J15: 0 | K15: 32.39 | L15: =J15*K15 -> 0 | N15: =J15*M15 -> 0 | O15: =IF(Titres[[#This Row],[Devise]]="CAD",Titres[[#This Row],[Valeur au marché ($ local)]],Titres[[#This Row],[Valeur au marché ($ local)]]*Ressources!$I$3) -> 0 | Q15: =Titres[[#This Row],[Variation du jour ($)]]/(Titres[[#This Row],[Valeur au marché ($ local)]]-Titres[[#This Row],[Variation du jour ($)]]) -> #DIV/0! | R15: =Titres[[#This Row],[Valeur au marché ($ local)]]-Titres[[#This Row],[Coût total]] -> 0 | S15: =Titres[[#This Row],[Gain non réalisé ($)]]/Titres[[#This Row],[Coût total]] -> #DIV/0! | T15: 0.35 | U15: =4*Titres[[#This Row],[Dividende trimestriel]] -> 1.4 | V15: =Titres[[#This Row],[Dividende annuel]]*Titres[[#This Row],[Nb d''actions]] -> 0 | W15: =Titres[[#This Row],[Dividende annuel]]/Titres[[#This Row],[Prix actuel]] -> #DIV/0! | X15: =Titres[[#This Row],[Dividende annuel]]/Titres[[#This Row],[Coût moyen]] -> 0.043223217 | Y15: 15 | Z15: =(((Titres[[#This Row],[Valeur au marché ($ local)]]-Titres[[#This Row],[Coût total]])+Titres[[#This Row],[Total - dividendes reçus]])/Titres[[#This Row],[Coût total]]) -> #DIV/0! | AA15: =SUM(Titres[[#This Row],[Janvier 2019]:[Août 2024]]) -> 645.42 | AB15: 24.18 | AD15: 25.11 | AG15: 25.11 | AJ15: 26.04 | AN15: 26.04 | AP15: 26.97 | AS15: 26.97 | AV15: 26.97 | AZ15: 26.97 | BB15: 26.97 | BE15: 26.97 | BH15: 26.97 | BL15: 27.9 | BN15: 27.9 | BQ15: 28.83 | BT15: 28.83 | BX15: 29.76 | BZ15: 29.76 | CC15: 30.69 | CF15: 30.69 | CJ15: 31.62 | CL15: 31.62 | CO15: 32.55 | CR15: 32.55 | CV15: 33.48
B16: =IF(C16="","",_xlfn.XLOOKUP(C16,Type_Compte,Num_Compte)) -> 20K6HZ6 | C16: CELI (CAD) | D16: #VALUE! | E16: {=_FV(Titres[[#This Row],[Action]],"Code mnémonique",TRUE)} -> RY | F16: {=_FV(D16,"Change")} -> Toronto Stock Exchange | G16: {=IFERROR(_FV(Titres[[#This Row],[Action]],"Industrie"),"")} -> Banking Services | H16: Actions canadiennes | I16: {=_FV(D16,"Devise")} -> CAD | J16: 55 | K16: 95.04 | L16: =J16*K16 -> 5227.2 | M16: {=_FV(D16,"Prix")} -> 242.81 | N16: =J16*M16 -> 13354.55 | O16: =IF(Titres[[#This Row],[Devise]]="CAD",Titres[[#This Row],[Valeur au marché ($ local)]],Titres[[#This Row],[Valeur au marché ($ local)]]*Ressources!$I$3) -> 13354.55 | P16: {=(Titres[[#This Row],[Prix actuel]]-_FV(Titres[[#This Row],[Action]],"Clôture précédente",TRUE))*Titres[[#This Row],[Nb d''actions]]} -> -167.2 | Q16: =Titres[[#This Row],[Variation du jour ($)]]/(Titres[[#This Row],[Valeur au marché ($ local)]]-Titres[[#This Row],[Variation du jour ($)]]) -> -0.012365263 | R16: =Titres[[#This Row],[Valeur au marché ($ local)]]-Titres[[#This Row],[Coût total]] -> 8127.35 | S16: =Titres[[#This Row],[Gain non réalisé ($)]]/Titres[[#This Row],[Coût total]] -> 1.554819 | T16: 1.64 | U16: =4*Titres[[#This Row],[Dividende trimestriel]] -> 6.56 | V16: =Titres[[#This Row],[Dividende annuel]]*Titres[[#This Row],[Nb d''actions]] -> 360.8 | W16: =Titres[[#This Row],[Dividende annuel]]/Titres[[#This Row],[Prix actuel]] -> 0.027017009 | X16: =Titres[[#This Row],[Dividende annuel]]/Titres[[#This Row],[Coût moyen]] -> 0.069023569 | Y16: 12 | Z16: =(((Titres[[#This Row],[Valeur au marché ($ local)]]-Titres[[#This Row],[Coût total]])+Titres[[#This Row],[Total - dividendes reçus]])/Titres[[#This Row],[Coût total]]) -> 1.784617 | AA16: =SUM(Titres[[#This Row],[Janvier 2019]:[Août 2024]]) -> 1201.2 | AC16: 19.6 | AF16: 20.4 | AI16: 20.4 | AL16: 21 | AO16: 21 | AR16: 21.6 | AU16: 21.6 | AX16: 21.6 | BA16: 59.4 | BD16: 59.4 | BG16: 59.4 | BJ16: 59.4 | BM16: 66 | BP16: 66 | BS16: 70.4 | BV16: 70.4 | BY16: 72.6 | CB16: 72.6 | CE16: 74.25 | CH16: 74.25 | CK16: 75.9 | CN16: 75.9 | CQ16: 78.1 | CT16: 78.1 | CW16: 81.4 | CZ16: 81.4 | DC16: 84.7 | DF16: 84.7 | DI16: 90.2
B17: =IF(C17="","",_xlfn.XLOOKUP(C17,Type_Compte,Num_Compte)) -> 20K6HZ6 | C17: CELI (CAD) | D17: #VALUE! | E17: {=_FV(Titres[[#This Row],[Action]],"Code mnémonique",TRUE)} -> BEP.UN | F17: {=_FV(D17,"Change")} -> Toronto Stock Exchange | G17: {=IFERROR(_FV(Titres[[#This Row],[Action]],"Industrie"),"")} | H17: Actions canadiennes | I17: {=_FV(D17,"Devise")} -> CAD | J17: 180 | K17: 38.81 | L17: =J17*K17 -> 6985.8 | M17: {=_FV(D17,"Prix")} -> 44.35 | N17: =J17*M17 -> 7983 | O17: =IF(Titres[[#This Row],[Devise]]="CAD",Titres[[#This Row],[Valeur au marché ($ local)]],Titres[[#This Row],[Valeur au marché ($ local)]]*Ressources!$I$3) -> 7983 | P17: {=(Titres[[#This Row],[Prix actuel]]-_FV(Titres[[#This Row],[Action]],"Clôture précédente",TRUE))*Titres[[#This Row],[Nb d''actions]]} -> -541.8 | Q17: =Titres[[#This Row],[Variation du jour ($)]]/(Titres[[#This Row],[Valeur au marché ($ local)]]-Titres[[#This Row],[Variation du jour ($)]]) -> -0.063555743 | R17: =Titres[[#This Row],[Valeur au marché ($ local)]]-Titres[[#This Row],[Coût total]] -> 997.2 | S17: =Titres[[#This Row],[Gain non réalisé ($)]]/Titres[[#This Row],[Coût total]] -> 0.14274671 | T17: 0.392 | U17: =4*Titres[[#This Row],[Dividende trimestriel]] -> 1.568 | V17: =Titres[[#This Row],[Dividende annuel]]*Titres[[#This Row],[Nb d''actions]] -> 282.24 | W17: =Titres[[#This Row],[Dividende annuel]]/Titres[[#This Row],[Prix actuel]] -> 0.03535513 | X17: =Titres[[#This Row],[Dividende annuel]]/Titres[[#This Row],[Coût moyen]] -> 0.040401958 | Y17: 1 | Z17: =(((Titres[[#This Row],[Valeur au marché ($ local)]]-Titres[[#This Row],[Coût total]])+Titres[[#This Row],[Total - dividendes reçus]])/Titres[[#This Row],[Coût total]]) -> 0.2049028 | AA17: =SUM(Titres[[#This Row],[Janvier 2019]:[Août 2024]]) -> 434.21 | BN17: 40.63 | BQ17: 40.47 | BT17: 41.96 | BW17: 43.23 | CC17: 45.91 | CF17: 45.67 | CI17: 45.84 | CL17: 43.36 | CP17: 87.14 | CR17: 86.21 | CU17: 89.52 | CX17: 96.94 | DA17: 92.37 | DD17: 92.26 | DG17: 93.86
B18: =IF(C18="","",_xlfn.XLOOKUP(C18,Type_Compte,Num_Compte)) -> 20K6HU7 | C18: REER (USD) | D18: #VALUE! | E18: {=_FV(Titres[[#This Row],[Action]],"Code mnémonique",TRUE)} -> CVX | F18: {=_FV(D18,"Change")} -> New York Stock Exchange | G18: {=IFERROR(_FV(Titres[[#This Row],[Action]],"Industrie"),"")} -> Oil & Gas | H18: Actions américaines | I18: {=_FV(D18,"Devise")} -> USD | J18: 12 | K18: 105.7 | L18: =J18*K18 -> 1268.4 | M18: {=_FV(D18,"Prix")} -> 186.02 | N18: =J18*M18 -> 2232.24 | O18: =IF(Titres[[#This Row],[Devise]]="CAD",Titres[[#This Row],[Valeur au marché ($ local)]],Titres[[#This Row],[Valeur au marché ($ local)]]*Ressources!$I$3) -> 3049.2398 | P18: {=(Titres[[#This Row],[Prix actuel]]-_FV(Titres[[#This Row],[Action]],"Clôture précédente",TRUE))*Titres[[#This Row],[Nb d''actions]]} -> 33.24 | Q18: =Titres[[#This Row],[Variation du jour ($)]]/(Titres[[#This Row],[Valeur au marché ($ local)]]-Titres[[#This Row],[Variation du jour ($)]]) -> 0.015115962 | R18: =Titres[[#This Row],[Valeur au marché ($ local)]]-Titres[[#This Row],[Coût total]] -> 963.84 | S18: =Titres[[#This Row],[Gain non réalisé ($)]]/Titres[[#This Row],[Coût total]] -> 0.75988647 | T18: 1.78 | U18: =4*Titres[[#This Row],[Dividende trimestriel]] -> 7.12 | V18: =Titres[[#This Row],[Dividende annuel]]*Titres[[#This Row],[Nb d''actions]] -> 85.44 | W18: =Titres[[#This Row],[Dividende annuel]]/Titres[[#This Row],[Prix actuel]] -> 0.038275454 | X18: =Titres[[#This Row],[Dividende annuel]]/Titres[[#This Row],[Coût moyen]] -> 0.067360454 | Y18: 35 | Z18: =(((Titres[[#This Row],[Valeur au marché ($ local)]]-Titres[[#This Row],[Coût total]])+Titres[[#This Row],[Total - dividendes reçus]])/Titres[[#This Row],[Coût total]]) -> 1.0456954 | AA18: =SUM(Titres[[#This Row],[Janvier 2019]:[Août 2024]]) -> 362.52 | AD18: 14.28 | AG18: 14.28 | AJ18: 14.28 | AM18: 14.28 | AP18: 15.48 | AS18: 15.48 | AV18: 15.48 | AY18: 15.48 | BB18: 15.48 | BE18: 16.08 | BH18: 16.08 | BK18: 16.08 | BN18: 17.04 | BQ18: 17.04 | BT18: 17.04 | BW18: 17.04 | BZ18: 18.12 | CC18: 18.12 | CF18: 18.12 | CI18: 18.12 | CL18: 19.56 | CO18: 19.56 | CR18: 19.56 | CU18: 19.56 | CX18: 20.52 | DA18: 20.52 | DD18: 20.52 | DG18: 20.52
B19: =IF(C19="","",_xlfn.XLOOKUP(C19,Type_Compte,Num_Compte)) -> 20K6HU7 | C19: REER (USD) | D19: #VALUE! | E19: {=_FV(Titres[[#This Row],[Action]],"Code mnémonique",TRUE)} -> CL | F19: {=_FV(D19,"Change")} -> New York Stock Exchange | G19: {=IFERROR(_FV(Titres[[#This Row],[Action]],"Industrie"),"")} -> Personal & Household Products & Services | H19: Actions américaines | I19: {=_FV(D19,"Devise")} -> USD | J19: 23 | K19: 68.74 | L19: =J19*K19 -> 1581.02 | M19: {=_FV(D19,"Prix")} -> 81.81 | N19: =J19*M19 -> 1881.63 | O19: =IF(Titres[[#This Row],[Devise]]="CAD",Titres[[#This Row],[Valeur au marché ($ local)]],Titres[[#This Row],[Valeur au marché ($ local)]]*Ressources!$I$3) -> 2570.3066 | P19: {=(Titres[[#This Row],[Prix actuel]]-_FV(Titres[[#This Row],[Action]],"Clôture précédente",TRUE))*Titres[[#This Row],[Nb d''actions]]} -> -39.56 | Q19: =Titres[[#This Row],[Variation du jour ($)]]/(Titres[[#This Row],[Valeur au marché ($ local)]]-Titres[[#This Row],[Variation du jour ($)]]) -> -0.020591404 | R19: =Titres[[#This Row],[Valeur au marché ($ local)]]-Titres[[#This Row],[Coût total]] -> 300.61 | S19: =Titres[[#This Row],[Gain non réalisé ($)]]/Titres[[#This Row],[Coût total]] -> 0.19013675 | T19: 0.52 | U19: =4*Titres[[#This Row],[Dividende trimestriel]] -> 2.08 | V19: =Titres[[#This Row],[Dividende annuel]]*Titres[[#This Row],[Nb d''actions]] -> 47.84 | W19: =Titres[[#This Row],[Dividende annuel]]/Titres[[#This Row],[Prix actuel]] -> 0.025424765 | X19: =Titres[[#This Row],[Dividende annuel]]/Titres[[#This Row],[Coût moyen]] -> 0.030258947 | Y19: 59 | Z19: =(((Titres[[#This Row],[Valeur au marché ($ local)]]-Titres[[#This Row],[Coût total]])+Titres[[#This Row],[Total - dividendes reçus]])/Titres[[#This Row],[Coût total]]) -> 0.34288624 | AA19: =SUM(Titres[[#This Row],[Janvier 2019]:[Août 2024]]) -> 241.5 | AC19: 9.66 | AF19: 9.89 | AI19: 9.89 | AL19: 9.89 | AO19: 9.89 | AR19: 10.12 | AU19: 10.12 | AX19: 10.12 | BA19: 10.12 | BD19: 10.35 | BG19: 10.35 | BJ19: 10.35 | BM19: 10.35 | BP19: 10.81 | BS19: 10.81 | BV19: 10.81 | BY19: 10.81 | CB19: 11.04 | CE19: 11.04 | CH19: 11.04 | CK19: 11.04 | CN19: 11.5 | CQ19: 11.5 | CT19: 11.5 | CW19: 11.5 | CZ19: 11.96 | DC19: 11.96 | DF19: 11.96 | DI19: 11.96
B20: =IF(C20="","",_xlfn.XLOOKUP(C20,Type_Compte,Num_Compte)) -> 20K6HF2 | C20: Marge (USD) | D20: #VALUE! | E20: {=_FV(Titres[[#This Row],[Action]],"Code mnémonique",TRUE)} -> CMP | F20: {=_FV(D20,"Change")} -> New York Stock Exchange | G20: {=IFERROR(_FV(Titres[[#This Row],[Action]],"Industrie"),"")} -> Chemicals | H20: Actions américaines | I20: {=_FV(D20,"Devise")} -> USD | J20: 0 | K20: 46.48 | L20: =J20*K20 -> 0 | M20: {=_FV(D20,"Prix")} -> 25.55 | N20: =J20*M20 -> 0 | O20: =IF(Titres[[#This Row],[Devise]]="CAD",Titres[[#This Row],[Valeur au marché ($ local)]],Titres[[#This Row],[Valeur au marché ($ local)]]*Ressources!$I$3) -> 0 | P20: {=(Titres[[#This Row],[Prix actuel]]-_FV(Titres[[#This Row],[Action]],"Clôture précédente",TRUE))*Titres[[#This Row],[Nb d''actions]]} -> 0 | Q20: =Titres[[#This Row],[Variation du jour ($)]]/(Titres[[#This Row],[Valeur au marché ($ local)]]-Titres[[#This Row],[Variation du jour ($)]]) -> #DIV/0! | R20: =Titres[[#This Row],[Valeur au marché ($ local)]]-Titres[[#This Row],[Coût total]] -> 0 | S20: =Titres[[#This Row],[Gain non réalisé ($)]]/Titres[[#This Row],[Coût total]] -> #DIV/0! | T20: 0.15 | U20: =4*Titres[[#This Row],[Dividende trimestriel]] -> 0.6 | V20: =Titres[[#This Row],[Dividende annuel]]*Titres[[#This Row],[Nb d''actions]] -> 0 | W20: =Titres[[#This Row],[Dividende annuel]]/Titres[[#This Row],[Prix actuel]] -> 0.023483366 | X20: =Titres[[#This Row],[Dividende annuel]]/Titres[[#This Row],[Coût moyen]] -> 0.012908778 | Y20: 0 | Z20: =(((Titres[[#This Row],[Valeur au marché ($ local)]]-Titres[[#This Row],[Coût total]])+Titres[[#This Row],[Total - dividendes reçus]])/Titres[[#This Row],[Coût total]]) -> #DIV/0! | AA20: =SUM(Titres[[#This Row],[Janvier 2019]:[Août 2024]]) -> 70.1 | BZ20: 14.02 | CC20: 14.02 | CF20: 14.02 | CI20: 14.02 | CL20: 14.02
B21: =IF(C21="","",_xlfn.XLOOKUP(C21,Type_Compte,Num_Compte)) -> 20K6HE4 | C21: Marge (CAD) | D21: #VALUE! | E21: {=_FV(Titres[[#This Row],[Action]],"Code mnémonique",TRUE)} -> XSP | F21: {=_FV(D21,"Change")} -> Toronto Stock Exchange | G21: {=IFERROR(_FV(Titres[[#This Row],[Action]],"Industrie"),"")} | H21: Actions américaines | I21: {=_FV(D21,"Devise")} -> CAD | J21: 500 | K21: 55.91 | L21: =J21*K21 -> 27955 | M21: {=_FV(D21,"Prix")} -> 71.38 | N21: =J21*M21 -> 35690 | O21: =IF(Titres[[#This Row],[Devise]]="CAD",Titres[[#This Row],[Valeur au marché ($ local)]],Titres[[#This Row],[Valeur au marché ($ local)]]*Ressources!$I$3) -> 35690 | P21: {=(Titres[[#This Row],[Prix actuel]]-_FV(Titres[[#This Row],[Action]],"Clôture précédente",TRUE))*Titres[[#This Row],[Nb d''actions]]} -> -230 | Q21: =Titres[[#This Row],[Variation du jour ($)]]/(Titres[[#This Row],[Valeur au marché ($ local)]]-Titres[[#This Row],[Variation du jour ($)]]) -> -0.006403118 | R21: =Titres[[#This Row],[Valeur au marché ($ local)]]-Titres[[#This Row],[Coût total]] -> 7735 | S21: =Titres[[#This Row],[Gain non réalisé ($)]]/Titres[[#This Row],[Coût total]] -> 0.27669469 | T21: 0.556 | U21: =4*Titres[[#This Row],[Dividende trimestriel]] -> 2.224 | V21: =Titres[[#This Row],[Dividende annuel]]*Titres[[#This Row],[Nb d''actions]] -> 1112 | W21: =Titres[[#This Row],[Dividende annuel]]/Titres[[#This Row],[Prix actuel]] -> 0.031157187 | X21: =Titres[[#This Row],[Dividende annuel]]/Titres[[#This Row],[Coût moyen]] -> 0.039778215 | Z21: =(((Titres[[#This Row],[Valeur au marché ($ local)]]-Titres[[#This Row],[Coût total]])+Titres[[#This Row],[Total - dividendes reçus]])/Titres[[#This Row],[Coût total]]) -> 0.27969952 | AA21: =SUM(Titres[[#This Row],[Janvier 2019]:[Août 2024]]) -> 84 | CP21: 84 | CV21: 192.35 | DA21: 150 | DH21: 278
B22: =IF(C22="","",_xlfn.XLOOKUP(C22,Type_Compte,Num_Compte)) -> 20K6HZ6 | C22: CELI (CAD) | D22: #VALUE! | E22: {=_FV(Titres[[#This Row],[Action]],"Code mnémonique",TRUE)} -> CTC | F22: {=_FV(D22,"Change")} -> Toronto Stock Exchange | G22: {=IFERROR(_FV(Titres[[#This Row],[Action]],"Industrie"),"")} -> Diversified Retail | H22: Actions canadiennes | I22: {=_FV(D22,"Devise")} -> CAD | J22: 24 | K22: 224.3 | L22: =J22*K22 -> 5383.2 | M22: {=_FV(D22,"Prix")} -> 219.99 | N22: =J22*M22 -> 5279.76 | O22: =IF(Titres[[#This Row],[Devise]]="CAD",Titres[[#This Row],[Valeur au marché ($ local)]],Titres[[#This Row],[Valeur au marché ($ local)]]*Ressources!$I$3) -> 5279.76 | P22: {=(Titres[[#This Row],[Prix actuel]]-_FV(Titres[[#This Row],[Action]],"Clôture précédente",TRUE))*Titres[[#This Row],[Nb d''actions]]} -> 167.76 | Q22: =Titres[[#This Row],[Variation du jour ($)]]/(Titres[[#This Row],[Valeur au marché ($ local)]]-Titres[[#This Row],[Variation du jour ($)]]) -> 0.032816901 | R22: =Titres[[#This Row],[Valeur au marché ($ local)]]-Titres[[#This Row],[Coût total]] -> -103.44 | S22: =Titres[[#This Row],[Gain non réalisé ($)]]/Titres[[#This Row],[Coût total]] -> -0.019215337 | T22: 1.8 | U22: =4*Titres[[#This Row],[Dividende trimestriel]] -> 7.2 | V22: =Titres[[#This Row],[Dividende annuel]]*Titres[[#This Row],[Nb d''actions]] -> 172.8 | W22: =Titres[[#This Row],[Dividende annuel]]/Titres[[#This Row],[Prix actuel]] -> 0.03272876 | X22: =Titres[[#This Row],[Dividende annuel]]/Titres[[#This Row],[Coût moyen]] -> 0.032099866 | Y22: 12 | Z22: =(((Titres[[#This Row],[Valeur au marché ($ local)]]-Titres[[#This Row],[Coût total]])+Titres[[#This Row],[Total - dividendes reçus]])/Titres[[#This Row],[Coût total]]) -> -0.015180562 | AA22: =SUM(Titres[[#This Row],[Janvier 2019]:[Août 2024]]) -> 21.72 | CE22: =25.55-3.83 -> 21.72 | CR22: 21 | CU22: 29.75 | CX22: 30.18 | DA22: 30.18 | DD22: 42.6 | DG22: 42.6
B23: =IF(C23="","",_xlfn.XLOOKUP(C23,Type_Compte,Num_Compte)) -> 20K6HZ6 | C23: CELI (CAD) | D23: #VALUE! | E23: {=_FV(Titres[[#This Row],[Action]],"Code mnémonique",TRUE)} -> CU | F23: {=_FV(D23,"Change")} -> Toronto Stock Exchange | G23: {=IFERROR(_FV(Titres[[#This Row],[Action]],"Industrie"),"")} -> Multiline Utilities | H23: Actions canadiennes | I23: {=_FV(D23,"Devise")} -> CAD | J23: 150 | K23: 44.48 | L23: =J23*K23 -> 6672 | M23: {=_FV(D23,"Prix")} -> 47.92 | N23: =J23*M23 -> 7188 | O23: =IF(Titres[[#This Row],[Devise]]="CAD",Titres[[#This Row],[Valeur au marché ($ local)]],Titres[[#This Row],[Valeur au marché ($ local)]]*Ressources!$I$3) -> 7188 | P23: {=(Titres[[#This Row],[Prix actuel]]-_FV(Titres[[#This Row],[Action]],"Clôture précédente",TRUE))*Titres[[#This Row],[Nb d''actions]]} -> -43.5 | Q23: =Titres[[#This Row],[Variation du jour ($)]]/(Titres[[#This Row],[Valeur au marché ($ local)]]-Titres[[#This Row],[Variation du jour ($)]]) -> -0.0060153495 | R23: =Titres[[#This Row],[Valeur au marché ($ local)]]-Titres[[#This Row],[Coût total]] -> 516 | S23: =Titres[[#This Row],[Gain non réalisé ($)]]/Titres[[#This Row],[Coût total]] -> 0.077338129 | T23: 0.462 | U23: =4*Titres[[#This Row],[Dividende trimestriel]] -> 1.848 | V23: =Titres[[#This Row],[Dividende annuel]]*Titres[[#This Row],[Nb d''actions]] -> 277.2 | W23: =Titres[[#This Row],[Dividende annuel]]/Titres[[#This Row],[Prix actuel]] -> 0.038564274 | X23: =Titres[[#This Row],[Dividende annuel]]/Titres[[#This Row],[Coût moyen]] -> 0.041546763 | Z23: =(((Titres[[#This Row],[Valeur au marché ($ local)]]-Titres[[#This Row],[Coût total]])+Titres[[#This Row],[Total - dividendes reçus]])/Titres[[#This Row],[Coût total]]) -> 0.080593525 | AA23: =SUM(Titres[[#This Row],[Janvier 2019]:[Août 2024]]) -> 21.72 | CE23: =25.55-3.83 -> 21.72
B24: =IF(C24="","",_xlfn.XLOOKUP(C24,Type_Compte,Num_Compte)) -> 20K6HZ6 | C24: CELI (CAD) | D24: #VALUE! | E24: {=_FV(Titres[[#This Row],[Action]],"Code mnémonique",TRUE)} -> EMA | F24: {=_FV(D24,"Change")} -> Toronto Stock Exchange | G24: {=IFERROR(_FV(Titres[[#This Row],[Action]],"Industrie"),"")} -> Electrical Utilities & IPPs | H24: Actions canadiennes | I24: {=_FV(D24,"Devise")} -> CAD | J24: 68 | K24: 43.98 | L24: =J24*K24 -> 2990.64 | M24: {=_FV(D24,"Prix")} -> 70.78 | N24: =J24*M24 -> 4813.04 | O24: =IF(Titres[[#This Row],[Devise]]="CAD",Titres[[#This Row],[Valeur au marché ($ local)]],Titres[[#This Row],[Valeur au marché ($ local)]]*Ressources!$I$3) -> 4813.04 | P24: {=(Titres[[#This Row],[Prix actuel]]-_FV(Titres[[#This Row],[Action]],"Clôture précédente",TRUE))*Titres[[#This Row],[Nb d''actions]]} -> -15.64 | Q24: =Titres[[#This Row],[Variation du jour ($)]]/(Titres[[#This Row],[Valeur au marché ($ local)]]-Titres[[#This Row],[Variation du jour ($)]]) -> -0.0032389804 | R24: =Titres[[#This Row],[Valeur au marché ($ local)]]-Titres[[#This Row],[Coût total]] -> 1822.4 | S24: =Titres[[#This Row],[Gain non réalisé ($)]]/Titres[[#This Row],[Coût total]] -> 0.60936789 | T24: 0.733 | U24: =4*Titres[[#This Row],[Dividende trimestriel]] -> 2.932 | V24: =Titres[[#This Row],[Dividende annuel]]*Titres[[#This Row],[Nb d''actions]] -> 199.376 | W24: =Titres[[#This Row],[Dividende annuel]]/Titres[[#This Row],[Prix actuel]] -> 0.041424131 | X24: =Titres[[#This Row],[Dividende annuel]]/Titres[[#This Row],[Coût moyen]] -> 0.066666667 | Y24: 16 | Z24: =(((Titres[[#This Row],[Valeur au marché ($ local)]]-Titres[[#This Row],[Coût total]])+Titres[[#This Row],[Total - dividendes reçus]])/Titres[[#This Row],[Coût total]]) -> 0.95139836 | AA24: =SUM(Titres[[#This Row],[Janvier 2019]:[Août 2024]]) -> 1022.89 | AC24: 39.95 | AF24: 39.95 | AI24: 39.95 | AL24: 41.65 | AO24: 41.65 | AR24: 41.65 | AU24: 41.65 | AX24: 43.35 | BA24: 43.35 | BD24: 43.35 | BG24: 43.35 | BJ24: 45.05 | BM24: 45.05 | BP24: 45.05 | BS24: 45.05 | BV24: 46.92 | BY24: 46.92 | CB24: 46.92 | CE24: 46.92 | CH24: 48.79 | CK24: 48.79 | CN24: 48.79 | CQ24: 48.79 | CT24: 49.3 | CW24: 49.3 | CZ24: 49.3 | DC24: 49.3 | DF24: 49.81 | DI24: 49.81
B25: =IF(C25="","",_xlfn.XLOOKUP(C25,Type_Compte,Num_Compte)) -> 20K6HU7 | C25: REER (USD) | D25: #VALUE! | E25: {=_FV(Titres[[#This Row],[Action]],"Code mnémonique",TRUE)} -> GEHC | F25: {=_FV(D25,"Change")} -> Nasdaq Stock Market | G25: {=IFERROR(_FV(Titres[[#This Row],[Action]],"Industrie"),"")} -> Healthcare Equipment & Supplies | H25: Actions américaines | I25: {=_FV(D25,"Devise")} -> USD | J25: 2 | K25: 54.13 | L25: =J25*K25 -> 108.26 | M25: {=_FV(D25,"Prix")} -> 72.26 | N25: =J25*M25 -> 144.52 | O25: =IF(Titres[[#This Row],[Devise]]="CAD",Titres[[#This Row],[Valeur au marché ($ local)]],Titres[[#This Row],[Valeur au marché ($ local)]]*Ressources!$I$3) -> 197.41432 | P25: {=(Titres[[#This Row],[Prix actuel]]-_FV(Titres[[#This Row],[Action]],"Clôture précédente",TRUE))*Titres[[#This Row],[Nb d''actions]]} -> -3.78 | Q25: =Titres[[#This Row],[Variation du jour ($)]]/(Titres[[#This Row],[Valeur au marché ($ local)]]-Titres[[#This Row],[Variation du jour ($)]]) -> -0.025488874 | R25: =Titres[[#This Row],[Valeur au marché ($ local)]]-Titres[[#This Row],[Coût total]] -> 36.26 | S25: =Titres[[#This Row],[Gain non réalisé ($)]]/Titres[[#This Row],[Coût total]] -> 0.33493442 | T25: 0.035 | U25: =4*Titres[[#This Row],[Dividende trimestriel]] -> 0.14 | V25: =Titres[[#This Row],[Dividende annuel]]*Titres[[#This Row],[Nb d''actions]] -> 0.28 | W25: =Titres[[#This Row],[Dividende annuel]]/Titres[[#This Row],[Prix actuel]] -> 0.0019374481 | X25: =Titres[[#This Row],[Dividende annuel]]/Titres[[#This Row],[Coût moyen]] -> 0.0025863662 | Y25: 0 | Z25: =(((Titres[[#This Row],[Valeur au marché ($ local)]]-Titres[[#This Row],[Coût total]])+Titres[[#This Row],[Total - dividendes reçus]])/Titres[[#This Row],[Coût total]]) -> 0.33825975 | AA25: =SUM(Titres[[#This Row],[Janvier 2019]:[Août 2024]]) -> 0.36 | CC25: 0.06 | CE25: 0.06 | CH25: 0.06 | CK25: 0.06 | CN25: 0.06 | CQ25: 0.06 | CT25: 0.06 | CW25: 0.07 | CZ25: 0.07 | DC25: 0.07 | DF25: 0.07 | DI25: 0.07
B26: =IF(C26="","",_xlfn.XLOOKUP(C26,Type_Compte,Num_Compte)) -> 20K6HU7 | C26: REER (USD) | D26: #VALUE! | E26: {=_FV(Titres[[#This Row],[Action]],"Code mnémonique",TRUE)} -> GEV | F26: {=_FV(D26,"Change")} -> New York Stock Exchange | G26: {=IFERROR(_FV(Titres[[#This Row],[Action]],"Industrie"),"")} -> Electrical Utilities & IPPs | H26: Actions américaines | I26: {=_FV(D26,"Devise")} -> USD | J26: 1 | K26: 142.85 | L26: =J26*K26 -> 142.85 | M26: {=_FV(D26,"Prix")} -> 991.52 | N26: =J26*M26 -> 991.52 | O26: =IF(Titres[[#This Row],[Devise]]="CAD",Titres[[#This Row],[Valeur au marché ($ local)]],Titres[[#This Row],[Valeur au marché ($ local)]]*Ressources!$I$3) -> 1354.4163 | P26: {=(Titres[[#This Row],[Prix actuel]]-_FV(Titres[[#This Row],[Action]],"Clôture précédente",TRUE))*Titres[[#This Row],[Nb d''actions]]} -> 1.34 | Q26: =Titres[[#This Row],[Variation du jour ($)]]/(Titres[[#This Row],[Valeur au marché ($ local)]]-Titres[[#This Row],[Variation du jour ($)]]) -> 0.0013532893 | R26: =Titres[[#This Row],[Valeur au marché ($ local)]]-Titres[[#This Row],[Coût total]] -> 848.67 | S26: =Titres[[#This Row],[Gain non réalisé ($)]]/Titres[[#This Row],[Coût total]] -> 5.940987 | T26: 0.5 | U26: =4*Titres[[#This Row],[Dividende trimestriel]] -> 2 | V26: =Titres[[#This Row],[Dividende annuel]]*Titres[[#This Row],[Nb d''actions]] -> 2 | W26: =Titres[[#This Row],[Dividende annuel]]/Titres[[#This Row],[Prix actuel]] -> 0.0020171051 | X26: =Titres[[#This Row],[Dividende annuel]]/Titres[[#This Row],[Coût moyen]] -> 0.0140007 | Z26: =(((Titres[[#This Row],[Valeur au marché ($ local)]]-Titres[[#This Row],[Coût total]])+Titres[[#This Row],[Total - dividendes reçus]])/Titres[[#This Row],[Coût total]]) -> 6.5302765 | AA26: =SUM(Titres[[#This Row],[Janvier 2019]:[Août 2024]]) -> 84.18 | CE26: =25.55-3.83 -> 21.72 | CM26: 62.46 | CZ26: 0.25 | DC26: 0.25 | DF26: 0.25 | DI26: 0.5
B27: =IF(C27="","",_xlfn.XLOOKUP(C27,Type_Compte,Num_Compte)) -> 20K6HU7 | C27: REER (USD) | D27: #VALUE! | E27: {=_FV(Titres[[#This Row],[Action]],"Code mnémonique",TRUE)} -> GE | F27: {=_FV(D27,"Change")} -> New York Stock Exchange | G27: {=IFERROR(_FV(Titres[[#This Row],[Action]],"Industrie"),"")} -> Aerospace & Defense | H27: Actions américaines | I27: {=_FV(D27,"Devise")} -> USD | J27: 6 | K27: 238.53 | L27: =J27*K27 -> 1431.18 | M27: {=_FV(D27,"Prix")} -> 286.74 | N27: =J27*M27 -> 1720.44 | O27: =IF(Titres[[#This Row],[Devise]]="CAD",Titres[[#This Row],[Valeur au marché ($ local)]],Titres[[#This Row],[Valeur au marché ($ local)]]*Ressources!$I$3) -> 2350.121 | P27: {=(Titres[[#This Row],[Prix actuel]]-_FV(Titres[[#This Row],[Action]],"Clôture précédente",TRUE))*Titres[[#This Row],[Nb d''actions]]} -> -101.16 | Q27: =Titres[[#This Row],[Variation du jour ($)]]/(Titres[[#This Row],[Valeur au marché ($ local)]]-Titres[[#This Row],[Variation du jour ($)]]) -> -0.055533597 | R27: =Titres[[#This Row],[Valeur au marché ($ local)]]-Titres[[#This Row],[Coût total]] -> 289.26 | S27: =Titres[[#This Row],[Gain non réalisé ($)]]/Titres[[#This Row],[Coût total]] -> 0.20211294 | T27: 0.08 | U27: =4*Titres[[#This Row],[Dividende trimestriel]] -> 0.32 | V27: =Titres[[#This Row],[Dividende annuel]]*Titres[[#This Row],[Nb d''actions]] -> 1.92 | W27: =Titres[[#This Row],[Dividende annuel]]/Titres[[#This Row],[Prix actuel]] -> 0.0011159936 | X27: =Titres[[#This Row],[Dividende annuel]]/Titres[[#This Row],[Coût moyen]] -> 0.0013415503 | Y27: 0 | Z27: =(((Titres[[#This Row],[Valeur au marché ($ local)]]-Titres[[#This Row],[Coût total]])+Titres[[#This Row],[Total - dividendes reçus]])/Titres[[#This Row],[Coût total]]) -> 0.22705041 | AA27: =SUM(Titres[[#This Row],[Janvier 2019]:[Août 2024]]) -> 35.69 | AB27: 0.55 | AC27: 21.48 | AE27: 0.55 | AH27: 0.55 | AK27: 0.55 | AN27: 0.55 | AQ27: 0.55 | AT27: 0.55 | AW27: 0.55 | AZ27: 0.55 | BC27: 0.55 | BF27: 0.55 | BI27: 0.48 | BL27: 0.48 | BO27: 0.48 | BR27: 0.48 | BU27: 0.48 | BX27: 0.48 | CA27: 0.48 | CD27: 0.48 | CG27: 0.48 | CJ27: 0.48 | CM27: 1.68 | CP27: 1.68 | CS27: 1.68 | CV27: 1.68 | CY27: 2.16 | DB27: 2.16 | DE27: 2.16 | DH27: 2.16
B28: =IF(C28="","",_xlfn.XLOOKUP(C28,Type_Compte,Num_Compte)) -> 20K6HU7 | C28: REER (USD) | D28: #VALUE! | E28: {=_FV(Titres[[#This Row],[Action]],"Code mnémonique",TRUE)} -> GIS | F28: {=_FV(D28,"Change")} -> New York Stock Exchange | G28: {=IFERROR(_FV(Titres[[#This Row],[Action]],"Industrie"),"")} -> Food & Tobacco | H28: Actions américaines | I28: {=_FV(D28,"Devise")} -> USD | J28: 129 | K28: 50.95 | L28: =J28*K28 -> 6572.55 | M28: {=_FV(D28,"Prix")} -> 35.055 | N28: =J28*M28 -> 4522.095 | O28: =IF(Titres[[#This Row],[Devise]]="CAD",Titres[[#This Row],[Valeur au marché ($ local)]],Titres[[#This Row],[Valeur au marché ($ local)]]*Ressources!$I$3) -> 6177.1818 | P28: {=(Titres[[#This Row],[Prix actuel]]-_FV(Titres[[#This Row],[Action]],"Clôture précédente",TRUE))*Titres[[#This Row],[Nb d''actions]]} -> -29.025 | Q28: =Titres[[#This Row],[Variation du jour ($)]]/(Titres[[#This Row],[Valeur au marché ($ local)]]-Titres[[#This Row],[Variation du jour ($)]]) -> -0.006377551 | R28: =Titres[[#This Row],[Valeur au marché ($ local)]]-Titres[[#This Row],[Coût total]] -> -2050.455 | S28: =Titres[[#This Row],[Gain non réalisé ($)]]/Titres[[#This Row],[Coût total]] -> -0.31197252 | T28: 0.61 | U28: =4*Titres[[#This Row],[Dividende trimestriel]] -> 2.44 | V28: =Titres[[#This Row],[Dividende annuel]]*Titres[[#This Row],[Nb d''actions]] -> 314.76 | W28: =Titres[[#This Row],[Dividende annuel]]/Titres[[#This Row],[Prix actuel]] -> 0.069604907 | X28: =Titres[[#This Row],[Dividende annuel]]/Titres[[#This Row],[Coût moyen]] -> 0.047890088 | Y28: 3 | Z28: =(((Titres[[#This Row],[Valeur au marché ($ local)]]-Titres[[#This Row],[Coût total]])+Titres[[#This Row],[Total - dividendes reçus]])/Titres[[#This Row],[Coût total]]) -> -0.25849556 | AA28: =SUM(Titres[[#This Row],[Janvier 2019]:[Août 2024]]) -> 351.48 | AC28: 14.21 | AF28: 14.21 | AI28: 14.21 | AL28: 14.21 | AO28: 14.21 | AR28: 14.21 | AU28: 14.21 | AX28: 14.79 | BA28: 14.79 | BD28: 14.79 | BG28: 14.79 | BJ28: 14.79 | BM28: 14.79 | BP28: 14.79 | BS28: 15.66 | BV28: 15.66 | BY28: 15.66 | CB28: 15.66 | CE28: 17.11 | CH28: 17.11 | CK28: 17.11 | CN28: 17.11 | CQ28: 17.4 | CT28: 17.4 | CW28: 17.4 | CZ28: 17.4 | DC28: 17.69 | DF28: 78.69 | DI28: 78.69
B29: =IF(C29="","",_xlfn.XLOOKUP(C29,Type_Compte,Num_Compte)) -> 20K6HZ6 | C29: CELI (CAD) | D29: #VALUE! | E29: {=_FV(Titres[[#This Row],[Action]],"Code mnémonique",TRUE)} -> ENB | F29: {=_FV(D29,"Change")} -> Toronto Stock Exchange | G29: {=IFERROR(_FV(Titres[[#This Row],[Action]],"Industrie"),"")} -> Oil & Gas Related Equipment and Services | H29: Actions canadiennes | I29: {=_FV(D29,"Devise")} -> CAD | J29: 53 | K29: 55.63 | L29: =J29*K29 -> 2948.39 | M29: {=_FV(D29,"Prix")} -> 70.98 | N29: =J29*M29 -> 3761.94 | O29: =IF(Titres[[#This Row],[Devise]]="CAD",Titres[[#This Row],[Valeur au marché ($ local)]],Titres[[#This Row],[Valeur au marché ($ local)]]*Ressources!$I$3) -> 3761.94 | P29: {=(Titres[[#This Row],[Prix actuel]]-_FV(Titres[[#This Row],[Action]],"Clôture précédente",TRUE))*Titres[[#This Row],[Nb d''actions]]} -> -18.02 | Q29: =Titres[[#This Row],[Variation du jour ($)]]/(Titres[[#This Row],[Valeur au marché ($ local)]]-Titres[[#This Row],[Variation du jour ($)]]) -> -0.0047672462 | R29: =Titres[[#This Row],[Valeur au marché ($ local)]]-Titres[[#This Row],[Coût total]] -> 813.55 | S29: =Titres[[#This Row],[Gain non réalisé ($)]]/Titres[[#This Row],[Coût total]] -> 0.27593025 | T29: 0.97 | U29: =4*Titres[[#This Row],[Dividende trimestriel]] -> 3.88 | V29: =Titres[[#This Row],[Dividende annuel]]*Titres[[#This Row],[Nb d''actions]] -> 205.64 | W29: =Titres[[#This Row],[Dividende annuel]]/Titres[[#This Row],[Prix actuel]] -> 0.054663285 | X29: =Titres[[#This Row],[Dividende annuel]]/Titres[[#This Row],[Coût moyen]] -> 0.06974654 | Y29: 8 | Z29: =(((Titres[[#This Row],[Valeur au marché ($ local)]]-Titres[[#This Row],[Coût total]])+Titres[[#This Row],[Total - dividendes reçus]])/Titres[[#This Row],[Coût total]]) -> 0.60583234 | AA29: =SUM(Titres[[#This Row],[Janvier 2019]:[Août 2024]]) -> 972.68 | AD29: 39.11 | AG29: 39.11 | AJ29: 39.11 | AM29: 39.11 | AP29: 42.93 | AS29: 42.93 | AV29: 42.93 | AY29: 42.93 | BB29: 44.26 | BE29: 44.26 | BH29: 44.26 | BK29: 44.26 | BN29: 45.58 | BQ29: 45.58 | BT29: 45.58 | BW29: 45.58 | BZ29: 47.04 | CC29: 47.04 | CF29: 47.04 | CI29: 47.04 | CL29: 48.5 | CO29: 48.5 | CR29: 48.5 | CU29: 48.5 | CX29: 49.95 | DA29: 49.95 | DD29: 49.95 | DG29: 49.95
B30: =IF(C30="","",_xlfn.XLOOKUP(C30,Type_Compte,Num_Compte)) -> 20K6HZ6 | C30: CELI (CAD) | D30: #VALUE! | E30: {=_FV(Titres[[#This Row],[Action]],"Code mnémonique",TRUE)} -> FTS | F30: {=_FV(D30,"Change")} -> Toronto Stock Exchange | G30: {=IFERROR(_FV(Titres[[#This Row],[Action]],"Industrie"),"")} -> Electrical Utilities & IPPs | H30: Actions canadiennes | I30: {=_FV(D30,"Devise")} -> CAD | J30: 80 | K30: 45.81 | L30: =J30*K30 -> 3664.8 | M30: {=_FV(D30,"Prix")} -> 76.44 | N30: =J30*M30 -> 6115.2 | O30: =IF(Titres[[#This Row],[Devise]]="CAD",Titres[[#This Row],[Valeur au marché ($ local)]],Titres[[#This Row],[Valeur au marché ($ local)]]*Ressources!$I$3) -> 6115.2 | P30: {=(Titres[[#This Row],[Prix actuel]]-_FV(Titres[[#This Row],[Action]],"Clôture précédente",TRUE))*Titres[[#This Row],[Nb d''actions]]} -> -41.6 | Q30: =Titres[[#This Row],[Variation du jour ($)]]/(Titres[[#This Row],[Valeur au marché ($ local)]]-Titres[[#This Row],[Variation du jour ($)]]) -> -0.0067567568 | R30: =Titres[[#This Row],[Valeur au marché ($ local)]]-Titres[[#This Row],[Coût total]] -> 2450.4 | S30: =Titres[[#This Row],[Gain non réalisé ($)]]/Titres[[#This Row],[Coût total]] -> 0.6686313 | T30: 0.64 | U30: =4*Titres[[#This Row],[Dividende trimestriel]] -> 2.56 | V30: =Titres[[#This Row],[Dividende annuel]]*Titres[[#This Row],[Nb d''actions]] -> 204.8 | W30: =Titres[[#This Row],[Dividende annuel]]/Titres[[#This Row],[Prix actuel]] -> 0.033490319 | X30: =Titres[[#This Row],[Dividende annuel]]/Titres[[#This Row],[Coût moyen]] -> 0.055882995 | Y30: 16 | Z30: =(((Titres[[#This Row],[Valeur au marché ($ local)]]-Titres[[#This Row],[Coût total]])+Titres[[#This Row],[Total - dividendes reçus]])/Titres[[#This Row],[Coût total]]) -> 0.80004366 | AA30: =SUM(Titres[[#This Row],[Janvier 2019]:[Août 2024]]) -> 481.6 | AD30: 18 | AG30: 18 | AJ30: 18 | AM30: 19.1 | AP30: 19.1 | AS30: 19.1 | AV30: 19.1 | AY30: 20.2 | BB30: 20.2 | BE30: 20.2 | BH30: 20.2 | BK30: 21.4 | BN30: 21.4 | BQ30: 21.4 | BT30: 21.4 | BW30: 22.6 | BZ30: 22.6 | CC30: 22.6 | CF30: 22.6 | CI30: 23.6 | CL30: 23.6 | CO30: 47.2 | CR30: 47.2 | CU30: 49.2 | CX30: 49.2 | DA30: 49.2 | DD30: 49.2
B31: =IF(C31="","",_xlfn.XLOOKUP(C31,Type_Compte,Num_Compte)) -> 20K6HZ6 | C31: CELI (CAD) | D31: #VALUE! | E31: {=_FV(Titres[[#This Row],[Action]],"Code mnémonique",TRUE)} -> WN | F31: {=_FV(D31,"Change")} -> Toronto Stock Exchange | G31: {=IFERROR(_FV(Titres[[#This Row],[Action]],"Industrie"),"")} -> Food & Drug Retailing | H31: Actions canadiennes | I31: {=_FV(D31,"Devise")} -> CAD | J31: 90 | K31: 48.6433 | L31: =J31*K31 -> 4377.897 | M31: {=_FV(D31,"Prix")} -> 97.15 | N31: =J31*M31 -> 8743.5 | O31: =IF(Titres[[#This Row],[Devise]]="CAD",Titres[[#This Row],[Valeur au marché ($ local)]],Titres[[#This Row],[Valeur au marché ($ local)]]*Ressources!$I$3) -> 8743.5 | P31: {=(Titres[[#This Row],[Prix actuel]]-_FV(Titres[[#This Row],[Action]],"Clôture précédente",TRUE))*Titres[[#This Row],[Nb d''actions]]} -> 70.2 | Q31: =Titres[[#This Row],[Variation du jour ($)]]/(Titres[[#This Row],[Valeur au marché ($ local)]]-Titres[[#This Row],[Variation du jour ($)]]) -> 0.0080938051 | R31: =Titres[[#This Row],[Valeur au marché ($ local)]]-Titres[[#This Row],[Coût total]] -> 4365.603 | S31: =Titres[[#This Row],[Gain non réalisé ($)]]/Titres[[#This Row],[Coût total]] -> 0.9971918 | T31: 0.298 | U31: =4*Titres[[#This Row],[Dividende trimestriel]] -> 1.192 | V31: =Titres[[#This Row],[Dividende annuel]]*Titres[[#This Row],[Nb d''actions]] -> 107.28 | W31: =Titres[[#This Row],[Dividende annuel]]/Titres[[#This Row],[Prix actuel]] -> 0.012269686 | X31: =Titres[[#This Row],[Dividende annuel]]/Titres[[#This Row],[Coût moyen]] -> 0.024504916 | Y31: 11 | Z31: =(((Titres[[#This Row],[Valeur au marché ($ local)]]-Titres[[#This Row],[Coût total]])+Titres[[#This Row],[Total - dividendes reçus]])/Titres[[#This Row],[Coût total]]) -> 1.017544 | AA31: =SUM(Titres[[#This Row],[Janvier 2019]:[Août 2024]]) -> 89.1 | CE31: =25.55-3.83 -> 21.72 | CJ31: 21.39 | CM31: 21.39 | CP31: 24.6 | CS31: 24.6 | CV31: 24.6 | CY31: 24.6 | DB31: 26.81 | DE31: 26.81 | DG31: 51.2 | DH31: 26.81
B32: =IF(C32="","",_xlfn.XLOOKUP(C32,Type_Compte,Num_Compte)) -> 20K6HU7 | C32: REER (USD) | D32: #VALUE! | E32: {=_FV(Titres[[#This Row],[Action]],"Code mnémonique",TRUE)} -> GSK | F32: {=_FV(D32,"Change")} -> New York Stock Exchange | G32: {=IFERROR(_FV(Titres[[#This Row],[Action]],"Industrie"),"")} -> Pharmaceuticals | H32: Actions internationales | I32: {=_FV(D32,"Devise")} -> USD | J32: 80 | K32: 59.67 | L32: =J32*K32 -> 4773.6 | M32: {=_FV(D32,"Prix")} -> 56.12 | N32: =J32*M32 -> 4489.6 | O32: =IF(Titres[[#This Row],[Devise]]="CAD",Titres[[#This Row],[Valeur au marché ($ local)]],Titres[[#This Row],[Valeur au marché ($ local)]]*Ressources!$I$3) -> 6132.7936 | P32: {=(Titres[[#This Row],[Prix actuel]]-_FV(Titres[[#This Row],[Action]],"Clôture précédente",TRUE))*Titres[[#This Row],[Nb d''actions]]} -> -98.4 | Q32: =Titres[[#This Row],[Variation du jour ($)]]/(Titres[[#This Row],[Valeur au marché ($ local)]]-Titres[[#This Row],[Variation du jour ($)]]) -> -0.021447254 | R32: =Titres[[#This Row],[Valeur au marché ($ local)]]-Titres[[#This Row],[Coût total]] -> -284 | S32: =Titres[[#This Row],[Gain non réalisé ($)]]/Titres[[#This Row],[Coût total]] -> -0.059493883 | T32: 0.36 | U32: =4*Titres[[#This Row],[Dividende trimestriel]] -> 1.44 | V32: =Titres[[#This Row],[Dividende annuel]]*Titres[[#This Row],[Nb d''actions]] -> 115.2 | W32: =Titres[[#This Row],[Dividende annuel]]/Titres[[#This Row],[Prix actuel]] -> 0.025659301 | X32: =Titres[[#This Row],[Dividende annuel]]/Titres[[#This Row],[Coût moyen]] -> 0.02413273 | Y32: 0 | Z32: =(((Titres[[#This Row],[Valeur au marché ($ local)]]-Titres[[#This Row],[Coût total]])+Titres[[#This Row],[Total - dividendes reçus]])/Titres[[#This Row],[Coût total]]) -> 0.039542484 | AA32: =SUM(Titres[[#This Row],[Janvier 2019]:[Août 2024]]) -> 472.76 | AB32: 11.97 | AE32: 14.85 | AH32: 11.64 | AK32: 11.46 | AN32: 12.31 | AQ32: 13.98 | AT32: 11.66 | AW32: 12.13 | AZ32: 12.73 | BC32: 15.73 | BF32: 12.97 | BI32: 12.75 | BL32: 12.73 | BO32: 14.9 | BR32: 33.39 | BU32: 28.96 | BX32: 26.18 | CA32: 26.75 | CD32: 28.28 | CG32: 26.88 | CJ32: 27.91 | CM32: 61.86 | CP32: 30.74 | CS32: 30.83 | CV32: 29.55 | CY32: 32.01 | DB32: 34.18 | DE32: 33.8 | DH32: 34.05
B33: =IF(C33="","",_xlfn.XLOOKUP(C33,Type_Compte,Num_Compte)) -> 20K6HZ6 | C33: CELI (CAD) | D33: #VALUE! | E33: {=_FV(Titres[[#This Row],[Action]],"Code mnémonique",TRUE)} -> GEI | F33: {=_FV(D33,"Change")} -> Toronto Stock Exchange | G33: {=IFERROR(_FV(Titres[[#This Row],[Action]],"Industrie"),"")} -> Oil & Gas | H33: Actions canadiennes | I33: {=_FV(D33,"Devise")} -> CAD | J33: 200 | K33: 23.39 | L33: =J33*K33 -> 4678 | M33: {=_FV(D33,"Prix")} -> 27.48 | N33: =J33*M33 -> 5496 | O33: =IF(Titres[[#This Row],[Devise]]="CAD",Titres[[#This Row],[Valeur au marché ($ local)]],Titres[[#This Row],[Valeur au marché ($ local)]]*Ressources!$I$3) -> 5496 | P33: {=(Titres[[#This Row],[Prix actuel]]-_FV(Titres[[#This Row],[Action]],"Clôture précédente",TRUE))*Titres[[#This Row],[Nb d''actions]]} -> 48 | Q33: =Titres[[#This Row],[Variation du jour ($)]]/(Titres[[#This Row],[Valeur au marché ($ local)]]-Titres[[#This Row],[Variation du jour ($)]]) -> 0.0088105727 | R33: =Titres[[#This Row],[Valeur au marché ($ local)]]-Titres[[#This Row],[Coût total]] -> 818 | S33: =Titres[[#This Row],[Gain non réalisé ($)]]/Titres[[#This Row],[Coût total]] -> 0.17486105 | T33: 0.43 | U33: =4*Titres[[#This Row],[Dividende trimestriel]] -> 1.72 | V33: =Titres[[#This Row],[Dividende annuel]]*Titres[[#This Row],[Nb d''actions]] -> 344 | W33: =Titres[[#This Row],[Dividende annuel]]/Titres[[#This Row],[Prix actuel]] -> 0.062590975 | X33: =Titres[[#This Row],[Dividende annuel]]/Titres[[#This Row],[Coût moyen]] -> 0.073535699 | Y33: 3 | Z33: =(((Titres[[#This Row],[Valeur au marché ($ local)]]-Titres[[#This Row],[Coût total]])+Titres[[#This Row],[Total - dividendes reçus]])/Titres[[#This Row],[Coût total]]) -> 0.27661394 | AA33: =SUM(Titres[[#This Row],[Janvier 2019]:[Août 2024]]) -> 476 | CA33: 78 | CD33: 78 | CG33: 78 | CJ33: 78 | CM33: 82 | CP33: 82 | CS33: 82 | CV33: 82 | CY33: 86 | DB33: 86 | DE33: 86 | DH33: 86
B34: =IF(C34="","",_xlfn.XLOOKUP(C34,Type_Compte,Num_Compte)) -> 20K6HU7 | C34: REER (USD) | D34: #VALUE! | E34: {=_FV(Titres[[#This Row],[Action]],"Code mnémonique",TRUE)} -> HLN | F34: {=_FV(D34,"Change")} -> New York Stock Exchange | G34: {=IFERROR(_FV(Titres[[#This Row],[Action]],"Industrie"),"")} -> Pharmaceuticals | H34: Actions internationales | I34: {=_FV(D34,"Devise")} -> USD | J34: 100 | K34: 7.28 | L34: =J34*K34 -> 728 | M34: {=_FV(D34,"Prix")} -> 9.525 | N34: =J34*M34 -> 952.5 | O34: =IF(Titres[[#This Row],[Devise]]="CAD",Titres[[#This Row],[Valeur au marché ($ local)]],Titres[[#This Row],[Valeur au marché ($ local)]]*Ressources!$I$3) -> 1301.115 | P34: {=(Titres[[#This Row],[Prix actuel]]-_FV(Titres[[#This Row],[Action]],"Clôture précédente",TRUE))*Titres[[#This Row],[Nb d''actions]]} -> -15.5 | Q34: =Titres[[#This Row],[Variation du jour ($)]]/(Titres[[#This Row],[Valeur au marché ($ local)]]-Titres[[#This Row],[Variation du jour ($)]]) -> -0.016012397 | R34: =Titres[[#This Row],[Valeur au marché ($ local)]]-Titres[[#This Row],[Coût total]] -> 224.5 | S34: =Titres[[#This Row],[Gain non réalisé ($)]]/Titres[[#This Row],[Coût total]] -> 0.30837912 | T34: 0.06 | U34: =4*Titres[[#This Row],[Dividende trimestriel]] -> 0.24 | V34: =Titres[[#This Row],[Dividende annuel]]*Titres[[#This Row],[Nb d''actions]] -> 24 | W34: =Titres[[#This Row],[Dividende annuel]]/Titres[[#This Row],[Prix actuel]] -> 0.02519685 | X34: =Titres[[#This Row],[Dividende annuel]]/Titres[[#This Row],[Coût moyen]] -> 0.032967033 | Y34: 0 | Z34: =(((Titres[[#This Row],[Valeur au marché ($ local)]]-Titres[[#This Row],[Coût total]])+Titres[[#This Row],[Total - dividendes reçus]])/Titres[[#This Row],[Coût total]]) -> 0.33707418 | AA34: =SUM(Titres[[#This Row],[Janvier 2019]:[Août 2024]]) -> 20.89 | CA34: 5.97 | CG34: 4.39 | CN34: 10.53 | CR34: 5.27 | DA34: 12.46 | DD34: 5.68
B35: =IF(C35="","",_xlfn.XLOOKUP(C35,Type_Compte,Num_Compte)) -> 20K6HZ6 | C35: CELI (CAD) | D35: #VALUE! | E35: {=_FV(Titres[[#This Row],[Action]],"Code mnémonique",TRUE)} -> GWO | F35: {=_FV(D35,"Change")} -> Toronto Stock Exchange | G35: {=IFERROR(_FV(Titres[[#This Row],[Action]],"Industrie"),"")} -> Insurance | H35: Actions canadiennes | I35: {=_FV(D35,"Devise")} -> CAD | J35: 145 | K35: 32.11 | L35: =J35*K35 -> 4655.95 | M35: {=_FV(D35,"Prix")} -> 70.85 | N35: =J35*M35 -> 10273.25 | O35: =IF(Titres[[#This Row],[Devise]]="CAD",Titres[[#This Row],[Valeur au marché ($ local)]],Titres[[#This Row],[Valeur au marché ($ local)]]*Ressources!$I$3) -> 10273.25 | P35: {=(Titres[[#This Row],[Prix actuel]]-_FV(Titres[[#This Row],[Action]],"Clôture précédente",TRUE))*Titres[[#This Row],[Nb d''actions]]} -> 42.05 | Q35: =Titres[[#This Row],[Variation du jour ($)]]/(Titres[[#This Row],[Valeur au marché ($ local)]]-Titres[[#This Row],[Variation du jour ($)]]) -> 0.0041099773 | R35: =Titres[[#This Row],[Valeur au marché ($ local)]]-Titres[[#This Row],[Coût total]] -> 5617.3 | S35: =Titres[[#This Row],[Gain non réalisé ($)]]/Titres[[#This Row],[Coût total]] -> 1.2064777 | T35: 0.61 | U35: =4*Titres[[#This Row],[Dividende trimestriel]] -> 2.44 | V35: =Titres[[#This Row],[Dividende annuel]]*Titres[[#This Row],[Nb d''actions]] -> 353.8 | W35: =Titres[[#This Row],[Dividende annuel]]/Titres[[#This Row],[Prix actuel]] -> 0.034438956 | X35: =Titres[[#This Row],[Dividende annuel]]/Titres[[#This Row],[Coût moyen]] -> 0.075988789 | Y35: 8 | Z35: =(((Titres[[#This Row],[Valeur au marché ($ local)]]-Titres[[#This Row],[Coût total]])+Titres[[#This Row],[Total - dividendes reçus]])/Titres[[#This Row],[Coût total]]) -> 1.4397577 | AA35: =SUM(Titres[[#This Row],[Janvier 2019]:[Août 2024]]) -> 1086.14 | AD35: 18.59 | AG35: 18.59 | AJ35: 18.59 | AM35: 18.59 | AP35: 19.71 | AS35: 19.71 | AV35: 19.71 | AY35: 19.71 | BB35: 63.51 | BE35: 63.51 | BH35: 63.51 | BK35: 71.05 | BN35: 71.05 | BQ35: 71.05 | BT35: 71.05 | BW35: 71.05 | CC35: 75.4 | CF35: 75.4 | CI35: 75.4 | CL35: 80.48 | CP35: 80.48 | CR35: 80.48 | CU35: 80.48 | CX35: 88.45 | DB35: 88.45 | DD35: 88.45 | DG35: 88.45
B36: =IF(C36="","",_xlfn.XLOOKUP(C36,Type_Compte,Num_Compte)) -> 20K6HZ6 | C36: CELI (CAD) | D36: #VALUE! | E36: {=_FV(Titres[[#This Row],[Action]],"Code mnémonique",TRUE)} -> HR.UN | F36: {=_FV(D36,"Change")} -> Toronto Stock Exchange | G36: {=IFERROR(_FV(Titres[[#This Row],[Action]],"Industrie"),"")} | H36: REIT | I36: {=_FV(D36,"Devise")} -> CAD | J36: 160 | K36: 18.67 | L36: =J36*K36 -> 2987.2 | M36: {=_FV(D36,"Prix")} -> 10.35 | N36: =J36*M36 -> 1656 | O36: =IF(Titres[[#This Row],[Devise]]="CAD",Titres[[#This Row],[Valeur au marché ($ local)]],Titres[[#This Row],[Valeur au marché ($ local)]]*Ressources!$I$3) -> 1656 | P36: {=(Titres[[#This Row],[Prix actuel]]-_FV(Titres[[#This Row],[Action]],"Clôture précédente",TRUE))*Titres[[#This Row],[Nb d''actions]]} -> 6.4 | Q36: =Titres[[#This Row],[Variation du jour ($)]]/(Titres[[#This Row],[Valeur au marché ($ local)]]-Titres[[#This Row],[Variation du jour ($)]]) -> 0.0038797284 | R36: =Titres[[#This Row],[Valeur au marché ($ local)]]-Titres[[#This Row],[Coût total]] -> -1331.2 | S36: =Titres[[#This Row],[Gain non réalisé ($)]]/Titres[[#This Row],[Coût total]] -> -0.44563471 | T36: 0.05 | U36: =4*Titres[[#This Row],[Dividende trimestriel]] -> 0.2 | V36: =Titres[[#This Row],[Dividende annuel]]*Titres[[#This Row],[Nb d''actions]] -> 32 | W36: =Titres[[#This Row],[Dividende annuel]]/Titres[[#This Row],[Prix actuel]] -> 0.019323671 | X36: =Titres[[#This Row],[Dividende annuel]]/Titres[[#This Row],[Coût moyen]] -> 0.010712373 | Y36: 0 | Z36: =(((Titres[[#This Row],[Valeur au marché ($ local)]]-Titres[[#This Row],[Coût total]])+Titres[[#This Row],[Total - dividendes reçus]])/Titres[[#This Row],[Coût total]]) -> -0.27237547 | AA36: =SUM(Titres[[#This Row],[Janvier 2019]:[Août 2024]]) -> 517.56 | AO36: 18.4 | AP36: 18.4 | AR36: 18.4 | AS36: 9.2 | AT36: 9.2 | AU36: 9.2 | AV36: 9.2 | AW36: 9.2 | AX36: 9.2 | AY36: 9.2 | AZ36: 9.2 | BA36: 9.2 | BB36: 9.2 | BC36: 9.2 | BD36: 9.2 | BE36: 9.2 | BF36: 9.2 | BG36: 9.2 | BH36: 9.2 | BI36: 9.2 | BJ36: 9.2 | BK36: 9.2 | BL36: 25.2 | BM36: 6.93 | BN36: 6.93 | BO36: 6.93 | BP36: 6.93 | BQ36: 7.33 | BR36: 7.33 | BS36: 7.33 | BT36: 7.33 | BU36: 7.33 | BV36: 7.33 | BW36: 7.33 | BX36: 15.33 | BY36: 8 | BZ36: 8 | CA36: 8 | CB36: 8 | CC36: 8 | CD36: 8 | CE36: 8 | CF36: 8 | CG36: 8 | CH36: 8 | CI36: 8 | CJ36: 24 | CK36: 8 | CL36: 8 | CM36: 8 | CN36: 8 | CO36: 8 | CP36: 8 | CQ36: 8 | CR36: 8 | CS36: 8 | CT36: 8 | CU36: 8 | CV36: 27.2 | CW36: 8 | CX36: 8 | CY36: 8 | CZ36: 8 | DA36: 8 | DB36: 8 | DC36: 8 | DD36: 8 | DE36: 8 | DF36: 8 | DG36: 8 | DH36: 8 | DI36: 8
B37: =IF(C37="","",_xlfn.XLOOKUP(C37,Type_Compte,Num_Compte)) -> 20K6HZ6 | C37: CELI (CAD) | D37: #VALUE! | E37: {=_FV(Titres[[#This Row],[Action]],"Code mnémonique",TRUE)} -> IAG | F37: {=_FV(D37,"Change")} -> Toronto Stock Exchange | G37: {=IFERROR(_FV(Titres[[#This Row],[Action]],"Industrie"),"")} -> Insurance | H37: Actions canadiennes | I37: {=_FV(D37,"Devise")} -> CAD | J37: 69 | K37: 42.88 | L37: =J37*K37 -> 2958.72 | M37: {=_FV(D37,"Prix")} -> 173.53 | N37: =J37*M37 -> 11973.57 | O37: =IF(Titres[[#This Row],[Devise]]="CAD",Titres[[#This Row],[Valeur au marché ($ local)]],Titres[[#This Row],[Valeur au marché ($ local)]]*Ressources!$I$3) -> 11973.57 | P37: {=(Titres[[#This Row],[Prix actuel]]-_FV(Titres[[#This Row],[Action]],"Clôture précédente",TRUE))*Titres[[#This Row],[Nb d''actions]]} -> 76.59 | Q37: =Titres[[#This Row],[Variation du jour ($)]]/(Titres[[#This Row],[Valeur au marché ($ local)]]-Titres[[#This Row],[Variation du jour ($)]]) -> 0.0064377682 | R37: =Titres[[#This Row],[Valeur au marché ($ local)]]-Titres[[#This Row],[Coût total]] -> 9014.85 | S37: =Titres[[#This Row],[Gain non réalisé ($)]]/Titres[[#This Row],[Coût total]] -> 3.046875 | T37: 0.99 | U37: =4*Titres[[#This Row],[Dividende trimestriel]] -> 3.96 | V37: =Titres[[#This Row],[Dividende annuel]]*Titres[[#This Row],[Nb d''actions]] -> 273.24 | W37: =Titres[[#This Row],[Dividende annuel]]/Titres[[#This Row],[Prix actuel]] -> 0.022820262 | X37: =Titres[[#This Row],[Dividende annuel]]/Titres[[#This Row],[Coût moyen]] -> 0.092350746 | Y37: 2 | Z37: =(((Titres[[#This Row],[Valeur au marché ($ local)]]-Titres[[#This Row],[Coût total]])+Titres[[#This Row],[Total - dividendes reçus]])/Titres[[#This Row],[Coût total]]) -> 3.3499588 | AA37: =SUM(Titres[[#This Row],[Janvier 2019]:[Août 2024]]) -> 896.74 | AD37: 28.64 | AG37: 31.05 | AJ37: 31.05 | AM37: 31.05 | AP37: 33.47 | AS37: 33.47 | AV37: 33.47 | AY37: 33.47 | BB37: 33.47 | BE37: 33.47 | BH37: 33.47 | BK37: 43.13 | BN37: 43.13 | BQ37: 43.13 | BT37: 46.58 | BW37: 46.58 | BZ37: 46.58 | CC37: 52.79 | CF37: 52.79 | CI37: 52.79 | CL37: 56.58 | CO37: 56.58 | CR37: 56.58 | CU37: 62.1 | CX37: 62.1 | DA37: 62.1 | DD37: 68.31 | DG37: 68.31
B38: =IF(C38="","",_xlfn.XLOOKUP(C38,Type_Compte,Num_Compte)) -> 20K6HU7 | C38: REER (USD) | D38: #VALUE! | E38: {=_FV(Titres[[#This Row],[Action]],"Code mnémonique",TRUE)} -> INTC | F38: {=_FV(D38,"Change")} -> Nasdaq Stock Market | G38: {=IFERROR(_FV(Titres[[#This Row],[Action]],"Industrie"),"")} -> Semiconductors & Semiconductor Equipment | H38: Actions américaines | I38: {=_FV(D38,"Devise")} -> USD | J38: 140 | K38: 24.23 | L38: =J38*K38 -> 3392.2 | M38: {=_FV(D38,"Prix")} -> 66.26 | N38: =J38*M38 -> 9276.4 | O38: =IF(Titres[[#This Row],[Devise]]="CAD",Titres[[#This Row],[Valeur au marché ($ local)]],Titres[[#This Row],[Valeur au marché ($ local)]]*Ressources!$I$3) -> 12671.562 | P38: {=(Titres[[#This Row],[Prix actuel]]-_FV(Titres[[#This Row],[Action]],"Clôture précédente",TRUE))*Titres[[#This Row],[Nb d''actions]]} -> 78.4 | Q38: =Titres[[#This Row],[Variation du jour ($)]]/(Titres[[#This Row],[Valeur au marché ($ local)]]-Titres[[#This Row],[Variation du jour ($)]]) -> 0.0085235921 | R38: =Titres[[#This Row],[Valeur au marché ($ local)]]-Titres[[#This Row],[Coût total]] -> 5884.2 | S38: =Titres[[#This Row],[Gain non réalisé ($)]]/Titres[[#This Row],[Coût total]] -> 1.7346265 | T38: 0.125 | U38: =4*Titres[[#This Row],[Dividende trimestriel]] -> 0.5 | V38: =Titres[[#This Row],[Dividende annuel]]*Titres[[#This Row],[Nb d''actions]] -> 70 | W38: =Titres[[#This Row],[Dividende annuel]]/Titres[[#This Row],[Prix actuel]] -> 0.0075460308 | X38: =Titres[[#This Row],[Dividende annuel]]/Titres[[#This Row],[Coût moyen]] -> 0.020635576 | Y38: 8 | Z38: =(((Titres[[#This Row],[Valeur au marché ($ local)]]-Titres[[#This Row],[Coût total]])+Titres[[#This Row],[Total - dividendes reçus]])/Titres[[#This Row],[Coût total]]) -> 1.8671305 | AA38: =SUM(Titres[[#This Row],[Janvier 2019]:[Août 2024]]) -> 449.48 | AD38: 22.05 | AG38: 22.05 | AJ38: 22.05 | AM38: 22.05 | AP38: 23.1 | AS38: 23.1 | AV38: 23.1 | AY38: 23.1 | BB38: 24.33 | BE38: 24.33 | BH38: 24.33 | BK38: 24.33 | BN38: 25.55 | BQ38: 25.55 | BT38: 25.55 | BW38: 25.55 | BZ38: 25.55 | CC38: 8.78 | CF38: 8.75 | CI38: 8.75 | CL38: 8.78 | CO38: 8.75 | CR38: 8.75
B39: =IF(C39="","",_xlfn.XLOOKUP(C39,Type_Compte,Num_Compte)) -> 20K6HU7 | C39: REER (USD) | D39: #VALUE! | E39: {=_FV(Titres[[#This Row],[Action]],"Code mnémonique",TRUE)} -> JNJ | F39: {=_FV(D39,"Change")} -> New York Stock Exchange | G39: {=IFERROR(_FV(Titres[[#This Row],[Action]],"Industrie"),"")} -> Pharmaceuticals | H39: Actions américaines | I39: {=_FV(D39,"Devise")} -> USD | J39: 20 | K39: 119.85 | L39: =J39*K39 -> 2397 | M39: {=_FV(D39,"Prix")} -> 226.16 | N39: =J39*M39 -> 4523.2 | O39: =IF(Titres[[#This Row],[Devise]]="CAD",Titres[[#This Row],[Valeur au marché ($ local)]],Titres[[#This Row],[Valeur au marché ($ local)]]*Ressources!$I$3) -> 6178.6912 | P39: {=(Titres[[#This Row],[Prix actuel]]-_FV(Titres[[#This Row],[Action]],"Clôture précédente",TRUE))*Titres[[#This Row],[Nb d''actions]]} -> -90.6 | Q39: =Titres[[#This Row],[Variation du jour ($)]]/(Titres[[#This Row],[Valeur au marché ($ local)]]-Titres[[#This Row],[Variation du jour ($)]]) -> -0.019636742 | R39: =Titres[[#This Row],[Valeur au marché ($ local)]]-Titres[[#This Row],[Coût total]] -> 2126.2 | S39: =Titres[[#This Row],[Gain non réalisé ($)]]/Titres[[#This Row],[Coût total]] -> 0.88702545 | T39: 1.3 | U39: =4*Titres[[#This Row],[Dividende trimestriel]] -> 5.2 | V39: =Titres[[#This Row],[Dividende annuel]]*Titres[[#This Row],[Nb d''actions]] -> 104 | W39: =Titres[[#This Row],[Dividende annuel]]/Titres[[#This Row],[Prix actuel]] -> 0.022992572 | X39: =Titres[[#This Row],[Dividende annuel]]/Titres[[#This Row],[Coût moyen]] -> 0.043387568 | Y39: 60 | Z39: =(((Titres[[#This Row],[Valeur au marché ($ local)]]-Titres[[#This Row],[Coût total]])+Titres[[#This Row],[Total - dividendes reçus]])/Titres[[#This Row],[Coût total]]) -> 1.0513141 | AA39: =SUM(Titres[[#This Row],[Janvier 2019]:[Août 2024]]) -> 393.8 | AD39: 13.5 | AG39: 14.25 | AJ39: 14.25 | AM39: 14.25 | AP39: 14.25 | AS39: 15.15 | AV39: 15.15 | AY39: 15.15 | BB39: 15.15 | BE39: 15.9 | BH39: 15.9 | BK39: 15.9 | BN39: 15.9 | BQ39: 16.95 | BT39: 16.95 | BW39: 22.6 | BZ39: 22.6 | CC39: 23.8 | CF39: 23.8 | CI39: 23.8 | CL39: 23.8 | CO39: 24.8 | CR39: 24.8 | CU39: 24.8 | CX39: 24.8 | DA39: 26 | DD39: 26 | DG39: 26
B40: =IF(C40="","",_xlfn.XLOOKUP(C40,Type_Compte,Num_Compte)) -> 20K6HZ6 | C40: CELI (CAD) | D40: #VALUE! | E40: {=_FV(Titres[[#This Row],[Action]],"Code mnémonique",TRUE)} -> IGM | F40: {=_FV(D40,"Change")} -> Toronto Stock Exchange | G40: {=IFERROR(_FV(Titres[[#This Row],[Action]],"Industrie"),"")} -> Investment Banking & Investment Services | H40: Actions canadiennes | I40: {=_FV(D40,"Devise")} -> CAD | J40: 85 | K40: 39.05 | L40: =J40*K40 -> 3319.25 | M40: {=_FV(D40,"Prix")} -> 73.22 | N40: =J40*M40 -> 6223.7 | O40: =IF(Titres[[#This Row],[Devise]]="CAD",Titres[[#This Row],[Valeur au marché ($ local)]],Titres[[#This Row],[Valeur au marché ($ local)]]*Ressources!$I$3) -> 6223.7 | P40: {=(Titres[[#This Row],[Prix actuel]]-_FV(Titres[[#This Row],[Action]],"Clôture précédente",TRUE))*Titres[[#This Row],[Nb d''actions]]} -> -114.75 | Q40: =Titres[[#This Row],[Variation du jour ($)]]/(Titres[[#This Row],[Valeur au marché ($ local)]]-Titres[[#This Row],[Variation du jour ($)]]) -> -0.018103795 | R40: =Titres[[#This Row],[Valeur au marché ($ local)]]-Titres[[#This Row],[Coût total]] -> 2904.45 | S40: =Titres[[#This Row],[Gain non réalisé ($)]]/Titres[[#This Row],[Coût total]] -> 0.87503201 | T40: 0.563 | U40: =4*Titres[[#This Row],[Dividende trimestriel]] -> 2.252 | V40: =Titres[[#This Row],[Dividende annuel]]*Titres[[#This Row],[Nb d''actions]] -> 191.42 | W40: =Titres[[#This Row],[Dividende annuel]]/Titres[[#This Row],[Prix actuel]] -> 0.030756624 | X40: =Titres[[#This Row],[Dividende annuel]]/Titres[[#This Row],[Coût moyen]] -> 0.057669654 | Y40: 0 | Z40: =(((Titres[[#This Row],[Valeur au marché ($ local)]]-Titres[[#This Row],[Coût total]])+Titres[[#This Row],[Total - dividendes reçus]])/Titres[[#This Row],[Coût total]]) -> 1.1306861 | AA40: =SUM(Titres[[#This Row],[Janvier 2019]:[Août 2024]]) -> 848.58 | AQ40: 47.81 | AT40: 41.81 | AW40: 47.81 | AZ40: 47.81 | BC40: 47.81 | BF40: 47.81 | BI40: 47.81 | BL40: 47.81 | BO40: 47.81 | BR40: 47.81 | BU40: 41.81 | BX40: 47.81 | CA40: 47.81 | CD40: 47.81 | CG40: 47.81 | CJ40: 47.81 | CM40: 47.81 | CP40: 47.81 | CS40: 47.81 | CV40: 47.81 | CY40: 47.81 | DB40: 47.81 | DE40: 47.81 | DH40: 47.81
B41: =IF(C41="","",_xlfn.XLOOKUP(C41,Type_Compte,Num_Compte)) -> 20K6HZ6 | C41: CELI (CAD) | D41: #VALUE! | E41: {=_FV(Titres[[#This Row],[Action]],"Code mnémonique",TRUE)} -> IFC | F41: {=_FV(D41,"Change")} -> Toronto Stock Exchange | G41: {=IFERROR(_FV(Titres[[#This Row],[Action]],"Industrie"),"")} -> Insurance | H41: Actions canadiennes | I41: {=_FV(D41,"Devise")} -> CAD | J41: 40 | K41: 136.52 | L41: =J41*K41 -> 5460.8 | M41: {=_FV(D41,"Prix")} -> 261.33 | N41: =J41*M41 -> 10453.2 | O41: =IF(Titres[[#This Row],[Devise]]="CAD",Titres[[#This Row],[Valeur au marché ($ local)]],Titres[[#This Row],[Valeur au marché ($ local)]]*Ressources!$I$3) -> 10453.2 | P41: {=(Titres[[#This Row],[Prix actuel]]-_FV(Titres[[#This Row],[Action]],"Clôture précédente",TRUE))*Titres[[#This Row],[Nb d''actions]]} -> -2 | Q41: =Titres[[#This Row],[Variation du jour ($)]]/(Titres[[#This Row],[Valeur au marché ($ local)]]-Titres[[#This Row],[Variation du jour ($)]]) -> -0.00019129237 | R41: =Titres[[#This Row],[Valeur au marché ($ local)]]-Titres[[#This Row],[Coût total]] -> 4992.4 | S41: =Titres[[#This Row],[Gain non réalisé ($)]]/Titres[[#This Row],[Coût total]] -> 0.91422502 | T41: 1.33 | U41: =4*Titres[[#This Row],[Dividende trimestriel]] -> 5.32 | V41: =Titres[[#This Row],[Dividende annuel]]*Titres[[#This Row],[Nb d''actions]] -> 212.8 | W41: =Titres[[#This Row],[Dividende annuel]]/Titres[[#This Row],[Prix actuel]] -> 0.020357403 | X41: =Titres[[#This Row],[Dividende annuel]]/Titres[[#This Row],[Coût moyen]] -> 0.038968649 | Y41: 17 | Z41: =(((Titres[[#This Row],[Valeur au marché ($ local)]]-Titres[[#This Row],[Coût total]])+Titres[[#This Row],[Total - dividendes reçus]])/Titres[[#This Row],[Coût total]]) -> 1.0402139 | AA41: =SUM(Titres[[#This Row],[Janvier 2019]:[Août 2024]]) -> 688 | AM41: 30.4 | AP41: 33.2 | AS41: 33.2 | AV41: 33.2 | AY41: 33.2 | BB41: 33.2 | BE41: 33.2 | BI41: 33.2 | BK41: 36.4 | BN41: 40 | BQ41: 40 | BU41: 40 | BW41: 40 | CC41: 44 | CF41: 44 | CI41: 44 | CM41: 48.4 | CP41: 48.4 | CR41: 48.4 | CU41: 48.4 | CX41: 53.2 | DA41: 53.2 | DD41: 53.2 | DG41: 53.2
B42: =IF(C42="","",_xlfn.XLOOKUP(C42,Type_Compte,Num_Compte)) -> 20K6HZ6 | C42: CELI (CAD) | D42: #VALUE! | E42: {=_FV(Titres[[#This Row],[Action]],"Code mnémonique",TRUE)} -> XEF | F42: {=_FV(D42,"Change")} -> NEO Exchange | G42: {=IFERROR(_FV(Titres[[#This Row],[Action]],"Industrie"),"")} | H42: Actions internationales | I42: {=_FV(D42,"Devise")} -> CAD | J42: 120 | K42: 49.2 | L42: =J42*K42 -> 5904 | M42: {=_FV(D42,"Prix")} -> 48.88 | N42: =J42*M42 -> 5865.6 | O42: =IF(Titres[[#This Row],[Devise]]="CAD",Titres[[#This Row],[Valeur au marché ($ local)]],Titres[[#This Row],[Valeur au marché ($ local)]]*Ressources!$I$3) -> 5865.6 | P42: {=(Titres[[#This Row],[Prix actuel]]-_FV(Titres[[#This Row],[Action]],"Clôture précédente",TRUE))*Titres[[#This Row],[Nb d''actions]]} -> -121.2 | Q42: =Titres[[#This Row],[Variation du jour ($)]]/(Titres[[#This Row],[Valeur au marché ($ local)]]-Titres[[#This Row],[Variation du jour ($)]]) -> -0.020244538 | R42: =Titres[[#This Row],[Valeur au marché ($ local)]]-Titres[[#This Row],[Coût total]] -> -38.4 | S42: =Titres[[#This Row],[Gain non réalisé ($)]]/Titres[[#This Row],[Coût total]] -> -0.006504065 | T42: 0.415 | U42: =4*Titres[[#This Row],[Dividende trimestriel]] -> 1.66 | V42: =Titres[[#This Row],[Dividende annuel]]*Titres[[#This Row],[Nb d''actions]] -> 199.2 | W42: =Titres[[#This Row],[Dividende annuel]]/Titres[[#This Row],[Prix actuel]] -> 0.03396072 | X42: =Titres[[#This Row],[Dividende annuel]]/Titres[[#This Row],[Coût moyen]] -> 0.033739837 | Z42: =(((Titres[[#This Row],[Valeur au marché ($ local)]]-Titres[[#This Row],[Coût total]])+Titres[[#This Row],[Total - dividendes reçus]])/Titres[[#This Row],[Coût total]]) -> -0.0028252033 | AA42: =SUM(Titres[[#This Row],[Janvier 2019]:[Août 2024]]) -> 21.72 | CE42: =25.55-3.83 -> 21.72
B43: =IF(C43="","",_xlfn.XLOOKUP(C43,Type_Compte,Num_Compte)) -> 20K6HZ6 | C43: CELI (CAD) | D43: #VALUE! | E43: {=_FV(Titres[[#This Row],[Action]],"Code mnémonique",TRUE)} -> TD | F43: {=_FV(D43,"Change")} -> Toronto Stock Exchange | G43: {=IFERROR(_FV(Titres[[#This Row],[Action]],"Industrie"),"")} -> Banking Services | H43: Actions canadiennes | I43: {=_FV(D43,"Devise")} -> CAD | J43: 48 | K43: 65.7 | L43: =J43*K43 -> 3153.6 | M43: {=_FV(D43,"Prix")} -> 144.11 | N43: =J43*M43 -> 6917.28 | O43: =IF(Titres[[#This Row],[Devise]]="CAD",Titres[[#This Row],[Valeur au marché ($ local)]],Titres[[#This Row],[Valeur au marché ($ local)]]*Ressources!$I$3) -> 6917.28 | P43: {=(Titres[[#This Row],[Prix actuel]]-_FV(Titres[[#This Row],[Action]],"Clôture précédente",TRUE))*Titres[[#This Row],[Nb d''actions]]} -> -62.4 | Q43: =Titres[[#This Row],[Variation du jour ($)]]/(Titres[[#This Row],[Valeur au marché ($ local)]]-Titres[[#This Row],[Variation du jour ($)]]) -> -0.0089402379 | R43: =Titres[[#This Row],[Valeur au marché ($ local)]]-Titres[[#This Row],[Coût total]] -> 3763.68 | S43: =Titres[[#This Row],[Gain non réalisé ($)]]/Titres[[#This Row],[Coût total]] -> 1.1934551 | T43: 1.08 | U43: =4*Titres[[#This Row],[Dividende trimestriel]] -> 4.32 | V43: =Titres[[#This Row],[Dividende annuel]]*Titres[[#This Row],[Nb d''actions]] -> 207.36 | W43: =Titres[[#This Row],[Dividende annuel]]/Titres[[#This Row],[Prix actuel]] -> 0.029977101 | X43: =Titres[[#This Row],[Dividende annuel]]/Titres[[#This Row],[Coût moyen]] -> 0.065753425 | Y43: 8 | Z43: =(((Titres[[#This Row],[Valeur au marché ($ local)]]-Titres[[#This Row],[Coût total]])+Titres[[#This Row],[Total - dividendes reçus]])/Titres[[#This Row],[Coût total]]) -> 1.4488204 | AA43: =SUM(Titres[[#This Row],[Janvier 2019]:[Août 2024]]) -> 805.32 | AB43: 20.1 | AE43: 22.2 | AH43: 22.2 | AK43: 22.2 | AN43: 22.2 | AQ43: 23.7 | AT43: 23.7 | AX43: 23.7 | BA43: 23.7 | BC43: 23.7 | BG43: 37.92 | BJ43: 37.92 | BL43: 42.72 | BP43: 42.72 | BS43: 42.72 | BU43: 42.72 | BX43: 46.08 | CB43: 46.08 | CD43: 46.08 | CG43: 46.08 | CJ43: 48.96 | CM43: 48.96 | CP43: 48.96 | CS43: 48.96 | CV43: 50.4 | CY43: 50.4 | DB43: 50.4 | DE43: 50.4 | DI43: 51.84
B44: =IF(C44="","",_xlfn.XLOOKUP(C44,Type_Compte,Num_Compte)) -> 20K6HU7 | C44: REER (USD) | D44: #VALUE! | E44: {=_FV(Titres[[#This Row],[Action]],"Code mnémonique",TRUE)} -> MCD | F44: {=_FV(D44,"Change")} -> New York Stock Exchange | G44: {=IFERROR(_FV(Titres[[#This Row],[Action]],"Industrie"),"")} -> Hotels & Entertainment Services | H44: Actions américaines | I44: {=_FV(D44,"Devise")} -> USD | J44: 13 | K44: 116.36 | L44: =J44*K44 -> 1512.68 | M44: {=_FV(D44,"Prix")} -> 301.81 | N44: =J44*M44 -> 3923.53 | O44: =IF(Titres[[#This Row],[Devise]]="CAD",Titres[[#This Row],[Valeur au marché ($ local)]],Titres[[#This Row],[Valeur au marché ($ local)]]*Ressources!$I$3) -> 5359.542 | P44: {=(Titres[[#This Row],[Prix actuel]]-_FV(Titres[[#This Row],[Action]],"Clôture précédente",TRUE))*Titres[[#This Row],[Nb d''actions]]} -> -66.69 | Q44: =Titres[[#This Row],[Variation du jour ($)]]/(Titres[[#This Row],[Valeur au marché ($ local)]]-Titres[[#This Row],[Variation du jour ($)]]) -> -0.016713364 | R44: =Titres[[#This Row],[Valeur au marché ($ local)]]-Titres[[#This Row],[Coût total]] -> 2410.85 | S44: =Titres[[#This Row],[Gain non réalisé ($)]]/Titres[[#This Row],[Coût total]] -> 1.5937607 | T44: 1.86 | U44: =4*Titres[[#This Row],[Dividende trimestriel]] -> 7.44 | V44: =Titres[[#This Row],[Dividende annuel]]*Titres[[#This Row],[Nb d''actions]] -> 96.72 | W44: =Titres[[#This Row],[Dividende annuel]]/Titres[[#This Row],[Prix actuel]] -> 0.024651271 | X44: =Titres[[#This Row],[Dividende annuel]]/Titres[[#This Row],[Coût moyen]] -> 0.063939498 | Y44: 21 | Z44: =(((Titres[[#This Row],[Valeur au marché ($ local)]]-Titres[[#This Row],[Coût total]])+Titres[[#This Row],[Total - dividendes reçus]])/Titres[[#This Row],[Coût total]]) -> 1.8537496 | AA44: =SUM(Titres[[#This Row],[Janvier 2019]:[Août 2024]]) -> 393.28 | AD44: 15.08 | AG44: 15.08 | AJ44: 15.08 | AM44: 16.25 | AP44: 16.25 | AS44: 16.25 | AV44: 16.25 | AY44: 16.77 | BB44: 16.77 | BE44: 16.77 | BH44: 16.77 | BK44: 17.97 | BN44: 17.94 | BQ44: 17.94 | BT44: 17.94 | BW44: 19.76 | BZ44: 19.76 | CC44: 19.76 | CF44: 19.76 | CI44: 21.71 | CL44: 21.71 | CO44: 21.71 | CR44: 21.71 | CU44: 23.01 | CX44: 23.01 | DA44: 23.01 | DD44: 23.01 | DG44: 24.18
B45: =IF(C45="","",_xlfn.XLOOKUP(C45,Type_Compte,Num_Compte)) -> 20K6HU7 | C45: REER (USD) | D45: #VALUE! | E45: {=_FV(Titres[[#This Row],[Action]],"Code mnémonique",TRUE)} -> MSFT | F45: {=_FV(D45,"Change")} -> Nasdaq Stock Market | G45: {=IFERROR(_FV(Titres[[#This Row],[Action]],"Industrie"),"")} -> Software & IT Services | H45: Actions américaines | I45: {=_FV(D45,"Devise")} -> USD | J45: 20 | K45: 40.63 | L45: =J45*K45 -> 812.6 | M45: {=_FV(D45,"Prix")} -> 424.16 | N45: =J45*M45 -> 8483.2 | O45: =IF(Titres[[#This Row],[Devise]]="CAD",Titres[[#This Row],[Valeur au marché ($ local)]],Titres[[#This Row],[Valeur au marché ($ local)]]*Ressources!$I$3) -> 11588.051 | P45: {=(Titres[[#This Row],[Prix actuel]]-_FV(Titres[[#This Row],[Action]],"Clôture précédente",TRUE))*Titres[[#This Row],[Nb d''actions]]} -> 121.8 | Q45: =Titres[[#This Row],[Variation du jour ($)]]/(Titres[[#This Row],[Valeur au marché ($ local)]]-Titres[[#This Row],[Variation du jour ($)]]) -> 0.014566939 | R45: =Titres[[#This Row],[Valeur au marché ($ local)]]-Titres[[#This Row],[Coût total]] -> 7670.6 | S45: =Titres[[#This Row],[Gain non réalisé ($)]]/Titres[[#This Row],[Coût total]] -> 9.4395767 | T45: 0.91 | U45: =4*Titres[[#This Row],[Dividende trimestriel]] -> 3.64 | V45: =Titres[[#This Row],[Dividende annuel]]*Titres[[#This Row],[Nb d''actions]] -> 72.8 | W45: =Titres[[#This Row],[Dividende annuel]]/Titres[[#This Row],[Prix actuel]] -> 0.0085816673 | X45: =Titres[[#This Row],[Dividende annuel]]/Titres[[#This Row],[Coût moyen]] -> 0.089588974 | Y45: 18 | Z45: =(((Titres[[#This Row],[Valeur au marché ($ local)]]-Titres[[#This Row],[Coût total]])+Titres[[#This Row],[Total - dividendes reçus]])/Titres[[#This Row],[Coût total]]) -> 9.9168102 | AA45: =SUM(Titres[[#This Row],[Janvier 2019]:[Août 2024]]) -> 387.8 | AD45: 18.4 | AG45: 18.4 | AJ45: 18.4 | AM45: 20.4 | AP45: 20.4 | AS45: 20.4 | AV45: 20.4 | AY45: 22.4 | BB45: 22.4 | BE45: 22.4 | BH45: 22.4 | BK45: 24.8 | BN45: 12.4 | BQ45: 12.4 | BT45: 12.4 | BW45: 13.6 | BZ45: 13.6 | CC45: 13.6 | CF45: 13.6 | CI45: 15 | CL45: 15 | CO45: 15 | CR45: 15 | CU45: 16.6 | CX45: 16.6 | DA45: 16.6 | DD45: 16.6 | DG45: 18.2
B46: =IF(C46="","",_xlfn.XLOOKUP(C46,Type_Compte,Num_Compte)) -> 20K6HZ6 | C46: CELI (CAD) | D46: #VALUE! | E46: {=_FV(Titres[[#This Row],[Action]],"Code mnémonique",TRUE)} -> #VALUE! | F46: {=_FV(D46,"Change")} -> OTC Markets | G46: {=IFERROR(_FV(Titres[[#This Row],[Action]],"Industrie"),"")} -> Automobiles & Auto Parts | H46: Actions canadiennes | I46: {=_FV(D46,"Devise")} -> USD | J46: 300 | K46: 12.62 | L46: =J46*K46 -> 3786 | M46: {=_FV(D46,"Prix")} -> 0.024 | N46: =J46*M46 -> 7.2 | O46: =IF(Titres[[#This Row],[Devise]]="CAD",Titres[[#This Row],[Valeur au marché ($ local)]],Titres[[#This Row],[Valeur au marché ($ local)]]*Ressources!$I$3) -> 9.8352 | P46: {=(Titres[[#This Row],[Prix actuel]]-_FV(Titres[[#This Row],[Action]],"Clôture précédente",TRUE))*Titres[[#This Row],[Nb d''actions]]} -> -1.8 | Q46: =Titres[[#This Row],[Variation du jour ($)]]/(Titres[[#This Row],[Valeur au marché ($ local)]]-Titres[[#This Row],[Variation du jour ($)]]) -> -0.2 | R46: =Titres[[#This Row],[Valeur au marché ($ local)]]-Titres[[#This Row],[Coût total]] -> -3778.8 | S46: =Titres[[#This Row],[Gain non réalisé ($)]]/Titres[[#This Row],[Coût total]] -> -0.99809826 | T46: 0 | U46: =4*Titres[[#This Row],[Dividende trimestriel]] -> 0 | V46: =Titres[[#This Row],[Dividende annuel]]*Titres[[#This Row],[Nb d''actions]] -> 0 | W46: =Titres[[#This Row],[Dividende annuel]]/Titres[[#This Row],[Prix actuel]] -> 0 | X46: =Titres[[#This Row],[Dividende annuel]]/Titres[[#This Row],[Coût moyen]] -> 0 | Y46: 0 | Z46: =(((Titres[[#This Row],[Valeur au marché ($ local)]]-Titres[[#This Row],[Coût total]])+Titres[[#This Row],[Total - dividendes reçus]])/Titres[[#This Row],[Coût total]]) -> -0.99809826 | AA46: =SUM(Titres[[#This Row],[Janvier 2019]:[Août 2024]]) -> 0
B47: =IF(C47="","",_xlfn.XLOOKUP(C47,Type_Compte,Num_Compte)) -> 20K6HZ6 | C47: CELI (CAD) | D47: #VALUE! | E47: {=_FV(Titres[[#This Row],[Action]],"Code mnémonique",TRUE)} -> L | F47: {=_FV(D47,"Change")} -> Toronto Stock Exchange | G47: {=IFERROR(_FV(Titres[[#This Row],[Action]],"Industrie"),"")} -> Food & Drug Retailing | H47: Actions canadiennes | I47: {=_FV(D47,"Devise")} -> CAD | J47: 140 | K47: 27.9025 | L47: =J47*K47 -> 3906.35 | M47: {=_FV(D47,"Prix")} -> 62.23 | N47: =J47*M47 -> 8712.2 | O47: =IF(Titres[[#This Row],[Devise]]="CAD",Titres[[#This Row],[Valeur au marché ($ local)]],Titres[[#This Row],[Valeur au marché ($ local)]]*Ressources!$I$3) -> 8712.2 | P47: {=(Titres[[#This Row],[Prix actuel]]-_FV(Titres[[#This Row],[Action]],"Clôture précédente",TRUE))*Titres[[#This Row],[Nb d''actions]]} -> 75.6 | Q47: =Titres[[#This Row],[Variation du jour ($)]]/(Titres[[#This Row],[Valeur au marché ($ local)]]-Titres[[#This Row],[Variation du jour ($)]]) -> 0.0087534446 | R47: =Titres[[#This Row],[Valeur au marché ($ local)]]-Titres[[#This Row],[Coût total]] -> 4805.85 | S47: =Titres[[#This Row],[Gain non réalisé ($)]]/Titres[[#This Row],[Coût total]] -> 1.2302661 | T47: 0.141 | U47: =4*Titres[[#This Row],[Dividende trimestriel]] -> 0.564 | V47: =Titres[[#This Row],[Dividende annuel]]*Titres[[#This Row],[Nb d''actions]] -> 78.96 | W47: =Titres[[#This Row],[Dividende annuel]]/Titres[[#This Row],[Prix actuel]] -> 0.0090631528 | X47: =Titres[[#This Row],[Dividende annuel]]/Titres[[#This Row],[Coût moyen]] -> 0.020213243 | Y47: 11 | Z47: =(((Titres[[#This Row],[Valeur au marché ($ local)]]-Titres[[#This Row],[Coût total]])+Titres[[#This Row],[Total - dividendes reçus]])/Titres[[#This Row],[Coût total]]) -> 1.2612208 | AA47: =SUM(Titres[[#This Row],[Janvier 2019]:[Août 2024]]) -> 120.92 | BR47: 6.08 | BU47: 6.08 | BW47: 14.18 | CA47: 14.18 | CD47: 15.61 | CG47: 15.61 | CJ47: 15.61 | CM47: 15.61 | CP47: 17.96 | CS47: 17.96 | CU47: 17.96 | CY47: 17.96 | DB47: 19.75 | DE47: 19.75 | DG47: 19.75
B48: =IF(C48="","",_xlfn.XLOOKUP(C48,Type_Compte,Num_Compte)) -> 20K6HU7 | C48: REER (USD) | D48: #VALUE! | E48: {=_FV(Titres[[#This Row],[Action]],"Code mnémonique",TRUE)} -> PEP | F48: {=_FV(D48,"Change")} -> Nasdaq Stock Market | G48: {=IFERROR(_FV(Titres[[#This Row],[Action]],"Industrie"),"")} -> Beverages | H48: Actions américaines | I48: {=_FV(D48,"Devise")} -> USD | J48: 18 | K48: 96.95 | L48: =J48*K48 -> 1745.1 | M48: {=_FV(D48,"Prix")} -> 154.92 | N48: =J48*M48 -> 2788.56 | O48: =IF(Titres[[#This Row],[Devise]]="CAD",Titres[[#This Row],[Valeur au marché ($ local)]],Titres[[#This Row],[Valeur au marché ($ local)]]*Ressources!$I$3) -> 3809.173 | P48: {=(Titres[[#This Row],[Prix actuel]]-_FV(Titres[[#This Row],[Action]],"Clôture précédente",TRUE))*Titres[[#This Row],[Nb d''actions]]} -> -37.26 | Q48: =Titres[[#This Row],[Variation du jour ($)]]/(Titres[[#This Row],[Valeur au marché ($ local)]]-Titres[[#This Row],[Variation du jour ($)]]) -> -0.013185553 | R48: =Titres[[#This Row],[Valeur au marché ($ local)]]-Titres[[#This Row],[Coût total]] -> 1043.46 | S48: =Titres[[#This Row],[Gain non réalisé ($)]]/Titres[[#This Row],[Coût total]] -> 0.59793708 | T48: 1.423 | U48: =4*Titres[[#This Row],[Dividende trimestriel]] -> 5.692 | V48: =Titres[[#This Row],[Dividende annuel]]*Titres[[#This Row],[Nb d''actions]] -> 102.456 | W48: =Titres[[#This Row],[Dividende annuel]]/Titres[[#This Row],[Prix actuel]] -> 0.036741544 | X48: =Titres[[#This Row],[Dividende annuel]]/Titres[[#This Row],[Coût moyen]] -> 0.058710676 | Y48: 50 | Z48: =(((Titres[[#This Row],[Valeur au marché ($ local)]]-Titres[[#This Row],[Coût total]])+Titres[[#This Row],[Total - dividendes reçus]])/Titres[[#This Row],[Coût total]]) -> 0.84478253 | AA48: =SUM(Titres[[#This Row],[Janvier 2019]:[Août 2024]]) -> 430.77 | AB48: 16.7 | AD48: 16.7 | AG48: 17.19 | AJ48: 17.19 | AN48: 17.19 | AP48: 17.19 | AS48: 18.41 | AV48: 18.41 | AZ48: 18.41 | BB48: 18.41 | BE48: 19.35 | BH48: 19.35 | BL48: 19.35 | BN48: 19.35 | BQ48: 20.7 | BT48: 20.7 | BX48: 20.7 | CC48: 22.77 | CF48: 22.77 | CJ48: 22.77 | CM48: 22.77 | CP48: 24.39 | CR48: 24.39 | CV48: 24.39 | CX48: 24.39 | DA48: 25.61 | DD48: 25.61 | DH48: 25.61
B49: =IF(C49="","",_xlfn.XLOOKUP(C49,Type_Compte,Num_Compte)) -> 20K6HF2 | C49: Marge (USD) | D49: #VALUE! | E49: {=_FV(Titres[[#This Row],[Action]],"Code mnémonique",TRUE)} -> PII | F49: {=_FV(D49,"Change")} -> New York Stock Exchange | G49: {=IFERROR(_FV(Titres[[#This Row],[Action]],"Industrie"),"")} -> Automobiles & Auto Parts | H49: Actions américaines | I49: {=_FV(D49,"Devise")} -> USD | J49: 0 | K49: 106.74 | L49: =J49*K49 -> 0 | M49: {=_FV(D49,"Prix")} -> 61.41 | N49: =J49*M49 -> 0 | O49: =IF(Titres[[#This Row],[Devise]]="CAD",Titres[[#This Row],[Valeur au marché ($ local)]],Titres[[#This Row],[Valeur au marché ($ local)]]*Ressources!$I$3) -> 0 | P49: {=(Titres[[#This Row],[Prix actuel]]-_FV(Titres[[#This Row],[Action]],"Clôture précédente",TRUE))*Titres[[#This Row],[Nb d''actions]]} -> 0 | Q49: =Titres[[#This Row],[Variation du jour ($)]]/(Titres[[#This Row],[Valeur au marché ($ local)]]-Titres[[#This Row],[Variation du jour ($)]]) -> #DIV/0! | R49: =Titres[[#This Row],[Valeur au marché ($ local)]]-Titres[[#This Row],[Coût total]] -> 0 | S49: =Titres[[#This Row],[Gain non réalisé ($)]]/Titres[[#This Row],[Coût total]] -> #DIV/0! | T49: 0.68 | U49: =4*Titres[[#This Row],[Dividende trimestriel]] -> 2.72 | V49: =Titres[[#This Row],[Dividende annuel]]*Titres[[#This Row],[Nb d''actions]] -> 0 | W49: =Titres[[#This Row],[Dividende annuel]]/Titres[[#This Row],[Prix actuel]] -> 0.044292461 | X49: =Titres[[#This Row],[Dividende annuel]]/Titres[[#This Row],[Coût moyen]] -> 0.025482481 | Y49: 17 | Z49: =(((Titres[[#This Row],[Valeur au marché ($ local)]]-Titres[[#This Row],[Coût total]])+Titres[[#This Row],[Total - dividendes reçus]])/Titres[[#This Row],[Coût total]]) -> #DIV/0! | AA49: =SUM(Titres[[#This Row],[Janvier 2019]:[Août 2024]]) -> 110.48 | BZ49: 27.62 | CC49: 27.62 | CE49: 27.62 | CI49: 27.62
B50: =IF(C50="","",_xlfn.XLOOKUP(C50,Type_Compte,Num_Compte)) -> 20K6HZ6 | C50: CELI (CAD) | D50: #VALUE! | E50: {=_FV(Titres[[#This Row],[Action]],"Code mnémonique",TRUE)} -> MFC | F50: {=_FV(D50,"Change")} -> Toronto Stock Exchange | G50: {=IFERROR(_FV(Titres[[#This Row],[Action]],"Industrie"),"")} -> Insurance | H50: Actions canadiennes | I50: {=_FV(D50,"Devise")} -> CAD | J50: 125 | K50: 20.66 | L50: =J50*K50 -> 2582.5 | M50: {=_FV(D50,"Prix")} -> 52.28 | N50: =J50*M50 -> 6535 | O50: =IF(Titres[[#This Row],[Devise]]="CAD",Titres[[#This Row],[Valeur au marché ($ local)]],Titres[[#This Row],[Valeur au marché ($ local)]]*Ressources!$I$3) -> 6535 | P50: {=(Titres[[#This Row],[Prix actuel]]-_FV(Titres[[#This Row],[Action]],"Clôture précédente",TRUE))*Titres[[#This Row],[Nb d''actions]]} -> -48.75 | Q50: =Titres[[#This Row],[Variation du jour ($)]]/(Titres[[#This Row],[Valeur au marché ($ local)]]-Titres[[#This Row],[Variation du jour ($)]]) -> -0.0074045946 | R50: =Titres[[#This Row],[Valeur au marché ($ local)]]-Titres[[#This Row],[Coût total]] -> 3952.5 | S50: =Titres[[#This Row],[Gain non réalisé ($)]]/Titres[[#This Row],[Coût total]] -> 1.5304937 | T50: 0.44 | U50: =4*Titres[[#This Row],[Dividende trimestriel]] -> 1.76 | V50: =Titres[[#This Row],[Dividende annuel]]*Titres[[#This Row],[Nb d''actions]] -> 220 | W50: =Titres[[#This Row],[Dividende annuel]]/Titres[[#This Row],[Prix actuel]] -> 0.033664881 | X50: =Titres[[#This Row],[Dividende annuel]]/Titres[[#This Row],[Coût moyen]] -> 0.085188771 | Y50: 9 | Z50: =(((Titres[[#This Row],[Valeur au marché ($ local)]]-Titres[[#This Row],[Coût total]])+Titres[[#This Row],[Total - dividendes reçus]])/Titres[[#This Row],[Coût total]]) -> 1.8630281 | AA50: =SUM(Titres[[#This Row],[Janvier 2019]:[Août 2024]]) -> 858.77 | AD50: 31.25 | AG50: 31.25 | AJ50: 31.25 | AM50: 31.25 | AP50: 35 | AS50: 35 | AV50: 35 | AY50: 35 | BB50: 35 | BE50: 35 | BH50: 35 | BK50: 41.25 | BN50: 41.25 | BQ50: 41.25 | BT50: 41.25 | BW50: 41.25 | BZ50: 45.63 | CC50: 45.63 | CF50: 45.63 | CI50: 45.63 | CL50: 50 | CO50: 50 | CR50: 50 | CU50: 50 | CX50: 55 | DA50: 55 | DD50: 55 | DG50: 55
B51: =IF(C51="","",_xlfn.XLOOKUP(C51,Type_Compte,Num_Compte)) -> 20K6HZ6 | C51: CELI (CAD) | D51: #VALUE! | E51: {=_FV(Titres[[#This Row],[Action]],"Code mnémonique",TRUE)} -> NTR | F51: {=_FV(D51,"Change")} -> Toronto Stock Exchange | G51: {=IFERROR(_FV(Titres[[#This Row],[Action]],"Industrie"),"")} -> Chemicals | H51: Actions canadiennes | I51: {=_FV(D51,"Devise")} -> CAD | J51: 53 | K51: 56.79 | L51: =J51*K51 -> 3009.87 | M51: {=_FV(D51,"Prix")} -> 99.29 | N51: =J51*M51 -> 5262.37 | O51: =IF(Titres[[#This Row],[Devise]]="CAD",Titres[[#This Row],[Valeur au marché ($ local)]],Titres[[#This Row],[Valeur au marché ($ local)]]*Ressources!$I$3) -> 5262.37 | P51: {=(Titres[[#This Row],[Prix actuel]]-_FV(Titres[[#This Row],[Action]],"Clôture précédente",TRUE))*Titres[[#This Row],[Nb d''actions]]} -> 113.42 | Q51: =Titres[[#This Row],[Variation du jour ($)]]/(Titres[[#This Row],[Valeur au marché ($ local)]]-Titres[[#This Row],[Variation du jour ($)]]) -> 0.022027792 | R51: =Titres[[#This Row],[Valeur au marché ($ local)]]-Titres[[#This Row],[Coût total]] -> 2252.5 | S51: =Titres[[#This Row],[Gain non réalisé ($)]]/Titres[[#This Row],[Coût total]] -> 0.74837119 | T51: 0.757 | U51: =4*Titres[[#This Row],[Dividende trimestriel]] -> 3.028 | V51: =Titres[[#This Row],[Dividende annuel]]*Titres[[#This Row],[Nb d''actions]] -> 160.484 | W51: =Titres[[#This Row],[Dividende annuel]]/Titres[[#This Row],[Prix actuel]] -> 0.030496525 | X51: =Titres[[#This Row],[Dividende annuel]]/Titres[[#This Row],[Coût moyen]] -> 0.053319246 | Y51: 2 | Z51: =(((Titres[[#This Row],[Valeur au marché ($ local)]]-Titres[[#This Row],[Coût total]])+Titres[[#This Row],[Total - dividendes reçus]])/Titres[[#This Row],[Coût total]]) -> 1.0033589 | AA51: =SUM(Titres[[#This Row],[Janvier 2019]:[Août 2024]]) -> 767.48 | AB51: 31.09 | AE51: 30.45 | AH51: 29.83 | AK51: 31.58 | AN51: 30.98 | AQ51: 33.84 | AT51: 32.5 | AW51: 31.81 | AZ51: 30.37 | BC51: 30.66 | BF51: 30.22 | BI51: 31.06 | BL51: 30.91 | BO51: 31.79 | BR51: 32.78 | BU51: 34.87 | BX51: 34.46 | CA51: 38.01 | CD51: 37.19 | CG51: 37.98 | CJ51: 37.15 | CM51: 38.78 | CP51: 39.17 | CS51: 38.63 | CV51: 41.18 | CY51: 41.53 | DB51: 39.41 | DE51: 40.21 | DH51: 39.59
B52: =IF(C52="","",_xlfn.XLOOKUP(C52,Type_Compte,Num_Compte)) -> 20K6HF2 | C52: Marge (USD) | D52: #VALUE! | E52: {=_FV(Titres[[#This Row],[Action]],"Code mnémonique",TRUE)} -> O | F52: {=_FV(D52,"Change")} -> New York Stock Exchange | G52: {=IFERROR(_FV(Titres[[#This Row],[Action]],"Industrie"),"")} -> Residential & Commercial REIT | H52: REIT | I52: {=_FV(D52,"Devise")} -> USD | J52: 100 | K52: 65.6 | L52: =J52*K52 -> 6560 | M52: {=_FV(D52,"Prix")} -> 64.04 | N52: =J52*M52 -> 6404 | O52: =IF(Titres[[#This Row],[Devise]]="CAD",Titres[[#This Row],[Valeur au marché ($ local)]],Titres[[#This Row],[Valeur au marché ($ local)]]*Ressources!$I$3) -> 8747.864 | P52: {=(Titres[[#This Row],[Prix actuel]]-_FV(Titres[[#This Row],[Action]],"Clôture précédente",TRUE))*Titres[[#This Row],[Nb d''actions]]} -> -88 | Q52: =Titres[[#This Row],[Variation du jour ($)]]/(Titres[[#This Row],[Valeur au marché ($ local)]]-Titres[[#This Row],[Variation du jour ($)]]) -> -0.013555145 | R52: =Titres[[#This Row],[Valeur au marché ($ local)]]-Titres[[#This Row],[Coût total]] -> -156 | S52: =Titres[[#This Row],[Gain non réalisé ($)]]/Titres[[#This Row],[Coût total]] -> -0.023780488 | T52: 0.81 | U52: =4*Titres[[#This Row],[Dividende trimestriel]] -> 3.24 | V52: =Titres[[#This Row],[Dividende annuel]]*Titres[[#This Row],[Nb d''actions]] -> 324 | W52: =Titres[[#This Row],[Dividende annuel]]/Titres[[#This Row],[Prix actuel]] -> 0.050593379 | X52: =Titres[[#This Row],[Dividende annuel]]/Titres[[#This Row],[Coût moyen]] -> 0.049390244 | Y52: 26 | Z52: =(((Titres[[#This Row],[Valeur au marché ($ local)]]-Titres[[#This Row],[Coût total]])+Titres[[#This Row],[Total - dividendes reçus]])/Titres[[#This Row],[Coût total]]) -> 0.036739329 | AA52: =SUM(Titres[[#This Row],[Janvier 2019]:[Août 2024]]) -> 397.01 | BZ52: 21.63 | CA52: 21.67 | CB52: 21.67 | CC52: 21.67 | CD52: 21.72 | CE52: 21.72 | CF52: 21.72 | CG52: 25.6 | CH52: 21.76 | CI52: 21.76 | CJ52: 21.8 | CK52: 21.8 | CL52: 21.8 | CM52: 21.84 | CN52: 21.84 | CO52: 22.31 | CP52: 22.35 | CQ52: 22.35 | CR52: 22.35 | CS52: 22.4 | CT52: 22.4 | CU52: 22.4 | CV52: 22.44 | CW52: 22.44 | CX52: 22.78 | CY52: 22.82 | CZ52: 22.82 | DA52: 22.82 | DB52: 22.86 | DC52: 22.86 | DD52: 22.86 | DE52: 22.91 | DF52: 22.9 | DG52: 22.91 | DH52: 22.95 | DI52: 22.95
B53: =IF(C53="","",_xlfn.XLOOKUP(C53,Type_Compte,Num_Compte)) -> 20K6HZ6 | C53: CELI (CAD) | D53: #VALUE! | E53: {=_FV(Titres[[#This Row],[Action]],"Code mnémonique",TRUE)} -> PKI | F53: {=_FV(D53,"Change")} -> Toronto Stock Exchange | G53: {=IFERROR(_FV(Titres[[#This Row],[Action]],"Industrie"),"")} -> Oil & Gas | H53: Actions canadiennes | I53: {=_FV(D53,"Devise")} -> CAD | J53: 0 | K53: 31.17 | L53: =J53*K53 -> 0 | M53: {=_FV(D53,"Prix")} -> 39.84 | N53: =J53*M53 -> 0 | O53: =IF(Titres[[#This Row],[Devise]]="CAD",Titres[[#This Row],[Valeur au marché ($ local)]],Titres[[#This Row],[Valeur au marché ($ local)]]*Ressources!$I$3) -> 0 | P53: {=(Titres[[#This Row],[Prix actuel]]-_FV(Titres[[#This Row],[Action]],"Clôture précédente",TRUE))*Titres[[#This Row],[Nb d''actions]]} -> 0 | Q53: =Titres[[#This Row],[Variation du jour ($)]]/(Titres[[#This Row],[Valeur au marché ($ local)]]-Titres[[#This Row],[Variation du jour ($)]]) -> #DIV/0! | R53: =Titres[[#This Row],[Valeur au marché ($ local)]]-Titres[[#This Row],[Coût total]] -> 0 | S53: =Titres[[#This Row],[Gain non réalisé ($)]]/Titres[[#This Row],[Coût total]] -> #DIV/0! | T53: 0.35 | U53: =4*Titres[[#This Row],[Dividende trimestriel]] -> 1.4 | V53: =Titres[[#This Row],[Dividende annuel]]*Titres[[#This Row],[Nb d''actions]] -> 0 | W53: =Titres[[#This Row],[Dividende annuel]]/Titres[[#This Row],[Prix actuel]] -> 0.035140562 | X53: =Titres[[#This Row],[Dividende annuel]]/Titres[[#This Row],[Coût moyen]] -> 0.044914982 | Y53: 0 | Z53: =(((Titres[[#This Row],[Valeur au marché ($ local)]]-Titres[[#This Row],[Coût total]])+Titres[[#This Row],[Total - dividendes reçus]])/Titres[[#This Row],[Coût total]]) -> #DIV/0! | AA53: =SUM(Titres[[#This Row],[Janvier 2019]:[Août 2024]]) -> 241.54 | AB53: 0.98 | AC53: 0.98 | AD53: 0.98 | AE53: 1 | AF53: 1 | AG53: 1 | AH53: 1 | AI53: 1 | AJ53: 1 | AK53: 1 | AL53: 1 | AM53: 1 | AN53: 1 | AO53: 1 | AP53: 1 | CA53: 37.4 | CD53: 37.4 | CG53: 37.4 | CJ53: 37.4 | CM53: 38.5 | CP53: 38.5 | CS53: 38.5 | CV53: 38.5 | CY53: 39.6 | DB53: 39.6 | DE53: 39.6
B54: =IF(C54="","",_xlfn.XLOOKUP(C54,Type_Compte,Num_Compte)) -> 20K6HU7 | C54: REER (USD) | D54: #VALUE! | E54: {=_FV(Titres[[#This Row],[Action]],"Code mnémonique",TRUE)} -> SOLV | F54: {=_FV(D54,"Change")} -> New York Stock Exchange | G54: {=IFERROR(_FV(Titres[[#This Row],[Action]],"Industrie"),"")} -> Healthcare Equipment & Supplies | H54: Actions américaines | I54: {=_FV(D54,"Devise")} -> USD | J54: 7 | K54: 69.15 | L54: =J54*K54 -> 484.05 | M54: {=_FV(D54,"Prix")} -> 69.01 | N54: =J54*M54 -> 483.07 | O54: =IF(Titres[[#This Row],[Devise]]="CAD",Titres[[#This Row],[Valeur au marché ($ local)]],Titres[[#This Row],[Valeur au marché ($ local)]]*Ressources!$I$3) -> 659.87362 | P54: {=(Titres[[#This Row],[Prix actuel]]-_FV(Titres[[#This Row],[Action]],"Clôture précédente",TRUE))*Titres[[#This Row],[Nb d''actions]]} -> -7.21 | Q54: =Titres[[#This Row],[Variation du jour ($)]]/(Titres[[#This Row],[Valeur au marché ($ local)]]-Titres[[#This Row],[Variation du jour ($)]]) -> -0.014705882 | R54: =Titres[[#This Row],[Valeur au marché ($ local)]]-Titres[[#This Row],[Coût total]] -> -0.98 | S54: =Titres[[#This Row],[Gain non réalisé ($)]]/Titres[[#This Row],[Coût total]] -> -0.0020245842 | T54: 0 | U54: =4*Titres[[#This Row],[Dividende trimestriel]] -> 0 | V54: =Titres[[#This Row],[Dividende annuel]]*Titres[[#This Row],[Nb d''actions]] -> 0 | W54: =Titres[[#This Row],[Dividende annuel]]/Titres[[#This Row],[Prix actuel]] -> 0 | X54: =Titres[[#This Row],[Dividende annuel]]/Titres[[#This Row],[Coût moyen]] -> 0 | Z54: =(((Titres[[#This Row],[Valeur au marché ($ local)]]-Titres[[#This Row],[Coût total]])+Titres[[#This Row],[Total - dividendes reçus]])/Titres[[#This Row],[Coût total]]) -> 0.11009193 | AA54: =SUM(Titres[[#This Row],[Janvier 2019]:[Août 2024]]) -> 54.27 | CE54: =25.55-3.83 -> 21.72 | CM54: 32.55
B55: =IF(C55="","",_xlfn.XLOOKUP(C55,Type_Compte,Num_Compte)) -> 20K6HZ6 | C55: CELI (CAD) | D55: #VALUE! | E55: {=_FV(Titres[[#This Row],[Action]],"Code mnémonique",TRUE)} -> POW | F55: {=_FV(D55,"Change")} -> Toronto Stock Exchange | G55: {=IFERROR(_FV(Titres[[#This Row],[Action]],"Industrie"),"")} -> Insurance | H55: Actions canadiennes | I55: {=_FV(D55,"Devise")} -> CAD | J55: 255 | K55: 26.53 | L55: =J55*K55 -> 6765.15 | M55: {=_FV(D55,"Prix")} -> 72.09 | N55: =J55*M55 -> 18382.95 | O55: =IF(Titres[[#This Row],[Devise]]="CAD",Titres[[#This Row],[Valeur au marché ($ local)]],Titres[[#This Row],[Valeur au marché ($ local)]]*Ressources!$I$3) -> 18382.95 | P55: {=(Titres[[#This Row],[Prix actuel]]-_FV(Titres[[#This Row],[Action]],"Clôture précédente",TRUE))*Titres[[#This Row],[Nb d''actions]]} -> -40.8 | Q55: =Titres[[#This Row],[Variation du jour ($)]]/(Titres[[#This Row],[Valeur au marché ($ local)]]-Titres[[#This Row],[Variation du jour ($)]]) -> -0.0022145329 | R55: =Titres[[#This Row],[Valeur au marché ($ local)]]-Titres[[#This Row],[Coût total]] -> 11617.8 | S55: =Titres[[#This Row],[Gain non réalisé ($)]]/Titres[[#This Row],[Coût total]] -> 1.7173012 | T55: 0.613 | U55: =4*Titres[[#This Row],[Dividende trimestriel]] -> 2.452 | V55: =Titres[[#This Row],[Dividende annuel]]*Titres[[#This Row],[Nb d''actions]] -> 625.26 | W55: =Titres[[#This Row],[Dividende annuel]]/Titres[[#This Row],[Prix actuel]] -> 0.034013039 | X55: =Titres[[#This Row],[Dividende annuel]]/Titres[[#This Row],[Coût moyen]] -> 0.092423671 | Y55: 1 | Z55: =(((Titres[[#This Row],[Valeur au marché ($ local)]]-Titres[[#This Row],[Coût total]])+Titres[[#This Row],[Total - dividendes reçus]])/Titres[[#This Row],[Coût total]]) -> 2.0736421 | AA55: =SUM(Titres[[#This Row],[Janvier 2019]:[Août 2024]]) -> 2410.7 | AC55: 43.3 | AF55: 45.55 | AI55: 45.55 | AL55: 45.55 | AN55: 45.55 | AR55: 46.99 | AT55: 114.11 | AW55: 114.11 | BA55: 114.11 | BC55: 114.11 | BF55: 114.11 | BJ55: 114.11 | BM55: 126.23 | BO55: 126.23 | BR55: 126.23 | BV55: 126.23 | BY55: 126.23 | CB55: 133.88 | CE55: 133.88 | CH55: 133.88 | CK55: 133.88 | CN55: 143.44 | CQ55: 143.44 | CT55: 143.44 | CZ55: 156.19 | DC55: 156.19 | DE55: 156.19 | DH55: 156.19
B56: =IF(C56="","",_xlfn.XLOOKUP(C56,Type_Compte,Num_Compte)) -> 20K6HZ6 | C56: CELI (CAD) | D56: #VALUE! | E56: {=_FV(Titres[[#This Row],[Action]],"Code mnémonique",TRUE)} -> PMZ.UN | F56: {=_FV(D56,"Change")} -> Toronto Stock Exchange | G56: {=IFERROR(_FV(Titres[[#This Row],[Action]],"Industrie"),"")} | H56: REIT | I56: {=_FV(D56,"Devise")} -> CAD | J56: 40 | K56: 13.28 | L56: =J56*K56 -> 531.2 | M56: {=_FV(D56,"Prix")} -> 18.81 | N56: =J56*M56 -> 752.4 | O56: =IF(Titres[[#This Row],[Devise]]="CAD",Titres[[#This Row],[Valeur au marché ($ local)]],Titres[[#This Row],[Valeur au marché ($ local)]]*Ressources!$I$3) -> 752.4 | P56: {=(Titres[[#This Row],[Prix actuel]]-_FV(Titres[[#This Row],[Action]],"Clôture précédente",TRUE))*Titres[[#This Row],[Nb d''actions]]} -> -4.4 | Q56: =Titres[[#This Row],[Variation du jour ($)]]/(Titres[[#This Row],[Valeur au marché ($ local)]]-Titres[[#This Row],[Variation du jour ($)]]) -> -0.0058139535 | R56: =Titres[[#This Row],[Valeur au marché ($ local)]]-Titres[[#This Row],[Coût total]] -> 221.2 | S56: =Titres[[#This Row],[Gain non réalisé ($)]]/Titres[[#This Row],[Coût total]] -> 0.41641566 | T56: 0.073 | U56: =4*Titres[[#This Row],[Dividende trimestriel]] -> 0.292 | V56: =Titres[[#This Row],[Dividende annuel]]*Titres[[#This Row],[Nb d''actions]] -> 11.68 | W56: =Titres[[#This Row],[Dividende annuel]]/Titres[[#This Row],[Prix actuel]] -> 0.015523658 | X56: =Titres[[#This Row],[Dividende annuel]]/Titres[[#This Row],[Coût moyen]] -> 0.021987952 | Y56: 0 | Z56: =(((Titres[[#This Row],[Valeur au marché ($ local)]]-Titres[[#This Row],[Coût total]])+Titres[[#This Row],[Total - dividendes reçus]])/Titres[[#This Row],[Coût total]]) -> 0.57554593 | AA56: =SUM(Titres[[#This Row],[Janvier 2019]:[Août 2024]]) -> 84.53 | BM56: 2.67 | BN56: 2.67 | BO56: 2.67 | BP56: 2.67 | BQ56: 2.67 | BR56: 2.67 | BS56: 2.67 | BT56: 2.67 | BU56: 2.67 | BV56: 2.67 | BW56: 2.67 | BX56: 2.73 | BY56: 2.73 | BZ56: 2.73 | CA56: 2.73 | CB56: 2.73 | CC56: 2.73 | CD56: 2.73 | CE56: 2.73 | CF56: 2.73 | CG56: 2.73 | CH56: 2.73 | CI56: 2.73 | CJ56: 2.8 | CK56: 2.8 | CL56: 2.8 | CM56: 2.8 | CN56: 2.8 | CO56: 2.8 | CP56: 2.8 | CQ56: 2.8 | CR56: 2.8 | CS56: 2.8 | CT56: 2.8 | CU56: 2.8 | CV56: 2.87 | CW56: 2.87 | CX56: 2.87 | CY56: 2.87 | CZ56: 2.87 | DA56: 2.87 | DB56: 2.87 | DC56: 2.87 | DD56: 2.87 | DE56: 2.87 | DF56: 2.87 | DG56: 2.87 | DH56: 2.93 | DI56: 2.93
B57: =IF(C57="","",_xlfn.XLOOKUP(C57,Type_Compte,Num_Compte)) -> 20K6HZ6 | C57: CELI (CAD) | D57: #VALUE! | E57: {=_FV(Titres[[#This Row],[Action]],"Code mnémonique",TRUE)} -> RCI.B | F57: {=_FV(D57,"Change")} -> Toronto Stock Exchange | G57: {=IFERROR(_FV(Titres[[#This Row],[Action]],"Industrie"),"")} -> Telecommunications Services | H57: Actions canadiennes | I57: {=_FV(D57,"Devise")} -> CAD | J57: 100 | K57: 48.95 | L57: =J57*K57 -> 4895 | M57: {=_FV(D57,"Prix")} -> 45.1 | N57: =J57*M57 -> 4510 | O57: =IF(Titres[[#This Row],[Devise]]="CAD",Titres[[#This Row],[Valeur au marché ($ local)]],Titres[[#This Row],[Valeur au marché ($ local)]]*Ressources!$I$3) -> 4510 | P57: {=(Titres[[#This Row],[Prix actuel]]-_FV(Titres[[#This Row],[Action]],"Clôture précédente",TRUE))*Titres[[#This Row],[Nb d''actions]]} -> -42 | Q57: =Titres[[#This Row],[Variation du jour ($)]]/(Titres[[#This Row],[Valeur au marché ($ local)]]-Titres[[#This Row],[Variation du jour ($)]]) -> -0.0092267135 | R57: =Titres[[#This Row],[Valeur au marché ($ local)]]-Titres[[#This Row],[Coût total]] -> -385 | S57: =Titres[[#This Row],[Gain non réalisé ($)]]/Titres[[#This Row],[Coût total]] -> -0.078651685 | T57: 0.5 | U57: =4*Titres[[#This Row],[Dividende trimestriel]] -> 2 | V57: =Titres[[#This Row],[Dividende annuel]]*Titres[[#This Row],[Nb d''actions]] -> 200 | W57: =Titres[[#This Row],[Dividende annuel]]/Titres[[#This Row],[Prix actuel]] -> 0.044345898 | X57: =Titres[[#This Row],[Dividende annuel]]/Titres[[#This Row],[Coût moyen]] -> 0.040858018 | Y57: 0 | Z57: =(((Titres[[#This Row],[Valeur au marché ($ local)]]-Titres[[#This Row],[Coût total]])+Titres[[#This Row],[Total - dividendes reçus]])/Titres[[#This Row],[Coût total]]) -> 0.043301328 | AA57: =SUM(Titres[[#This Row],[Janvier 2019]:[Août 2024]]) -> 596.96 | AB57: 24.96 | AE57: 26 | AH57: 26 | AK57: 26 | AN57: 26 | AQ57: 26 | AT57: 26 | AW57: 26 | AZ57: 26 | BC57: 26 | BF57: 26 | BI57: 26 | BL57: 26 | BO57: 26 | BR57: 26 | BU57: 26 | BX57: 26 | CA57: 26 | CD57: 26 | CG57: 26 | CJ57: 26 | CM57: 26 | CP57: 26 | CS57: 26 | CV57: 26 | CY57: 26 | DB57: 26 | DE57: 26 | DH57: 50
B58: =IF(C58="","",_xlfn.XLOOKUP(C58,Type_Compte,Num_Compte)) -> 20K6HZ6 | C58: CELI (CAD) | D58: #VALUE! | E58: {=_FV(Titres[[#This Row],[Action]],"Code mnémonique",TRUE)} -> SOBO | F58: {=_FV(D58,"Change")} -> Toronto Stock Exchange | G58: {=IFERROR(_FV(Titres[[#This Row],[Action]],"Industrie"),"")} -> Oil & Gas Related Equipment and Services | I58: {=_FV(D58,"Devise")} -> CAD | J58: 9 | K58: 28.01 | L58: =J58*K58 -> 252.09 | M58: {=_FV(D58,"Prix")} -> 42.83 | N58: =J58*M58 -> 385.47 | O58: =IF(Titres[[#This Row],[Devise]]="CAD",Titres[[#This Row],[Valeur au marché ($ local)]],Titres[[#This Row],[Valeur au marché ($ local)]]*Ressources!$I$3) -> 385.47 | P58: {=(Titres[[#This Row],[Prix actuel]]-_FV(Titres[[#This Row],[Action]],"Clôture précédente",TRUE))*Titres[[#This Row],[Nb d''actions]]} -> -1.35 | Q58: =Titres[[#This Row],[Variation du jour ($)]]/(Titres[[#This Row],[Valeur au marché ($ local)]]-Titres[[#This Row],[Variation du jour ($)]]) -> -0.0034899953 | R58: =Titres[[#This Row],[Valeur au marché ($ local)]]-Titres[[#This Row],[Coût total]] -> 133.38 | S58: =Titres[[#This Row],[Gain non réalisé ($)]]/Titres[[#This Row],[Coût total]] -> 0.52909675 | T58: 0.694 | U58: =4*Titres[[#This Row],[Dividende trimestriel]] -> 2.776 | V58: =Titres[[#This Row],[Dividende annuel]]*Titres[[#This Row],[Nb d''actions]] -> 24.984 | W58: =Titres[[#This Row],[Dividende annuel]]/Titres[[#This Row],[Prix actuel]] -> 0.064814382 | X58: =Titres[[#This Row],[Dividende annuel]]/Titres[[#This Row],[Coût moyen]] -> 0.099107462 | Z58: =(((Titres[[#This Row],[Valeur au marché ($ local)]]-Titres[[#This Row],[Coût total]])+Titres[[#This Row],[Total - dividendes reçus]])/Titres[[#This Row],[Coût total]]) -> 0.61525646 | AA58: =SUM(Titres[[#This Row],[Janvier 2019]:[Août 2024]]) -> 21.72 | CE58: =25.55-3.83 -> 21.72 | CY58: 6.47 | DB58: 6.14 | DE58: 6.26 | DH58: 6.17
B59: =IF(C59="","",_xlfn.XLOOKUP(C59,Type_Compte,Num_Compte)) -> 20K6HZ6 | C59: CELI (CAD) | D59: #VALUE! | E59: {=_FV(Titres[[#This Row],[Action]],"Code mnémonique",TRUE)} -> SLF | F59: {=_FV(D59,"Change")} -> Toronto Stock Exchange | G59: {=IFERROR(_FV(Titres[[#This Row],[Action]],"Industrie"),"")} -> Insurance | H59: Actions canadiennes | I59: {=_FV(D59,"Devise")} -> CAD | J59: 54 | K59: 47.01 | L59: =J59*K59 -> 2538.54 | M59: {=_FV(D59,"Prix")} -> 96.19 | N59: =J59*M59 -> 5194.26 | O59: =IF(Titres[[#This Row],[Devise]]="CAD",Titres[[#This Row],[Valeur au marché ($ local)]],Titres[[#This Row],[Valeur au marché ($ local)]]*Ressources!$I$3) -> 5194.26 | P59: {=(Titres[[#This Row],[Prix actuel]]-_FV(Titres[[#This Row],[Action]],"Clôture précédente",TRUE))*Titres[[#This Row],[Nb d''actions]]} -> 5.94 | Q59: =Titres[[#This Row],[Variation du jour ($)]]/(Titres[[#This Row],[Valeur au marché ($ local)]]-Titres[[#This Row],[Variation du jour ($)]]) -> 0.0011448793 | R59: =Titres[[#This Row],[Valeur au marché ($ local)]]-Titres[[#This Row],[Coût total]] -> 2655.72 | S59: =Titres[[#This Row],[Gain non réalisé ($)]]/Titres[[#This Row],[Coût total]] -> 1.0461604 | T59: 0.92 | U59: =4*Titres[[#This Row],[Dividende trimestriel]] -> 3.68 | V59: =Titres[[#This Row],[Dividende annuel]]*Titres[[#This Row],[Nb d''actions]] -> 198.72 | W59: =Titres[[#This Row],[Dividende annuel]]/Titres[[#This Row],[Prix actuel]] -> 0.038257615 | X59: =Titres[[#This Row],[Dividende annuel]]/Titres[[#This Row],[Coût moyen]] -> 0.078281217 | Y59: 8 | Z59: =(((Titres[[#This Row],[Valeur au marché ($ local)]]-Titres[[#This Row],[Coût total]])+Titres[[#This Row],[Total - dividendes reçus]])/Titres[[#This Row],[Coût total]]) -> 1.3278026 | AA59: =SUM(Titres[[#This Row],[Janvier 2019]:[Août 2024]]) -> 714.96 | AD59: 27 | AG59: 28.35 | AJ59: 28.35 | AM59: 29.7 | AP59: 29.7 | AS59: 29.7 | AV59: 29.7 | AY59: 29.7 | BB59: 29.7 | BE59: 29.7 | BH59: 29.7 | BK59: 35.64 | BN59: 35.64 | BQ59: 37.26 | BT59: 37.26 | BW59: 38.88 | CC59: 40.5 | CF59: 40.5 | CI59: 42.12 | CL59: 42.12 | CP59: 43.74 | CR59: 43.74 | CU59: 45.36 | CX59: 45.36 | DA59: 47.52 | DD59: 47.52 | DG59: 49.68
B60: =IF(C60="","",_xlfn.XLOOKUP(C60,Type_Compte,Num_Compte)) -> 20K6HU7 | C60: REER (USD) | D60: #VALUE! | E60: {=_FV(Titres[[#This Row],[Action]],"Code mnémonique",TRUE)} -> KO | F60: {=_FV(D60,"Change")} -> New York Stock Exchange | G60: {=IFERROR(_FV(Titres[[#This Row],[Action]],"Industrie"),"")} -> Beverages | H60: Actions américaines | I60: {=_FV(D60,"Devise")} -> USD | J60: 35 | K60: 42.27 | L60: =J60*K60 -> 1479.45 | M60: {=_FV(D60,"Prix")} -> 74.71 | N60: =J60*M60 -> 2614.85 | O60: =IF(Titres[[#This Row],[Devise]]="CAD",Titres[[#This Row],[Valeur au marché ($ local)]],Titres[[#This Row],[Valeur au marché ($ local)]]*Ressources!$I$3) -> 3571.8851 | P60: {=(Titres[[#This Row],[Prix actuel]]-_FV(Titres[[#This Row],[Action]],"Clôture précédente",TRUE))*Titres[[#This Row],[Nb d''actions]]} -> -26.95 | Q60: =Titres[[#This Row],[Variation du jour ($)]]/(Titres[[#This Row],[Valeur au marché ($ local)]]-Titres[[#This Row],[Variation du jour ($)]]) -> -0.010201378 | R60: =Titres[[#This Row],[Valeur au marché ($ local)]]-Titres[[#This Row],[Coût total]] -> 1135.4 | S60: =Titres[[#This Row],[Gain non réalisé ($)]]/Titres[[#This Row],[Coût total]] -> 0.76744736 | T60: 0.51 | U60: =4*Titres[[#This Row],[Dividende trimestriel]] -> 2.04 | V60: =Titres[[#This Row],[Dividende annuel]]*Titres[[#This Row],[Nb d''actions]] -> 71.4 | W60: =Titres[[#This Row],[Dividende annuel]]/Titres[[#This Row],[Prix actuel]] -> 0.027305582 | X60: =Titres[[#This Row],[Dividende annuel]]/Titres[[#This Row],[Coût moyen]] -> 0.048261178 | Y60: 60 | Z60: =(((Titres[[#This Row],[Valeur au marché ($ local)]]-Titres[[#This Row],[Coût total]])+Titres[[#This Row],[Total - dividendes reçus]])/Titres[[#This Row],[Coût total]]) -> 0.99196323 | AA60: =SUM(Titres[[#This Row],[Janvier 2019]:[Août 2024]]) -> 332.16 | AE60: 14 | AH60: 14 | AK60: 14 | AM60: 14 | AQ60: 14.35 | AT60: 14.35 | AW60: 14.35 | AY60: 14.35 | BC60: 14.7 | BF60: 14.7 | BI60: 14.7 | BK60: 14.7 | BO60: 15.4 | BR60: 15.4 | BU60: 15.4 | BW60: 15.4 | CA60: 16.1 | CD60: 16.1 | CG60: 16.1 | CI60: 16.1 | CM60: 16.98 | CP60: 16.98 | CS60: 16.98 | CU60: 16.98 | CY60: 17.85 | DB60: 17.85 | DE60: 17.85 | DG60: 17.85
B61: =IF(C61="","",_xlfn.XLOOKUP(C61,Type_Compte,Num_Compte)) -> 20K6HU7 | C61: REER (USD) | D61: #VALUE! | E61: {=_FV(Titres[[#This Row],[Action]],"Code mnémonique",TRUE)} -> KHC | F61: {=_FV(D61,"Change")} -> Nasdaq Stock Market | G61: {=IFERROR(_FV(Titres[[#This Row],[Action]],"Industrie"),"")} -> Food & Tobacco | H61: Actions américaines | I61: {=_FV(D61,"Devise")} -> USD | J61: 90 | K61: 32.91 | L61: =J61*K61 -> 2961.9 | M61: {=_FV(D61,"Prix")} -> 21.98 | N61: =J61*M61 -> 1978.2 | O61: =IF(Titres[[#This Row],[Devise]]="CAD",Titres[[#This Row],[Valeur au marché ($ local)]],Titres[[#This Row],[Valeur au marché ($ local)]]*Ressources!$I$3) -> 2702.2212 | P61: {=(Titres[[#This Row],[Prix actuel]]-_FV(Titres[[#This Row],[Action]],"Clôture précédente",TRUE))*Titres[[#This Row],[Nb d''actions]]} -> -20.7 | Q61: =Titres[[#This Row],[Variation du jour ($)]]/(Titres[[#This Row],[Valeur au marché ($ local)]]-Titres[[#This Row],[Variation du jour ($)]]) -> -0.010355696 | R61: =Titres[[#This Row],[Valeur au marché ($ local)]]-Titres[[#This Row],[Coût total]] -> -983.7 | S61: =Titres[[#This Row],[Gain non réalisé ($)]]/Titres[[#This Row],[Coût total]] -> -0.3321179 | T61: 0.4 | U61: =4*Titres[[#This Row],[Dividende trimestriel]] -> 1.6 | V61: =Titres[[#This Row],[Dividende annuel]]*Titres[[#This Row],[Nb d''actions]] -> 144 | W61: =Titres[[#This Row],[Dividende annuel]]/Titres[[#This Row],[Prix actuel]] -> 0.072793449 | X61: =Titres[[#This Row],[Dividende annuel]]/Titres[[#This Row],[Coût moyen]] -> 0.048617442 | Y61: 0 | Z61: =(((Titres[[#This Row],[Valeur au marché ($ local)]]-Titres[[#This Row],[Coût total]])+Titres[[#This Row],[Total - dividendes reçus]])/Titres[[#This Row],[Coût total]]) -> -0.08903069 | AA61: =SUM(Titres[[#This Row],[Janvier 2019]:[Août 2024]]) -> 720 | AG61: 36 | AJ61: 36 | AM61: 36 | AP61: 36 | AS61: 36 | AV61: 36 | AY61: 36 | BB61: 36 | BE61: 36 | BH61: 36 | BK61: 36 | BN61: 36 | BQ61: 36 | BT61: 36 | BW61: 36 | CC61: 36 | CF61: 36 | CI61: 36 | CL61: 36 | CP61: 36 | CR61: 36 | CU61: 36 | CX61: 36 | DA61: 36 | DD61: 36 | DG61: 36
B62: =IF(C62="","",_xlfn.XLOOKUP(C62,Type_Compte,Num_Compte)) -> 20K6HZ6 | C62: CELI (CAD) | D62: #VALUE! | E62: {=_FV(Titres[[#This Row],[Action]],"Code mnémonique",TRUE)} -> SU | F62: {=_FV(D62,"Change")} -> Toronto Stock Exchange | G62: {=IFERROR(_FV(Titres[[#This Row],[Action]],"Industrie"),"")} -> Oil & Gas | H62: Actions canadiennes | I62: {=_FV(D62,"Devise")} -> CAD | J62: 237 | K62: 22.78 | L62: =J62*K62 -> 5398.86 | M62: {=_FV(D62,"Prix")} -> 85.73 | N62: =J62*M62 -> 20318.01 | O62: =IF(Titres[[#This Row],[Devise]]="CAD",Titres[[#This Row],[Valeur au marché ($ local)]],Titres[[#This Row],[Valeur au marché ($ local)]]*Ressources!$I$3) -> 20318.01 | P62: {=(Titres[[#This Row],[Prix actuel]]-_FV(Titres[[#This Row],[Action]],"Clôture précédente",TRUE))*Titres[[#This Row],[Nb d''actions]]} -> 383.94 | Q62: =Titres[[#This Row],[Variation du jour ($)]]/(Titres[[#This Row],[Valeur au marché ($ local)]]-Titres[[#This Row],[Variation du jour ($)]]) -> 0.019260492 | R62: =Titres[[#This Row],[Valeur au marché ($ local)]]-Titres[[#This Row],[Coût total]] -> 14919.15 | S62: =Titres[[#This Row],[Gain non réalisé ($)]]/Titres[[#This Row],[Coût total]] -> 2.7633889 | T62: 0.6 | U62: =4*Titres[[#This Row],[Dividende trimestriel]] -> 2.4 | V62: =Titres[[#This Row],[Dividende annuel]]*Titres[[#This Row],[Nb d''actions]] -> 568.8 | W62: =Titres[[#This Row],[Dividende annuel]]/Titres[[#This Row],[Prix actuel]] -> 0.027994868 | X62: =Titres[[#This Row],[Dividende annuel]]/Titres[[#This Row],[Coût moyen]] -> 0.10535558 | Y62: 1 | Z62: =(((Titres[[#This Row],[Valeur au marché ($ local)]]-Titres[[#This Row],[Coût total]])+Titres[[#This Row],[Total - dividendes reçus]])/Titres[[#This Row],[Coût total]]) -> 3.0941606 | AA62: =SUM(Titres[[#This Row],[Janvier 2019]:[Août 2024]]) -> 1785.79 | AD62: 36.54 | AG62: 36.54 | AJ62: 36.54 | AM62: 36.54 | AP62: 40.46 | AS62: 49.77 | AV62: 49.77 | AY62: 49.77 | BB62: 49.77 | BE62: 49.77 | BH62: 47.99 | BK62: 99.54 | BN62: 99.54 | BQ62: 111.39 | BT62: 111.39 | BW62: 123.24 | BZ62: 123.24 | CC62: 123.24 | CF62: 123.24 | CI62: 129.17 | CL62: 129.17 | CO62: 129.17 | CR62: 129.17 | CU62: 135.09 | CX62: 135.09 | DA62: 135.09 | DD62: 135.09 | DG62: 142.2
B63: =IF(C63="","",_xlfn.XLOOKUP(C63,Type_Compte,Num_Compte)) -> 20K6HU7 | C63: REER (USD) | D63: #VALUE! | E63: {=_FV(Titres[[#This Row],[Action]],"Code mnémonique",TRUE)} -> PG | F63: {=_FV(D63,"Change")} -> New York Stock Exchange | G63: {=IFERROR(_FV(Titres[[#This Row],[Action]],"Industrie"),"")} -> Personal & Household Products & Services | H63: Actions américaines | I63: {=_FV(D63,"Devise")} -> USD | J63: 22 | K63: 49.97 | L63: =J63*K63 -> 1099.34 | M63: {=_FV(D63,"Prix")} -> 142.34 | N63: =J63*M63 -> 3131.48 | O63: =IF(Titres[[#This Row],[Devise]]="CAD",Titres[[#This Row],[Valeur au marché ($ local)]],Titres[[#This Row],[Valeur au marché ($ local)]]*Ressources!$I$3) -> 4277.6017 | P63: {=(Titres[[#This Row],[Prix actuel]]-_FV(Titres[[#This Row],[Action]],"Clôture précédente",TRUE))*Titres[[#This Row],[Nb d''actions]]} -> -47.3 | Q63: =Titres[[#This Row],[Variation du jour ($)]]/(Titres[[#This Row],[Valeur au marché ($ local)]]-Titres[[#This Row],[Variation du jour ($)]]) -> -0.014879922 | R63: =Titres[[#This Row],[Valeur au marché ($ local)]]-Titres[[#This Row],[Coût total]] -> 2032.14 | S63: =Titres[[#This Row],[Gain non réalisé ($)]]/Titres[[#This Row],[Coût total]] -> 1.8485091 | T63: 1.057 | U63: =4*Titres[[#This Row],[Dividende trimestriel]] -> 4.228 | V63: =Titres[[#This Row],[Dividende annuel]]*Titres[[#This Row],[Nb d''actions]] -> 93.016 | W63: =Titres[[#This Row],[Dividende annuel]]/Titres[[#This Row],[Prix actuel]] -> 0.029703527 | X63: =Titres[[#This Row],[Dividende annuel]]/Titres[[#This Row],[Coût moyen]] -> 0.084610766 | Y63: 66 | Z63: =(((Titres[[#This Row],[Valeur au marché ($ local)]]-Titres[[#This Row],[Coût total]])+Titres[[#This Row],[Total - dividendes reçus]])/Titres[[#This Row],[Coût total]]) -> 2.2447923 | AA63: =SUM(Titres[[#This Row],[Janvier 2019]:[Août 2024]]) -> 435.65 | AC63: 16.41 | AF63: 16.41 | AI63: 16.41 | AL63: 16.41 | AO63: 16.41 | AR63: 17.4 | AU63: 17.4 | AX63: 17.4 | BA63: 17.4 | BD63: 19.14 | BG63: 19.14 | BJ63: 19.14 | BM63: 19.14 | BP63: 20.09 | BS63: 20.09 | BV63: 20.09 | BY63: 20.09 | CB63: 20.7 | CE63: 20.7 | CH63: 20.7 | CK63: 20.7 | CN63: 22.14 | CQ63: 22.14 | CT63: 22.14 | CW63: 22.14 | CZ63: 23.25 | DC63: 23.25 | DF63: 23.25 | DI63: 23.25
B64: =IF(C64="","",_xlfn.XLOOKUP(C64,Type_Compte,Num_Compte)) -> 20K6HU7 | C64: REER (USD) | D64: #VALUE! | E64: {=_FV(Titres[[#This Row],[Action]],"Code mnémonique",TRUE)} -> TTE | F64: {=_FV(D64,"Change")} -> New York Stock Exchange | G64: {=IFERROR(_FV(Titres[[#This Row],[Action]],"Industrie"),"")} -> Oil & Gas | H64: Actions internationales | I64: {=_FV(D64,"Devise")} -> USD | J64: 135 | K64: 48.24 | L64: =J64*K64 -> 6512.4 | M64: {=_FV(D64,"Prix")} -> 88.37 | N64: =J64*M64 -> 11929.95 | O64: =IF(Titres[[#This Row],[Devise]]="CAD",Titres[[#This Row],[Valeur au marché ($ local)]],Titres[[#This Row],[Valeur au marché ($ local)]]*Ressources!$I$3) -> 16296.312 | P64: {=(Titres[[#This Row],[Prix actuel]]-_FV(Titres[[#This Row],[Action]],"Clôture précédente",TRUE))*Titres[[#This Row],[Nb d''actions]]} -> 143.1 | Q64: =Titres[[#This Row],[Variation du jour ($)]]/(Titres[[#This Row],[Valeur au marché ($ local)]]-Titres[[#This Row],[Variation du jour ($)]]) -> 0.012140648 | R64: =Titres[[#This Row],[Valeur au marché ($ local)]]-Titres[[#This Row],[Coût total]] -> 5417.55 | S64: =Titres[[#This Row],[Gain non réalisé ($)]]/Titres[[#This Row],[Coût total]] -> 0.83188226 | T64: 0.85 | U64: =4*Titres[[#This Row],[Dividende trimestriel]] -> 3.4 | V64: =Titres[[#This Row],[Dividende annuel]]*Titres[[#This Row],[Nb d''actions]] -> 459 | W64: =Titres[[#This Row],[Dividende annuel]]/Titres[[#This Row],[Prix actuel]] -> 0.038474595 | X64: =Titres[[#This Row],[Dividende annuel]]/Titres[[#This Row],[Coût moyen]] -> 0.070480929 | Y64: 0 | Z64: =(((Titres[[#This Row],[Valeur au marché ($ local)]]-Titres[[#This Row],[Coût total]])+Titres[[#This Row],[Total - dividendes reçus]])/Titres[[#This Row],[Coût total]]) -> 1.0234107 | AA64: =SUM(Titres[[#This Row],[Janvier 2019]:[Août 2024]]) -> 1247.31 | AB64: 15.45 | AE64: 14.76 | AH64: 14.86 | AK64: 14.81 | AN64: 15.52 | AQ64: 15.83 | AT64: 16.44 | AW64: 16.35 | AZ64: 17.36 | BC64: 16.74 | BF64: 76.07 | BI64: 74.31 | BL64: 75.13 | BO64: 72.37 | BR64: 68.35 | BU64: 66.88 | BW64: 105.98 | BX64: 73.7 | CA64: 74.33 | CD64: 80.09 | CG64: 77.58 | CJ64: 80.71 | CM64: 79.24 | CP64: 84.45 | CS64: 87.25 | CV64: 80.9 | CY64: 85.13 | DB64: 99.82 | DE64: 99.24 | DH64: 100.01
B65: =IF(C65="","",_xlfn.XLOOKUP(C65,Type_Compte,Num_Compte)) -> 20K6HF2 | C65: Marge (USD) | D65: #VALUE! | E65: {=_FV(Titres[[#This Row],[Action]],"Code mnémonique",TRUE)} -> VFC | F65: {=_FV(D65,"Change")} -> New York Stock Exchange | G65: {=IFERROR(_FV(Titres[[#This Row],[Action]],"Industrie"),"")} -> Textiles & Apparel | H65: Actions américaines | I65: {=_FV(D65,"Devise")} -> USD | J65: 0 | K65: 30.89 | L65: =J65*K65 -> 0 | M65: {=_FV(D65,"Prix")} -> 21.47 | N65: =J65*M65 -> 0 | O65: =IF(Titres[[#This Row],[Devise]]="CAD",Titres[[#This Row],[Valeur au marché ($ local)]],Titres[[#This Row],[Valeur au marché ($ local)]]*Ressources!$I$3) -> 0 | P65: {=(Titres[[#This Row],[Prix actuel]]-_FV(Titres[[#This Row],[Action]],"Clôture précédente",TRUE))*Titres[[#This Row],[Nb d''actions]]} -> 0 | Q65: =Titres[[#This Row],[Variation du jour ($)]]/(Titres[[#This Row],[Valeur au marché ($ local)]]-Titres[[#This Row],[Variation du jour ($)]]) -> #DIV/0! | R65: =Titres[[#This Row],[Valeur au marché ($ local)]]-Titres[[#This Row],[Coût total]] -> 0 | S65: =Titres[[#This Row],[Gain non réalisé ($)]]/Titres[[#This Row],[Coût total]] -> #DIV/0! | T65: 0.09 | U65: =4*Titres[[#This Row],[Dividende trimestriel]] -> 0.36 | V65: =Titres[[#This Row],[Dividende annuel]]*Titres[[#This Row],[Nb d''actions]] -> 0 | W65: =Titres[[#This Row],[Dividende annuel]]/Titres[[#This Row],[Prix actuel]] -> 0.016767583 | X65: =Titres[[#This Row],[Dividende annuel]]/Titres[[#This Row],[Coût moyen]] -> 0.011654257 | Y65: 49 | Z65: =(((Titres[[#This Row],[Valeur au marché ($ local)]]-Titres[[#This Row],[Coût total]])+Titres[[#This Row],[Total - dividendes reçus]])/Titres[[#This Row],[Coût total]]) -> #DIV/0! | AA65: =SUM(Titres[[#This Row],[Janvier 2019]:[Août 2024]]) -> 158.05 | BZ65: 43.35 | CC65: 43.35 | CF65: 43.35 | CI65: 15 | CL65: 13
B66: =IF(C66="","",_xlfn.XLOOKUP(C66,Type_Compte,Num_Compte)) -> 20K6HE4 | C66: Marge (CAD) | D66: #VALUE! | E66: {=_FV(Titres[[#This Row],[Action]],"Code mnémonique",TRUE)} -> VCE | F66: {=_FV(D66,"Change")} -> Toronto Stock Exchange | G66: {=IFERROR(_FV(Titres[[#This Row],[Action]],"Industrie"),"")} | H66: Actions canadiennes | I66: {=_FV(D66,"Devise")} -> CAD | J66: 1900 | K66: 46.31 | L66: =J66*K66 -> 87989 | M66: {=_FV(D66,"Prix")} -> 72.43 | N66: =J66*M66 -> 137617 | O66: =IF(Titres[[#This Row],[Devise]]="CAD",Titres[[#This Row],[Valeur au marché ($ local)]],Titres[[#This Row],[Valeur au marché ($ local)]]*Ressources!$I$3) -> 137617 | P66: {=(Titres[[#This Row],[Prix actuel]]-_FV(Titres[[#This Row],[Action]],"Clôture précédente",TRUE))*Titres[[#This Row],[Nb d''actions]]} -> -1957 | Q66: =Titres[[#This Row],[Variation du jour ($)]]/(Titres[[#This Row],[Valeur au marché ($ local)]]-Titres[[#This Row],[Variation du jour ($)]]) -> -0.014021236 | R66: =Titres[[#This Row],[Valeur au marché ($ local)]]-Titres[[#This Row],[Coût total]] -> 49628 | S66: =Titres[[#This Row],[Gain non réalisé ($)]]/Titres[[#This Row],[Coût total]] -> 0.56402505 | T66: 0.413 | U66: =4*Titres[[#This Row],[Dividende trimestriel]] -> 1.652 | V66: =Titres[[#This Row],[Dividende annuel]]*Titres[[#This Row],[Nb d''actions]] -> 3138.8 | W66: =Titres[[#This Row],[Dividende annuel]]/Titres[[#This Row],[Prix actuel]] -> 0.022808229 | X66: =Titres[[#This Row],[Dividende annuel]]/Titres[[#This Row],[Coût moyen]] -> 0.035672641 | Y66: 2 | Z66: =(((Titres[[#This Row],[Valeur au marché ($ local)]]-Titres[[#This Row],[Coût total]])+Titres[[#This Row],[Total - dividendes reçus]])/Titres[[#This Row],[Coût total]]) -> 0.63224539 | AA66: =SUM(Titres[[#This Row],[Janvier 2019]:[Août 2024]]) -> 6002.64 | BC66: 107.54 | BF66: 115.81 | BI66: 183.01 | BL66: 222.87 | BO66: 306.02 | BR66: 416.12 | BU66: 519.53 | BX66: 503.82 | CA66: 554.7 | CD66: 567 | CG66: 560.14 | CJ66: 621.08 | CL66: 650.16 | CP66: 674.84 | CR66: 648.09 | CV66: 709.93 | CX66: 699.87 | DA66: 709.84 | DD66: 696.51 | DH66: 785.21
B67: =IF(C67="","",_xlfn.XLOOKUP(C67,Type_Compte,Num_Compte)) -> 20K6HE4 | C67: Marge (CAD) | D67: #VALUE! | E67: {=_FV(Titres[[#This Row],[Action]],"Code mnémonique",TRUE)} -> VFV | F67: {=_FV(D67,"Change")} -> Toronto Stock Exchange | G67: {=IFERROR(_FV(Titres[[#This Row],[Action]],"Industrie"),"")} | H67: Actions américaines | I67: {=_FV(D67,"Devise")} -> CAD | J67: 350 | K67: 92.69 | L67: =J67*K67 -> 32441.5 | M67: {=_FV(D67,"Prix")} -> 171.19 | N67: =J67*M67 -> 59916.5 | O67: =IF(Titres[[#This Row],[Devise]]="CAD",Titres[[#This Row],[Valeur au marché ($ local)]],Titres[[#This Row],[Valeur au marché ($ local)]]*Ressources!$I$3) -> 59916.5 | P67: {=(Titres[[#This Row],[Prix actuel]]-_FV(Titres[[#This Row],[Action]],"Clôture précédente",TRUE))*Titres[[#This Row],[Nb d''actions]]} -> -315 | Q67: =Titres[[#This Row],[Variation du jour ($)]]/(Titres[[#This Row],[Valeur au marché ($ local)]]-Titres[[#This Row],[Variation du jour ($)]]) -> -0.0052298216 | R67: =Titres[[#This Row],[Valeur au marché ($ local)]]-Titres[[#This Row],[Coût total]] -> 27475 | S67: =Titres[[#This Row],[Gain non réalisé ($)]]/Titres[[#This Row],[Coût total]] -> 0.84690905 | T67: 0.393 | U67: =4*Titres[[#This Row],[Dividende trimestriel]] -> 1.572 | V67: =Titres[[#This Row],[Dividende annuel]]*Titres[[#This Row],[Nb d''actions]] -> 550.2 | W67: =Titres[[#This Row],[Dividende annuel]]/Titres[[#This Row],[Prix actuel]] -> 0.0091827794 | X67: =Titres[[#This Row],[Dividende annuel]]/Titres[[#This Row],[Coût moyen]] -> 0.016959758 | Y67: 2 | Z67: =(((Titres[[#This Row],[Valeur au marché ($ local)]]-Titres[[#This Row],[Coût total]])+Titres[[#This Row],[Total - dividendes reçus]])/Titres[[#This Row],[Coût total]]) -> 0.88483547 | AA67: =SUM(Titres[[#This Row],[Janvier 2019]:[Août 2024]]) -> 1230.39 | AW67: 54.4 | AZ67: 51.26 | BC67: 53.8 | BF67: 51.86 | BI67: 53.34 | BL67: 67.07 | BO67: 47.97 | BR67: 56.22 | BU67: 63.83 | BX67: 109.71 | CA67: 98.44 | CD67: 97.04 | CG67: 94.95 | CJ67: 112.44 | CM67: 105.04 | CP67: 113.02 | CS67: 107 | CV67: 120.07 | CY67: 119.44 | DB67: 129.21 | DE67: 128.6 | DH67: 137.53
B68: =IF(C68="","",_xlfn.XLOOKUP(C68,Type_Compte,Num_Compte)) -> 20K6HU7 | C68: REER (USD) | D68: #VALUE! | E68: {=_FV(Titres[[#This Row],[Action]],"Code mnémonique",TRUE)} -> WMT | F68: {=_FV(D68,"Change")} -> Nasdaq Stock Market | G68: {=IFERROR(_FV(Titres[[#This Row],[Action]],"Industrie"),"")} -> Food & Drug Retailing | H68: Actions américaines | I68: {=_FV(D68,"Devise")} -> USD | J68: 72 | K68: 21.06 | L68: =J68*K68 -> 1516.32 | M68: {=_FV(D68,"Prix")} -> 129.6 | N68: =J68*M68 -> 9331.2 | O68: =IF(Titres[[#This Row],[Devise]]="CAD",Titres[[#This Row],[Valeur au marché ($ local)]],Titres[[#This Row],[Valeur au marché ($ local)]]*Ressources!$I$3) -> 12746.419 | P68: {=(Titres[[#This Row],[Prix actuel]]-_FV(Titres[[#This Row],[Action]],"Clôture précédente",TRUE))*Titres[[#This Row],[Nb d''actions]]} -> 120.96 | Q68: =Titres[[#This Row],[Variation du jour ($)]]/(Titres[[#This Row],[Valeur au marché ($ local)]]-Titres[[#This Row],[Variation du jour ($)]]) -> 0.013133208 | R68: =Titres[[#This Row],[Valeur au marché ($ local)]]-Titres[[#This Row],[Coût total]] -> 7814.88 | S68: =Titres[[#This Row],[Gain non réalisé ($)]]/Titres[[#This Row],[Coût total]] -> 5.1538462 | T68: 0.235 | U68: =4*Titres[[#This Row],[Dividende trimestriel]] -> 0.94 | V68: =Titres[[#This Row],[Dividende annuel]]*Titres[[#This Row],[Nb d''actions]] -> 67.68 | W68: =Titres[[#This Row],[Dividende annuel]]/Titres[[#This Row],[Prix actuel]] -> 0.0072530864 | X68: =Titres[[#This Row],[Dividende annuel]]/Titres[[#This Row],[Coût moyen]] -> 0.044634378 | Y68: 49 | Z68: =(((Titres[[#This Row],[Valeur au marché ($ local)]]-Titres[[#This Row],[Coût total]])+Titres[[#This Row],[Total - dividendes reçus]])/Titres[[#This Row],[Coût total]]) -> 5.3558879 | AA68: =SUM(Titres[[#This Row],[Janvier 2019]:[Août 2024]]) -> 306.36 | AB68: 12.48 | AE68: 12.72 | AG68: 12.72 | AJ68: 12.72 | AN68: 12.72 | AQ68: 12.96 | AS68: 12.96 | AV68: 12.96 | AZ68: 12.96 | BC68: 13.2 | BE68: 13.2 | BH68: 13.2 | BL68: 13.2 | BO68: 13.44 | BP68: 13.44 | BT68: 13.44 | BX68: 13.44 | CA68: 13.68 | CB68: 13.68 | CF68: 13.68 | CJ68: 13.68 | CM68: 14.94 | CN68: 14.94 | CR68: 14.94 | CV68: 14.94 | CY68: 16.92 | CZ68: 16.92 | DD68: 16.92 | DH68: 16.92
B69: =IF(C69="","",_xlfn.XLOOKUP(C69,Type_Compte,Num_Compte)) -> 20K6HU7 | C69: REER (USD) | D69: #VALUE! | E69: {=_FV(Titres[[#This Row],[Action]],"Code mnémonique",TRUE)} -> WBD | F69: {=_FV(D69,"Change")} -> Nasdaq Stock Market | G69: {=IFERROR(_FV(Titres[[#This Row],[Action]],"Industrie"),"")} -> Media & Publishing | H69: Actions américaines | I69: {=_FV(D69,"Devise")} -> USD | J69: 10 | K69: 24.08 | L69: =J69*K69 -> 240.8 | M69: {=_FV(D69,"Prix")} -> 27.31 | N69: =J69*M69 -> 273.1 | O69: =IF(Titres[[#This Row],[Devise]]="CAD",Titres[[#This Row],[Valeur au marché ($ local)]],Titres[[#This Row],[Valeur au marché ($ local)]]*Ressources!$I$3) -> 373.0546 | P69: {=(Titres[[#This Row],[Prix actuel]]-_FV(Titres[[#This Row],[Action]],"Clôture précédente",TRUE))*Titres[[#This Row],[Nb d''actions]]} -> -1.1 | Q69: =Titres[[#This Row],[Variation du jour ($)]]/(Titres[[#This Row],[Valeur au marché ($ local)]]-Titres[[#This Row],[Variation du jour ($)]]) -> -0.0040116703 | R69: =Titres[[#This Row],[Valeur au marché ($ local)]]-Titres[[#This Row],[Coût total]] -> 32.3 | S69: =Titres[[#This Row],[Gain non réalisé ($)]]/Titres[[#This Row],[Coût total]] -> 0.13413621 | T69: 0 | U69: =4*Titres[[#This Row],[Dividende trimestriel]] -> 0 | V69: =Titres[[#This Row],[Dividende annuel]]*Titres[[#This Row],[Nb d''actions]] -> 0 | W69: =Titres[[#This Row],[Dividende annuel]]/Titres[[#This Row],[Prix actuel]] -> 0 | X69: =Titres[[#This Row],[Dividende annuel]]/Titres[[#This Row],[Coût moyen]] -> 0 | Y69: 0 | Z69: =(((Titres[[#This Row],[Valeur au marché ($ local)]]-Titres[[#This Row],[Coût total]])+Titres[[#This Row],[Total - dividendes reçus]])/Titres[[#This Row],[Coût total]]) -> 0.13413621 | AA69: =SUM(Titres[[#This Row],[Janvier 2019]:[Août 2024]]) -> 0
B70: =IF(C70="","",_xlfn.XLOOKUP(C70,Type_Compte,Num_Compte)) -> 20K6HZ6 | C70: CELI (CAD) | D70: #VALUE! | E70: {=_FV(Titres[[#This Row],[Action]],"Code mnémonique",TRUE)} -> SUNC | F70: {=_FV(D70,"Change")} -> New York Stock Exchange | G70: {=IFERROR(_FV(Titres[[#This Row],[Action]],"Industrie"),"")} | H70: Actions canadiennes | I70: {=_FV(D70,"Devise")} -> USD | J70: 32 | K70: 72.1 | L70: =J70*K70 -> 2307.2 | M70: {=_FV(D70,"Prix")} -> 62.2 | N70: =J70*M70 -> 1990.4 | O70: =IF(Titres[[#This Row],[Devise]]="CAD",Titres[[#This Row],[Valeur au marché ($ local)]],Titres[[#This Row],[Valeur au marché ($ local)]]*Ressources!$I$3) -> 2718.8864 | P70: {=(Titres[[#This Row],[Prix actuel]]-_FV(Titres[[#This Row],[Action]],"Clôture précédente",TRUE))*Titres[[#This Row],[Nb d''actions]]} -> 35.52 | Q70: =Titres[[#This Row],[Variation du jour ($)]]/(Titres[[#This Row],[Valeur au marché ($ local)]]-Titres[[#This Row],[Variation du jour ($)]]) -> 0.018169913 | R70: =Titres[[#This Row],[Valeur au marché ($ local)]]-Titres[[#This Row],[Coût total]] -> -316.8 | S70: =Titres[[#This Row],[Gain non réalisé ($)]]/Titres[[#This Row],[Coût total]] -> -0.13730929 | T70: 0.932 | U70: =4*Titres[[#This Row],[Dividende trimestriel]] -> 3.728 | V70: =Titres[[#This Row],[Dividende annuel]]*Titres[[#This Row],[Nb d''actions]] -> 119.296 | W70: =Titres[[#This Row],[Dividende annuel]]/Titres[[#This Row],[Prix actuel]] -> 0.059935691 | X70: =Titres[[#This Row],[Dividende annuel]]/Titres[[#This Row],[Coût moyen]] -> 0.051705964 | Z70: =(((Titres[[#This Row],[Valeur au marché ($ local)]]-Titres[[#This Row],[Coût total]])+Titres[[#This Row],[Total - dividendes reçus]])/Titres[[#This Row],[Coût total]]) -> -0.12789528 | AA70: =SUM(Titres[[#This Row],[Janvier 2019]:[Août 2024]]) -> 21.72 | CE70: =25.55-3.83 -> 21.72 | DI70: 34.18
B71: =IF(C71="","",_xlfn.XLOOKUP(C71,Type_Compte,Num_Compte)) -> 20K6HU7 | C71: REER (USD) | D71: #VALUE! | E71: {=_FV(Titres[[#This Row],[Action]],"Code mnémonique",TRUE)} -> DIS | F71: {=_FV(D71,"Change")} -> New York Stock Exchange | G71: {=IFERROR(_FV(Titres[[#This Row],[Action]],"Industrie"),"")} -> Media & Publishing | H71: Actions américaines | I71: {=_FV(D71,"Devise")} -> USD | J71: 51 | K71: 85.23 | L71: =J71*K71 -> 4346.73 | M71: {=_FV(D71,"Prix")} -> 104.3 | N71: =J71*M71 -> 5319.3 | O71: =IF(Titres[[#This Row],[Devise]]="CAD",Titres[[#This Row],[Valeur au marché ($ local)]],Titres[[#This Row],[Valeur au marché ($ local)]]*Ressources!$I$3) -> 7266.1638 | P71: {=(Titres[[#This Row],[Prix actuel]]-_FV(Titres[[#This Row],[Action]],"Clôture précédente",TRUE))*Titres[[#This Row],[Nb d''actions]]} -> -102 | Q71: =Titres[[#This Row],[Variation du jour ($)]]/(Titres[[#This Row],[Valeur au marché ($ local)]]-Titres[[#This Row],[Variation du jour ($)]]) -> -0.018814675 | R71: =Titres[[#This Row],[Valeur au marché ($ local)]]-Titres[[#This Row],[Coût total]] -> 972.57 | S71: =Titres[[#This Row],[Gain non réalisé ($)]]/Titres[[#This Row],[Coût total]] -> 0.22374751 | T71: 0.75 | U71: =4*Titres[[#This Row],[Dividende trimestriel]] -> 3 | V71: =Titres[[#This Row],[Dividende annuel]]*Titres[[#This Row],[Nb d''actions]] -> 153 | W71: =Titres[[#This Row],[Dividende annuel]]/Titres[[#This Row],[Prix actuel]] -> 0.028763183 | X71: =Titres[[#This Row],[Dividende annuel]]/Titres[[#This Row],[Coût moyen]] -> 0.035198874 | Z71: =(((Titres[[#This Row],[Valeur au marché ($ local)]]-Titres[[#This Row],[Coût total]])+Titres[[#This Row],[Total - dividendes reçus]])/Titres[[#This Row],[Coût total]]) -> 0.22874437 | AA71: =SUM(Titres[[#This Row],[Janvier 2019]:[Août 2024]]) -> 21.72 | CE71: =25.55-3.83 -> 21.72 | CV71: 25.5 | DB71: 25.5 | DH71: 38.25
B72: =IF(C72="","",_xlfn.XLOOKUP(C72,Type_Compte,Num_Compte)) -> 20K6HZ6 | C72: CELI (CAD) | D72: #VALUE! | E72: {=_FV(Titres[[#This Row],[Action]],"Code mnémonique",TRUE)} -> TRP | F72: {=_FV(D72,"Change")} -> Toronto Stock Exchange | G72: {=IFERROR(_FV(Titres[[#This Row],[Action]],"Industrie"),"")} -> Oil & Gas Related Equipment and Services | H72: Actions canadiennes | I72: {=_FV(D72,"Devise")} -> CAD | J72: 45 | K72: 63.65 | L72: =J72*K72 -> 2864.25 | M72: {=_FV(D72,"Prix")} -> 82.21 | N72: =J72*M72 -> 3699.45 | O72: =IF(Titres[[#This Row],[Devise]]="CAD",Titres[[#This Row],[Valeur au marché ($ local)]],Titres[[#This Row],[Valeur au marché ($ local)]]*Ressources!$I$3) -> 3699.45 | P72: {=(Titres[[#This Row],[Prix actuel]]-_FV(Titres[[#This Row],[Action]],"Clôture précédente",TRUE))*Titres[[#This Row],[Nb d''actions]]} -> -36.9 | Q72: =Titres[[#This Row],[Variation du jour ($)]]/(Titres[[#This Row],[Valeur au marché ($ local)]]-Titres[[#This Row],[Variation du jour ($)]]) -> -0.0098759485 | R72: =Titres[[#This Row],[Valeur au marché ($ local)]]-Titres[[#This Row],[Coût total]] -> 835.2 | S72: =Titres[[#This Row],[Gain non réalisé ($)]]/Titres[[#This Row],[Coût total]] -> 0.29159466 | T72: 0.85 | U72: =4*Titres[[#This Row],[Dividende trimestriel]] -> 3.4 | V72: =Titres[[#This Row],[Dividende annuel]]*Titres[[#This Row],[Nb d''actions]] -> 153 | W72: =Titres[[#This Row],[Dividende annuel]]/Titres[[#This Row],[Prix actuel]] -> 0.041357499 | X72: =Titres[[#This Row],[Dividende annuel]]/Titres[[#This Row],[Coût moyen]] -> 0.053417125 | Y72: 3 | Z72: =(((Titres[[#This Row],[Valeur au marché ($ local)]]-Titres[[#This Row],[Coût total]])+Titres[[#This Row],[Total - dividendes reçus]])/Titres[[#This Row],[Coût total]]) -> 0.60031422 | AA72: =SUM(Titres[[#This Row],[Janvier 2019]:[Août 2024]]) -> 884.25 | AB72: 31.05 | AE72: 33.75 | AH72: 33.75 | AK72: 33.75 | AN72: 33.75 | AQ72: 36.45 | AT72: 36.45 | AW72: 36.45 | AZ72: 36.45 | BC72: 39.15 | BF72: 39.15 | BI72: 39.15 | BL72: 39.15 | BO72: 40.5 | BR72: 40.5 | BU72: 40.5 | BX72: 40.5 | CA72: 41.85 | CD72: 41.85 | CG72: 41.85 | CJ72: 41.85 | CM72: 43.2 | CP72: 43.2 | CS72: 43.2 | CV72: 37.01 | CY72: 38.25 | DB72: 38.25 | DE72: 38.25 | DH72: 38.25
B73: =IF(C73="","",_xlfn.XLOOKUP(C73,Type_Compte,Num_Compte)) -> 20K6HE4 | C73: Marge (CAD) | D73: #VALUE! | E73: {=_FV(Titres[[#This Row],[Action]],"Code mnémonique",TRUE)} -> XIU | F73: {=_FV(D73,"Change")} -> Toronto Stock Exchange | G73: {=IFERROR(_FV(Titres[[#This Row],[Action]],"Industrie"),"")} | H73: Actions canadiennes | I73: {=_FV(D73,"Devise")} -> CAD | J73: 200 | K73: 42.065 | L73: =J73*K73 -> 8413 | M73: {=_FV(D73,"Prix")} -> 49.88 | N73: =J73*M73 -> 9976 | O73: =IF(Titres[[#This Row],[Devise]]="CAD",Titres[[#This Row],[Valeur au marché ($ local)]],Titres[[#This Row],[Valeur au marché ($ local)]]*Ressources!$I$3) -> 9976 | P73: {=(Titres[[#This Row],[Prix actuel]]-_FV(Titres[[#This Row],[Action]],"Clôture précédente",TRUE))*Titres[[#This Row],[Nb d''actions]]} -> -126 | Q73: =Titres[[#This Row],[Variation du jour ($)]]/(Titres[[#This Row],[Valeur au marché ($ local)]]-Titres[[#This Row],[Variation du jour ($)]]) -> -0.012472778 | R73: =Titres[[#This Row],[Valeur au marché ($ local)]]-Titres[[#This Row],[Coût total]] -> 1563 | S73: =Titres[[#This Row],[Gain non réalisé ($)]]/Titres[[#This Row],[Coût total]] -> 0.18578391 | T73: 0.3 | U73: =4*Titres[[#This Row],[Dividende trimestriel]] -> 1.2 | V73: =Titres[[#This Row],[Dividende annuel]]*Titres[[#This Row],[Nb d''actions]] -> 240 | W73: =Titres[[#This Row],[Dividende annuel]]/Titres[[#This Row],[Prix actuel]] -> 0.024057739 | X73: =Titres[[#This Row],[Dividende annuel]]/Titres[[#This Row],[Coût moyen]] -> 0.028527279 | Z73: =(((Titres[[#This Row],[Valeur au marché ($ local)]]-Titres[[#This Row],[Coût total]])+Titres[[#This Row],[Total - dividendes reçus]])/Titres[[#This Row],[Coût total]]) -> 0.18836562 | AA73: =SUM(Titres[[#This Row],[Janvier 2019]:[Août 2024]]) -> 21.72 | CE73: =25.55-3.83 -> 21.72 | DC73: 55.6 | DF73: 60 | DI73: 55.4
B74: =IF(C74="","",_xlfn.XLOOKUP(C74,Type_Compte,Num_Compte)) -> 20K6HZ6 | C74: CELI (CAD) | D74: #VALUE! | E74: {=_FV(Titres[[#This Row],[Action]],"Code mnémonique",TRUE)} -> BNS | F74: {=_FV(D74,"Change")} -> Toronto Stock Exchange | G74: {=IFERROR(_FV(Titres[[#This Row],[Action]],"Industrie"),"")} -> Banking Services | H74: Actions canadiennes | I74: {=_FV(D74,"Devise")} -> CAD | J74: 76 | K74: 67.53 | L74: =J74*K74 -> 5132.28 | M74: {=_FV(D74,"Prix")} -> 103.78 | N74: =J74*M74 -> 7887.28 | O74: =IF(Titres[[#This Row],[Devise]]="CAD",Titres[[#This Row],[Valeur au marché ($ local)]],Titres[[#This Row],[Valeur au marché ($ local)]]*Ressources!$I$3) -> 7887.28 | P74: {=(Titres[[#This Row],[Prix actuel]]-_FV(Titres[[#This Row],[Action]],"Clôture précédente",TRUE))*Titres[[#This Row],[Nb d''actions]]} -> -84.36 | Q74: =Titres[[#This Row],[Variation du jour ($)]]/(Titres[[#This Row],[Valeur au marché ($ local)]]-Titres[[#This Row],[Variation du jour ($)]]) -> -0.010582515 | R74: =Titres[[#This Row],[Valeur au marché ($ local)]]-Titres[[#This Row],[Coût total]] -> 2755 | S74: =Titres[[#This Row],[Gain non réalisé ($)]]/Titres[[#This Row],[Coût total]] -> 0.53679846 | T74: 1.1 | U74: =4*Titres[[#This Row],[Dividende trimestriel]] -> 4.4 | V74: =Titres[[#This Row],[Dividende annuel]]*Titres[[#This Row],[Nb d''actions]] -> 334.4 | W74: =Titres[[#This Row],[Dividende annuel]]/Titres[[#This Row],[Prix actuel]] -> 0.042397379 | X74: =Titres[[#This Row],[Dividende annuel]]/Titres[[#This Row],[Coût moyen]] -> 0.065156227 | Y74: 1 | Z74: =(((Titres[[#This Row],[Valeur au marché ($ local)]]-Titres[[#This Row],[Coût total]])+Titres[[#This Row],[Total - dividendes reçus]])/Titres[[#This Row],[Coût total]]) -> 0.70244803 | AA74: =SUM(Titres[[#This Row],[Janvier 2019]:[Août 2024]]) -> 850.16 | AE74: 31.32 | AH74: 31.32 | AK74: 32.4 | AN74: 32.4 | AQ74: 32.4 | AT74: 32.4 | AW74: 32.4 | AZ74: 32.4 | BC74: 32.4 | BF74: 32.4 | BI74: 32.4 | BL74: 36 | BO74: 36 | BR74: 37.08 | BU74: 37.08 | BX74: 37.08 | CA74: 37.08 | CD74: 38.16 | CG74: 38.16 | CJ74: 38.16 | CM74: 80.56 | CP74: 80.56 | CS74: 80.56 | CV74: 80.56 | CY74: 80.56 | DB74: 83.6 | DE74: 83.6 | DH74: 83.6
B75: =IF(C75="","",_xlfn.XLOOKUP(C75,Type_Compte,Num_Compte)) -> 20K6HZ6 | C75: CELI (CAD) | D75: #VALUE! | E75: {=_FV(Titres[[#This Row],[Action]],"Code mnémonique",TRUE)} -> NWC | F75: {=_FV(D75,"Change")} -> Toronto Stock Exchange | G75: {=IFERROR(_FV(Titres[[#This Row],[Action]],"Industrie"),"")} -> Food & Drug Retailing | H75: Actions canadiennes | I75: {=_FV(D75,"Devise")} -> CAD | J75: 125 | K75: 27.7 | L75: =J75*K75 -> 3462.5 | M75: {=_FV(D75,"Prix")} -> 51.79 | N75: =J75*M75 -> 6473.75 | O75: =IF(Titres[[#This Row],[Devise]]="CAD",Titres[[#This Row],[Valeur au marché ($ local)]],Titres[[#This Row],[Valeur au marché ($ local)]]*Ressources!$I$3) -> 6473.75 | P75: {=(Titres[[#This Row],[Prix actuel]]-_FV(Titres[[#This Row],[Action]],"Clôture précédente",TRUE))*Titres[[#This Row],[Nb d''actions]]} -> -23.75 | Q75: =Titres[[#This Row],[Variation du jour ($)]]/(Titres[[#This Row],[Valeur au marché ($ local)]]-Titres[[#This Row],[Variation du jour ($)]]) -> -0.003655252 | R75: =Titres[[#This Row],[Valeur au marché ($ local)]]-Titres[[#This Row],[Coût total]] -> 3011.25 | S75: =Titres[[#This Row],[Gain non réalisé ($)]]/Titres[[#This Row],[Coût total]] -> 0.86967509 | T75: 0.41 | U75: =4*Titres[[#This Row],[Dividende trimestriel]] -> 1.64 | V75: =Titres[[#This Row],[Dividende annuel]]*Titres[[#This Row],[Nb d''actions]] -> 205 | W75: =Titres[[#This Row],[Dividende annuel]]/Titres[[#This Row],[Prix actuel]] -> 0.031666345 | X75: =Titres[[#This Row],[Dividende annuel]]/Titres[[#This Row],[Coût moyen]] -> 0.059205776 | Y75: 4 | Z75: =(((Titres[[#This Row],[Valeur au marché ($ local)]]-Titres[[#This Row],[Coût total]])+Titres[[#This Row],[Total - dividendes reçus]])/Titres[[#This Row],[Coût total]]) -> 1.1101083 | AA75: =SUM(Titres[[#This Row],[Janvier 2019]:[Août 2024]]) -> 832.5 | AQ75: 41.25 | AT75: 41.25 | AW75: 45 | AZ75: 45 | BC75: 45 | BF75: 45 | BI75: 46.25 | BL75: 46.25 | BO75: 46.25 | BR75: 46.25 | BU75: 47.5 | BX75: 47.5 | CA75: 47.5 | CD75: 47.5 | CG75: 48.75 | CJ75: 48.75 | CM75: 48.75 | CP75: 48.75 | CS75: 50 | CV75: 50 | CY75: 50 | DB75: 50 | DE75: 51.25 | DH75: 51.25
B76: =IF(C76="","",_xlfn.XLOOKUP(C76,Type_Compte,Num_Compte)) -> 20K6HZ6 | C76: CELI (CAD) | D76: #VALUE! | E76: {=_FV(Titres[[#This Row],[Action]],"Code mnémonique",TRUE)} -> X | F76: {=_FV(D76,"Change")} -> Toronto Stock Exchange | G76: {=IFERROR(_FV(Titres[[#This Row],[Action]],"Industrie"),"")} -> Investment Banking & Investment Services | I76: {=_FV(D76,"Devise")} -> CAD | J76: 100 | K76: 50.82 | L76: =J76*K76 -> 5082 | M76: {=_FV(D76,"Prix")} -> 53.89 | N76: =J76*M76 -> 5389 | O76: =IF(Titres[[#This Row],[Devise]]="CAD",Titres[[#This Row],[Valeur au marché ($ local)]],Titres[[#This Row],[Valeur au marché ($ local)]]*Ressources!$I$3) -> 5389 | P76: {=(Titres[[#This Row],[Prix actuel]]-_FV(Titres[[#This Row],[Action]],"Clôture précédente",TRUE))*Titres[[#This Row],[Nb d''actions]]} -> -28 | Q76: =Titres[[#This Row],[Variation du jour ($)]]/(Titres[[#This Row],[Valeur au marché ($ local)]]-Titres[[#This Row],[Variation du jour ($)]]) -> -0.0051689127 | R76: =Titres[[#This Row],[Valeur au marché ($ local)]]-Titres[[#This Row],[Coût total]] -> 307 | S76: =Titres[[#This Row],[Gain non réalisé ($)]]/Titres[[#This Row],[Coût total]] -> 0.060409288 | T76: 0.22 | U76: =4*Titres[[#This Row],[Dividende trimestriel]] -> 0.88 | V76: =Titres[[#This Row],[Dividende annuel]]*Titres[[#This Row],[Nb d''actions]] -> 88 | W76: =Titres[[#This Row],[Dividende annuel]]/Titres[[#This Row],[Prix actuel]] -> 0.01632956 | X76: =Titres[[#This Row],[Dividende annuel]]/Titres[[#This Row],[Coût moyen]] -> 0.017316017 | Z76: =(((Titres[[#This Row],[Valeur au marché ($ local)]]-Titres[[#This Row],[Coût total]])+Titres[[#This Row],[Total - dividendes reçus]])/Titres[[#This Row],[Coût total]]) -> 0.064683196 | AA76: =SUM(Titres[[#This Row],[Janvier 2019]:[Août 2024]]) -> 21.72 | CE76: =25.55-3.83 -> 21.72 | DA76: 20 | DC76: 22 | DF76: 22
B77: =IF(C77="","",_xlfn.XLOOKUP(C77,Type_Compte,Num_Compte)) -> 20K6HU7 | C77: REER (USD) | D77: #VALUE! | E77: {=_FV(Titres[[#This Row],[Action]],"Code mnémonique",TRUE)} -> IEFA | F77: {=_FV(D77,"Change")} -> CBOE BZX Exchange | G77: {=IFERROR(_FV(Titres[[#This Row],[Action]],"Industrie"),"")} | H77: Actions internationales | I77: {=_FV(D77,"Devise")} -> USD | J77: 40 | K77: 93.95 | L77: =J77*K77 -> 3758 | M77: {=_FV(D77,"Prix")} -> 94.93 | N77: =J77*M77 -> 3797.2 | O77: =IF(Titres[[#This Row],[Devise]]="CAD",Titres[[#This Row],[Valeur au marché ($ local)]],Titres[[#This Row],[Valeur au marché ($ local)]]*Ressources!$I$3) -> 5186.9752 | P77: {=(Titres[[#This Row],[Prix actuel]]-_FV(Titres[[#This Row],[Action]],"Clôture précédente",TRUE))*Titres[[#This Row],[Nb d''actions]]} -> -84.4 | Q77: =Titres[[#This Row],[Variation du jour ($)]]/(Titres[[#This Row],[Valeur au marché ($ local)]]-Titres[[#This Row],[Variation du jour ($)]]) -> -0.021743611 | R77: =Titres[[#This Row],[Valeur au marché ($ local)]]-Titres[[#This Row],[Coût total]] -> 39.2 | S77: =Titres[[#This Row],[Gain non réalisé ($)]]/Titres[[#This Row],[Coût total]] -> 0.01043108 | T77: 1.711 | U77: =4*Titres[[#This Row],[Dividende trimestriel]] -> 6.844 | V77: =Titres[[#This Row],[Dividende annuel]]*Titres[[#This Row],[Nb d''actions]] -> 273.76 | W77: =Titres[[#This Row],[Dividende annuel]]/Titres[[#This Row],[Prix actuel]] -> 0.072095228 | X77: =Titres[[#This Row],[Dividende annuel]]/Titres[[#This Row],[Coût moyen]] -> 0.072847259 | Z77: =(((Titres[[#This Row],[Valeur au marché ($ local)]]-Titres[[#This Row],[Coût total]])+Titres[[#This Row],[Total - dividendes reçus]])/Titres[[#This Row],[Coût total]]) -> 0.01043108 | AA77: =SUM(Titres[[#This Row],[Janvier 2019]:[Août 2024]]) -> 0
B78: =IF(C78="","",_xlfn.XLOOKUP(C78,Type_Compte,Num_Compte)) -> 20K6HE4 | C78: Marge (CAD) | D78: #VALUE! | E78: {=_FV(Titres[[#This Row],[Action]],"Code mnémonique",TRUE)} -> IEFA | F78: {=_FV(D78,"Change")} -> CBOE BZX Exchange | G78: {=IFERROR(_FV(Titres[[#This Row],[Action]],"Industrie"),"")} | H78: Actions internationales | I78: {=_FV(D78,"Devise")} -> USD | J78: 110 | K78: 92.015 | L78: =J78*K78 -> 10121.65 | M78: {=_FV(D78,"Prix")} -> 94.93 | N78: =J78*M78 -> 10442.3 | O78: =IF(Titres[[#This Row],[Devise]]="CAD",Titres[[#This Row],[Valeur au marché ($ local)]],Titres[[#This Row],[Valeur au marché ($ local)]]*Ressources!$I$3) -> 14264.182 | P78: {=(Titres[[#This Row],[Prix actuel]]-_FV(Titres[[#This Row],[Action]],"Clôture précédente",TRUE))*Titres[[#This Row],[Nb d''actions]]} -> -232.1 | Q78: =Titres[[#This Row],[Variation du jour ($)]]/(Titres[[#This Row],[Valeur au marché ($ local)]]-Titres[[#This Row],[Variation du jour ($)]]) -> -0.021743611 | R78: =Titres[[#This Row],[Valeur au marché ($ local)]]-Titres[[#This Row],[Coût total]] -> 320.65 | S78: =Titres[[#This Row],[Gain non réalisé ($)]]/Titres[[#This Row],[Coût total]] -> 0.031679617 | T78: 1.711 | U78: =4*Titres[[#This Row],[Dividende trimestriel]] -> 6.844 | V78: =Titres[[#This Row],[Dividende annuel]]*Titres[[#This Row],[Nb d''actions]] -> 752.84 | W78: =Titres[[#This Row],[Dividende annuel]]/Titres[[#This Row],[Prix actuel]] -> 0.072095228 | X78: =Titres[[#This Row],[Dividende annuel]]/Titres[[#This Row],[Coût moyen]] -> 0.074379177 | Z78: =(((Titres[[#This Row],[Valeur au marché ($ local)]]-Titres[[#This Row],[Coût total]])+Titres[[#This Row],[Total - dividendes reçus]])/Titres[[#This Row],[Coût total]]) -> 0.031679617 | AA78: =SUM(Titres[[#This Row],[Janvier 2019]:[Août 2024]]) -> 0
B79: Total | E79: =SUBTOTAL(103,Titres[Symbole]) -> 73 | K79: =SUBTOTAL(101,Titres[Coût moyen]) -> 59.307614 | L79: =SUBTOTAL(109,Titres[Coût total]) -> 388303.04 | M79: =SUBTOTAL(101,Titres[Prix actuel]) -> 108.79138 | N79: =SUBTOTAL(109,Titres[Valeur au marché ($ local)]) -> 626994.02 | O79: =SUBTOTAL(109,Titres[Valeur au marché (CAD)]) -> 672201.79 | P79: =SUBTOTAL(109,Titres[Variation du jour ($)]) -> -4389.715 | Q79: =Titres[[#Totals],[Variation du jour ($)]]/(Titres[[#Totals],[Valeur au marché ($ local)]]-Titres[[#Totals],[Variation du jour ($)]]) -> -0.0069525311 | R79: =SUBTOTAL(109,Titres[Gain non réalisé ($)]) -> 238690.98 | S79: =Titres[[#Totals],[Gain non réalisé ($)]]/Titres[[#Totals],[Coût total]] -> 0.61470284 | T79: =SUBTOTAL(109,Titres[Dividende trimestriel]) -> 48.336 | U79: =SUBTOTAL(109,Titres[Dividende annuel]) -> 193.344 | V79: =SUBTOTAL(109,Titres[Revenu annuel anticipé]) -> 17184.78 | W79: =Titres[[#Totals],[Revenu annuel anticipé]]/Titres[[#Totals],[Valeur au marché ($ local)]] -> 0.027408204 | X79: =SUBTOTAL(101,Titres[$ de dividendes par $ investi]) -> 0.04721488 | Z79: =(((Titres[[#Totals],[Valeur au marché ($ local)]]-Titres[[#Totals],[Coût total]])+Titres[[#Totals],[Total - dividendes reçus]])/Titres[[#Totals],[Coût total]]) -> 0.72106598 | AA79: =SUBTOTAL(109,Titres[Total - dividendes reçus]) -> 41301.13 | AB79: =SUBTOTAL(109,Titres[Janvier 2019]) -> 215.75 | AC79: =SUBTOTAL(109,Titres[Février 2019]) -> 221.23 | AD79: =SUBTOTAL(109,Titres[Mars 2019]) -> 332.43 | AE79: =SUBTOTAL(109,Titres[Avril 2019]) -> 228.4 | AF79: =SUBTOTAL(109,Titres[Mai 2019]) -> 233.05 | AG79: =SUBTOTAL(109,Titres[Juin 2019]) -> 386.17 | AH79: =SUBTOTAL(109,Titres[Juillet 2019]) -> 246.33 | AI79: =SUBTOTAL(109,Titres[Août 2019]) -> 235.15 | AJ79: =SUBTOTAL(109,Titres[Septembre 2019]) -> 387.1 | AK79: =SUBTOTAL(109,Titres[Octobre 2019]) -> 250.8 | AL79: =SUBTOTAL(109,Titres[Novembre 2019]) -> 237.45 | AM79: =SUBTOTAL(109,Titres[Décembre 2019]) -> 381.17 | AN79: =SUBTOTAL(109,Titres[Janvier 2020]) -> 338.88 | AO79: =SUBTOTAL(109,Titres[Février 2020]) -> 212.84 | AP79: =SUBTOTAL(109,Titres[Mars 2020]) -> 449.81 | AQ79: =SUBTOTAL(109,Titres[Avril 2020]) -> 417.01 | AR79: =SUBTOTAL(109,Titres[Mai 2020]) -> 260.65 | AS79: =SUBTOTAL(109,Titres[Juin 2020]) -> 464 | AT79: =SUBTOTAL(109,Titres[Juillet 2020]) -> 524.28 | AU79: =SUBTOTAL(109,Titres[Août 2020]) -> 204.46 | AV79: =SUBTOTAL(109,Titres[Septembre 2020]) -> 464 | AW79: =SUBTOTAL(109,Titres[Octobre 2020]) -> 563.16 | AX79: =SUBTOTAL(109,Titres[Novembre 2020]) -> 198.64 | AY79: =SUBTOTAL(109,Titres[Décembre 2020]) -> 423.63 | AZ79: =SUBTOTAL(109,Titres[Janvier 2021]) -> 533.47 | BA79: =SUBTOTAL(109,Titres[Février 2021]) -> 382.65 | BB79: =SUBTOTAL(109,Titres[Mars 2021]) -> 501.32 | BC79: =SUBTOTAL(109,Titres[Avril 2021]) -> 755.15 | BD79: =SUBTOTAL(109,Titres[Mai 2021]) -> 246.81 | BE79: =SUBTOTAL(109,Titres[Juin 2021]) -> 516.81 | BF79: =SUBTOTAL(109,Titres[Juillet 2021]) -> 783.27 | BG79: =SUBTOTAL(109,Titres[Août 2021]) -> 284.73 | BH79: =SUBTOTAL(109,Titres[Septembre 2021]) -> 481.83 | BI79: =SUBTOTAL(109,Titres[Octobre 2021]) -> 774.44 | BJ79: =SUBTOTAL(109,Titres[Novembre 2021]) -> 400.54 | BK79: =SUBTOTAL(109,Titres[Décembre 2021]) -> 566.65 | BL79: =SUBTOTAL(109,Titres[Janvier 2022]) -> 902.47 | BM79: =SUBTOTAL(109,Titres[Février 2022]) -> 388.74 | BN79: =SUBTOTAL(109,Titres[Mars 2022]) -> 675.25 | BO79: =SUBTOTAL(109,Titres[Avril 2022]) -> 1005.16 | BP79: =SUBTOTAL(109,Titres[Mai 2022]) -> 309.41 | BQ79: =SUBTOTAL(109,Titres[Juin 2022]) -> 692.29 | BR79: =SUBTOTAL(109,Titres[Juillet 2022]) -> 1138.79 | BS79: =SUBTOTAL(109,Titres[Août 2022]) -> 305.44 | BT79: =SUBTOTAL(109,Titres[Septembre 2022]) -> 672.17 | BU79: =SUBTOTAL(109,Titres[Octobre 2022]) -> 1199.71 | BV79: =SUBTOTAL(109,Titres[Novembre 2022]) -> 390.82 | BW79: =SUBTOTAL(109,Titres[Décembre 2022]) -> 809.37 | BX79: =SUBTOTAL(109,Titres[Janvier 2023]) -> 1257.49 | BY79: =SUBTOTAL(109,Titres[Février 2023]) -> 396.95 | BZ79: =SUBTOTAL(109,Titres[Mars 2023]) -> 531.83 | CA79: =SUBTOTAL(109,Titres[Avril 2023]) -> 1354.98 | CB79: =SUBTOTAL(109,Titres[Mai 2023]) -> 486.87 | CC79: =SUBTOTAL(109,Titres[.Juin 2023]) -> 846.28 | CD79: =SUBTOTAL(109,Titres[Juillet 2023]) -> 1402.3 | CE79: =SUBTOTAL(109,Titres[Août 2023]) -> 721.78 | CF79: =SUBTOTAL(109,Titres[Septembre 2023]) -> 835.06 | CG79: =SUBTOTAL(109,Titres[Octobre 2023]) -> 1402.49 | CH79: =SUBTOTAL(109,Titres[Novembre 2023]) -> 435.43 | CI79: =SUBTOTAL(109,Titres[Décembre 2023]) -> 840.4 | CJ79: =SUBTOTAL(109,Titres[Janvier 2024]) -> 1571.71 | CK79: =SUBTOTAL(109,Titres[Février 2024]) -> 439.99 | CL79: =SUBTOTAL(109,Titres[Mars 2024]) -> 1448.14 | CM79: =SUBTOTAL(109,Titres[Avril 2024]) -> 1171.76 | CN79: =SUBTOTAL(109,Titres[Mai 2024]) -> 476.96 | CO79: =SUBTOTAL(109,Titres[Juin 2024]) -> 507.93 | CP79: =SUBTOTAL(109,Titres[Juillet 2024]) -> 2121.81 | CQ79: =SUBTOTAL(109,Titres[Août 2024]) -> 457.29 | CR79: =SUBTOTAL(109,Titres[Septembre 2024]) -> 1582.27 | CS79: =SUBTOTAL(109,Titres[Octobre 2024]) -> 956.38 | CT79: =SUBTOTAL(109,Titres[Novembre 2024]) -> 480.05 | CU79: =SUBTOTAL(109,Titres[Décembre 2024]) -> 913.29 | CV79: =SUBTOTAL(109,Titres[Janvier 2025]) -> 1951.04 | CW79: =SUBTOTAL(109,Titres[Février 2025]) -> 342.83 | CX79: =SUBTOTAL(109,Titres[Mars 2025]) -> 1633.56 | CY79: =SUBTOTAL(109,Titres[Avril 2025]) -> 1005.4 | CZ79: =SUBTOTAL(109,Titres[Mai 2025]) -> 620.53 | DA79: =SUBTOTAL(109,Titres[Juin 2025]) -> 1737.59 | DB79: =SUBTOTAL(109,Titres[Juillet 2025]) -> 1132.2 | DC79: =SUBTOTAL(109,Titres[Août 2025]) -> 690.68 | DD79: =SUBTOTAL(109,Titres[Septembre 2025]) -> 1674.41 | DE79: =SUBTOTAL(109,Titres[Octobre 2025]) -> 1177.56 | DF79: =SUBTOTAL(109,Titres[Novembre 2025]) -> 600.44 | DG79: =SUBTOTAL(109,Titres[Décembre 2025]) -> 982.98 | DH79: =SUBTOTAL(109,Titres[Janvier 2026]) -> 2237.06 | DI79: =SUBTOTAL(109,Titres[Février 2026]) -> 673.18

Sheet CRCD
B1: Capital régional et coopératif Desjardins (CRCD) | I1: Prix actuel : | J1: 19.45
B3: Année d'émission | C3: Nb | D3: Prix d'achat | E3: Coût total | F3: Admissibilité au rachat | G3: Prix actuel | H3: Valeur marchande | I3: Gain ($) | J3: Gain (%)
B4: 2022 | C4: 174.115 | D4: 17.23 | E4: =C4*D4 -> 3000.0015 | F4: 47389 | G4: =$J$1 -> 19.45 | H4: =Tableau4[[#This Row],[Nb]]*Tableau4[[#This Row],[Prix actuel]] -> 3386.5368 | I4: =Tableau4[[#This Row],[Valeur marchande]]-Tableau4[[#This Row],[Coût total]] -> 386.5353 | J4: =Tableau4[[#This Row],[Gain ($)]]/Tableau4[[#This Row],[Coût total]] -> 0.12884504
B5: 2024 | C5: 168.5391 | D5: 17.8 | E5: =C5*D5 -> 2999.996 | F5: 48116 | G5: =$J$1 -> 19.45 | H5: =Tableau4[[#This Row],[Nb]]*Tableau4[[#This Row],[Prix actuel]] -> 3278.0855 | I5: =Tableau4[[#This Row],[Valeur marchande]]-Tableau4[[#This Row],[Coût total]] -> 278.08951 | J5: =Tableau4[[#This Row],[Gain ($)]]/Tableau4[[#This Row],[Coût total]] -> 0.092696629
B6: 2025 | C6: 267.8092 | D6: 18.67 | E6: =C6*D6 -> 4999.9978 | F6: 48490 | G6: =$J$1 -> 19.45 | H6: =Tableau4[[#This Row],[Nb]]*Tableau4[[#This Row],[Prix actuel]] -> 5208.8889 | I6: =Tableau4[[#This Row],[Valeur marchande]]-Tableau4[[#This Row],[Coût total]] -> 208.89118 | J6: =Tableau4[[#This Row],[Gain ($)]]/Tableau4[[#This Row],[Coût total]] -> 0.041778254
B7: Total | E7: =SUBTOTAL(109,Tableau4[Coût total]) -> 10999.995 | H7: =SUBTOTAL(109,Tableau4[Valeur marchande]) -> 11873.511 | I7: =Tableau4[[#Totals],[Valeur marchande]]-Tableau4[[#Totals],[Coût total]] -> 873.51599 | J7: =Tableau4[[#Totals],[Gain ($)]]/Tableau4[[#Totals],[Coût total]] -> 0.079410579

Sheet Watchlist
B1: Liste de surveillance
B3: Source | C3: Politique ? | D3: Action | E3: Symbole | F3: Bourse | G3: Industrie | H3: Devise | I3: Prix actuel | J3: Mensuel ? | K3: Dividende trimestriel | L3: Dividende annuel | M3: Rendement des dividendes | N3: Croissance (années) | O3: Beta | P3: Capitalisation boursière (en milliard) | Q3: Année de constitution
B4: Dividend King | D4: #VALUE! | E4: {=_FV(Tableau8[[#This Row],[Action]],"Code mnémonique",TRUE)} -> LEG | F4: {=_FV(Tableau8[[#This Row],[Action]],"Change")} -> New York Stock Exchange | G4: {=IFERROR(_FV(Tableau8[[#This Row],[Action]],"industrie"),"")} -> Household Goods | H4: {=_FV(Tableau8[[#This Row],[Action]],"Devise")} -> USD | I4: {=_FV(Tableau8[[#This Row],[Action]],"Prix")} -> 11.67 | K4: 0.44 | L4: =4*Tableau8[[#This Row],[Dividende trimestriel]] -> 1.76 | M4: =Tableau8[[#This Row],[Dividende annuel]]/Tableau8[[#This Row],[Prix actuel]] -> 0.15081405 | N4: 29 | O4: {=IFERROR(_FV(Tableau8[[#This Row],[Action]],"Bêta"),"")} -> 0.8514 | P4: {=_FV(Tableau8[[#This Row],[Action]],"Capitalisation boursière",TRUE)} -> 1591820676 | Q4: {=IFERROR(_FV(Tableau8[[#This Row],[Action]],"Année de constitution",TRUE),"")} -> 1901
B5: Mes recherches | D5: #VALUE! | E5: {=_FV(Tableau8[[#This Row],[Action]],"Code mnémonique",TRUE)} -> JEPI | F5: {=_FV(Tableau8[[#This Row],[Action]],"Change")} -> NYSE Arca | G5: {=IFERROR(_FV(Tableau8[[#This Row],[Action]],"industrie"),"")} | H5: {=_FV(Tableau8[[#This Row],[Action]],"Devise")} -> USD | I5: {=_FV(Tableau8[[#This Row],[Action]],"Prix")} -> 57.53 | K5: 1.719 | L5: =4*Tableau8[[#This Row],[Dividende trimestriel]] -> 6.876 | M5: =Tableau8[[#This Row],[Dividende annuel]]/Tableau8[[#This Row],[Prix actuel]] -> 0.11952025 | N5: 2 | O5: {=IFERROR(_FV(Tableau8[[#This Row],[Action]],"Bêta"),"")} -> 0.4227 | P5: {=_FV(Tableau8[[#This Row],[Action]],"Capitalisation boursière",TRUE)} -> 4.3964335e+10 | Q5: {=IFERROR(_FV(Tableau8[[#This Row],[Action]],"Année de constitution",TRUE),"")}
B6: Aristocrats | D6: #VALUE! | E6: {=_FV(Tableau8[[#This Row],[Action]],"Code mnémonique",TRUE)} -> X | F6: {=_FV(Tableau8[[#This Row],[Action]],"Change")} -> Toronto Stock Exchange | G6: {=IFERROR(_FV(Tableau8[[#This Row],[Action]],"industrie"),"")} -> Investment Banking & Investment Services | H6: {=_FV(Tableau8[[#This Row],[Action]],"Devise")} -> CAD | I6: {=_FV(Tableau8[[#This Row],[Action]],"Prix")} -> 53.89 | K6: 0.83 | L6: =4*Tableau8[[#This Row],[Dividende trimestriel]] -> 3.32 | M6: =Tableau8[[#This Row],[Dividende annuel]]/Tableau8[[#This Row],[Prix actuel]] -> 0.061606977 | N6: 7 | O6: {=IFERROR(_FV(Tableau8[[#This Row],[Action]],"Bêta"),"")} -> 0.0351 | P6: {=_FV(Tableau8[[#This Row],[Action]],"Capitalisation boursière",TRUE)} -> 14930278390 | Q6: {=IFERROR(_FV(Tableau8[[#This Row],[Action]],"Année de constitution",TRUE),"")} -> 2017
B7: Aristocrats | D7: #VALUE! | E7: {=_FV(Tableau8[[#This Row],[Action]],"Code mnémonique",TRUE)} -> CNQ | F7: {=_FV(Tableau8[[#This Row],[Action]],"Change")} -> Toronto Stock Exchange | G7: {=IFERROR(_FV(Tableau8[[#This Row],[Action]],"industrie"),"")} -> Oil & Gas | H7: {=_FV(Tableau8[[#This Row],[Action]],"Devise")} -> CAD | I7: {=_FV(Tableau8[[#This Row],[Action]],"Prix")} -> 60.55 | K7: 0.85 | L7: =4*Tableau8[[#This Row],[Dividende trimestriel]] -> 3.4 | M7: =Tableau8[[#This Row],[Dividende annuel]]/Tableau8[[#This Row],[Prix actuel]] -> 0.056151941 | N7: 11 | O7: {=IFERROR(_FV(Tableau8[[#This Row],[Action]],"Bêta"),"")} -> 0.8447 | P7: {=_FV(Tableau8[[#This Row],[Action]],"Capitalisation boursière",TRUE)} -> 126301850500 | Q7: {=IFERROR(_FV(Tableau8[[#This Row],[Action]],"Année de constitution",TRUE),"")} -> 2015
B8: Dividend King | D8: #VALUE! | E8: {=_FV(Tableau8[[#This Row],[Action]],"Code mnémonique",TRUE)} -> UVV | F8: {=_FV(Tableau8[[#This Row],[Action]],"Change")} -> New York Stock Exchange | G8: {=IFERROR(_FV(Tableau8[[#This Row],[Action]],"industrie"),"")} -> Food & Tobacco | H8: {=_FV(Tableau8[[#This Row],[Action]],"Devise")} -> USD | I8: {=_FV(Tableau8[[#This Row],[Action]],"Prix")} -> 51.86 | K8: 0.79 | L8: =4*Tableau8[[#This Row],[Dividende trimestriel]] -> 3.16 | M8: =Tableau8[[#This Row],[Dividende annuel]]/Tableau8[[#This Row],[Prix actuel]] -> 0.060933282 | N8: 31 | O8: {=IFERROR(_FV(Tableau8[[#This Row],[Action]],"Bêta"),"")} -> 0.5786 | P8: {=_FV(Tableau8[[#This Row],[Action]],"Capitalisation boursière",TRUE)} -> 1292532710 | Q8: {=IFERROR(_FV(Tableau8[[#This Row],[Action]],"Année de constitution",TRUE),"")} -> 1918
B9: Aristocrats | D9: #VALUE! | E9: {=_FV(Tableau8[[#This Row],[Action]],"Code mnémonique",TRUE)} -> CU | F9: {=_FV(Tableau8[[#This Row],[Action]],"Change")} -> Toronto Stock Exchange | G9: {=IFERROR(_FV(Tableau8[[#This Row],[Action]],"industrie"),"")} -> Multiline Utilities | H9: {=_FV(Tableau8[[#This Row],[Action]],"Devise")} -> CAD | I9: {=_FV(Tableau8[[#This Row],[Action]],"Prix")} -> 47.92 | K9: 0.449 | L9: =4*Tableau8[[#This Row],[Dividende trimestriel]] -> 1.796 | M9: =Tableau8[[#This Row],[Dividende annuel]]/Tableau8[[#This Row],[Prix actuel]] -> 0.037479132 | N9: 8 | O9: {=IFERROR(_FV(Tableau8[[#This Row],[Action]],"Bêta"),"")} -> 0.5758 | P9: {=_FV(Tableau8[[#This Row],[Action]],"Capitalisation boursière",TRUE)} -> 9855548264 | Q9: {=IFERROR(_FV(Tableau8[[#This Row],[Action]],"Année de constitution",TRUE),"")} -> 1979
B10: Dividend King | D10: #VALUE! | E10: {=_FV(Tableau8[[#This Row],[Action]],"Code mnémonique",TRUE)} -> NWN | F10: {=_FV(Tableau8[[#This Row],[Action]],"Change")} -> New York Stock Exchange | G10: {=IFERROR(_FV(Tableau8[[#This Row],[Action]],"industrie"),"")} -> Natural Gas Utilities | H10: {=_FV(Tableau8[[#This Row],[Action]],"Devise")} -> USD | I10: {=_FV(Tableau8[[#This Row],[Action]],"Prix")} -> 52.24 | K10: 0.485 | L10: =4*Tableau8[[#This Row],[Dividende trimestriel]] -> 1.94 | M10: =Tableau8[[#This Row],[Dividende annuel]]/Tableau8[[#This Row],[Prix actuel]] -> 0.037136294 | N10: 23 | O10: {=IFERROR(_FV(Tableau8[[#This Row],[Action]],"Bêta"),"")} -> 0.4758 | P10: {=_FV(Tableau8[[#This Row],[Action]],"Capitalisation boursière",TRUE)} -> 2198259722 | Q10: {=IFERROR(_FV(Tableau8[[#This Row],[Action]],"Année de constitution",TRUE),"")} -> 2018
B11: Aristocrats | D11: #VALUE! | E11: {=_FV(Tableau8[[#This Row],[Action]],"Code mnémonique",TRUE)} -> O | F11: {=_FV(Tableau8[[#This Row],[Action]],"Change")} -> New York Stock Exchange | G11: {=IFERROR(_FV(Tableau8[[#This Row],[Action]],"industrie"),"")} -> Residential & Commercial REIT | H11: {=_FV(Tableau8[[#This Row],[Action]],"Devise")} -> USD | I11: {=_FV(Tableau8[[#This Row],[Action]],"Prix")} -> 64.04 | J11: X | K11: =3*0.248 -> 0.744 | L11: =4*Tableau8[[#This Row],[Dividende trimestriel]] -> 2.976 | M11: =Tableau8[[#This Row],[Dividende annuel]]/Tableau8[[#This Row],[Prix actuel]] -> 0.046470956 | N11: 26 | O11: {=IFERROR(_FV(Tableau8[[#This Row],[Action]],"Bêta"),"")} -> 0.7702 | P11: {=_FV(Tableau8[[#This Row],[Action]],"Capitalisation boursière",TRUE)} -> 59714136424 | Q11: {=IFERROR(_FV(Tableau8[[#This Row],[Action]],"Année de constitution",TRUE),"")} -> 1997
B12: Aristocrats | D12: #VALUE! | E12: {=_FV(Tableau8[[#This Row],[Action]],"Code mnémonique",TRUE)} -> KEY | F12: {=_FV(Tableau8[[#This Row],[Action]],"Change")} -> Toronto Stock Exchange | G12: {=IFERROR(_FV(Tableau8[[#This Row],[Action]],"industrie"),"")} -> Oil & Gas | H12: {=_FV(Tableau8[[#This Row],[Action]],"Devise")} -> CAD | I12: {=_FV(Tableau8[[#This Row],[Action]],"Prix")} -> 49.61 | J12: X | K12: 0.48 | L12: =4*Tableau8[[#This Row],[Dividende trimestriel]] -> 1.92 | M12: =Tableau8[[#This Row],[Dividende annuel]]/Tableau8[[#This Row],[Prix actuel]] -> 0.038701875 | N12: 0 | O12: {=IFERROR(_FV(Tableau8[[#This Row],[Action]],"Bêta"),"")} -> 0.7928 | P12: {=_FV(Tableau8[[#This Row],[Action]],"Capitalisation boursière",TRUE)} -> 13998294948 | Q12: {=IFERROR(_FV(Tableau8[[#This Row],[Action]],"Année de constitution",TRUE),"")} -> 2011
B13: Aristocrats | C13: X | D13: #VALUE! | E13: {=_FV(Tableau8[[#This Row],[Action]],"Code mnémonique",TRUE)} -> PPL | F13: {=_FV(Tableau8[[#This Row],[Action]],"Change")} -> Toronto Stock Exchange | G13: {=IFERROR(_FV(Tableau8[[#This Row],[Action]],"industrie"),"")} -> Oil & Gas Related Equipment and Services | H13: {=_FV(Tableau8[[#This Row],[Action]],"Devise")} -> CAD | I13: {=_FV(Tableau8[[#This Row],[Action]],"Prix")} -> 58.03 | J13: X | K13: 0.651 | L13: =4*Tableau8[[#This Row],[Dividende trimestriel]] -> 2.604 | M13: =Tableau8[[#This Row],[Dividende annuel]]/Tableau8[[#This Row],[Prix actuel]] -> 0.044873341 | N13: 1 | O13: {=IFERROR(_FV(Tableau8[[#This Row],[Action]],"Bêta"),"")} -> 0.658 | P13: {=_FV(Tableau8[[#This Row],[Action]],"Capitalisation boursière",TRUE)} -> 33733105938 | Q13: {=IFERROR(_FV(Tableau8[[#This Row],[Action]],"Année de constitution",TRUE),"")} -> 2010
B14: Dividend King | C14: X | D14: #VALUE! | E14: {=_FV(Tableau8[[#This Row],[Action]],"Code mnémonique",TRUE)} -> MMM | F14: {=_FV(Tableau8[[#This Row],[Action]],"Change")} -> New York Stock Exchange | G14: {=IFERROR(_FV(Tableau8[[#This Row],[Action]],"industrie"),"")} -> Consumer Goods Conglomerates | H14: {=_FV(Tableau8[[#This Row],[Action]],"Devise")} -> USD | I14: {=_FV(Tableau8[[#This Row],[Action]],"Prix")} -> 148.48 | K14: 1.49 | L14: =4*Tableau8[[#This Row],[Dividende trimestriel]] -> 5.96 | M14: =Tableau8[[#This Row],[Dividende annuel]]/Tableau8[[#This Row],[Prix actuel]] -> 0.040140086 | N14: 64 | O14: {=IFERROR(_FV(Tableau8[[#This Row],[Action]],"Bêta"),"")} -> 1.0579 | P14: {=_FV(Tableau8[[#This Row],[Action]],"Capitalisation boursière",TRUE)} -> 77565387776 | Q14: {=IFERROR(_FV(Tableau8[[#This Row],[Action]],"Année de constitution",TRUE),"")} -> 1929
B15: Aristocrats | D15: #VALUE! | E15: {=_FV(Tableau8[[#This Row],[Action]],"Code mnémonique",TRUE)} -> MG | F15: {=_FV(Tableau8[[#This Row],[Action]],"Change")} -> Toronto Stock Exchange | G15: {=IFERROR(_FV(Tableau8[[#This Row],[Action]],"industrie"),"")} -> Automobiles & Auto Parts | H15: {=_FV(Tableau8[[#This Row],[Action]],"Devise")} -> CAD | I15: {=_FV(Tableau8[[#This Row],[Action]],"Prix")} -> 84.32 | K15: 0.605 | L15: =4*Tableau8[[#This Row],[Dividende trimestriel]] -> 2.42 | M15: =Tableau8[[#This Row],[Dividende annuel]]/Tableau8[[#This Row],[Prix actuel]] -> 0.02870019 | N15: 7 | O15: {=IFERROR(_FV(Tableau8[[#This Row],[Action]],"Bêta"),"")} -> 1.8349 | P15: {=_FV(Tableau8[[#This Row],[Action]],"Capitalisation boursière",TRUE)} -> 23308501712 | Q15: {=IFERROR(_FV(Tableau8[[#This Row],[Action]],"Année de constitution",TRUE),"")} -> 2017
B16: Mes recherches | D16: #VALUE! | E16: {=_FV(Tableau8[[#This Row],[Action]],"Code mnémonique",TRUE)} -> PRU | F16: {=_FV(Tableau8[[#This Row],[Action]],"Change")} -> New York Stock Exchange | G16: {=IFERROR(_FV(Tableau8[[#This Row],[Action]],"industrie"),"")} -> Insurance | H16: {=_FV(Tableau8[[#This Row],[Action]],"Devise")} -> USD | I16: {=_FV(Tableau8[[#This Row],[Action]],"Prix")} -> 96.445 | K16: 1.2 | L16: =4*Tableau8[[#This Row],[Dividende trimestriel]] -> 4.8 | M16: =Tableau8[[#This Row],[Dividende annuel]]/Tableau8[[#This Row],[Prix actuel]] -> 0.049769299 | N16: 14 | O16: {=IFERROR(_FV(Tableau8[[#This Row],[Action]],"Bêta"),"")} -> 0.9005 | P16: {=_FV(Tableau8[[#This Row],[Action]],"Capitalisation boursière",TRUE)} -> 33545374521 | Q16: {=IFERROR(_FV(Tableau8[[#This Row],[Action]],"Année de constitution",TRUE),"")} -> 1999
B17: Dividend King | D17: #VALUE! | E17: {=_FV(Tableau8[[#This Row],[Action]],"Code mnémonique",TRUE)} -> BKH | F17: {=_FV(Tableau8[[#This Row],[Action]],"Change")} -> New York Stock Exchange | G17: {=IFERROR(_FV(Tableau8[[#This Row],[Action]],"industrie"),"")} -> Multiline Utilities | H17: {=_FV(Tableau8[[#This Row],[Action]],"Devise")} -> USD | I17: {=_FV(Tableau8[[#This Row],[Action]],"Prix")} -> 73.51 | K17: 0.625 | L17: =4*Tableau8[[#This Row],[Dividende trimestriel]] -> 2.5 | M17: =Tableau8[[#This Row],[Dividende annuel]]/Tableau8[[#This Row],[Prix actuel]] -> 0.034008978 | N17: 51 | O17: {=IFERROR(_FV(Tableau8[[#This Row],[Action]],"Bêta"),"")} -> 0.7337 | P17: {=_FV(Tableau8[[#This Row],[Action]],"Capitalisation boursière",TRUE)} -> 5590783202 | Q17: {=IFERROR(_FV(Tableau8[[#This Row],[Action]],"Année de constitution",TRUE),"")} -> 2000
B18: Dividend King | D18: #VALUE! | E18: {=_FV(Tableau8[[#This Row],[Action]],"Code mnémonique",TRUE)} -> FRT | F18: {=_FV(Tableau8[[#This Row],[Action]],"Change")} -> New York Stock Exchange | G18: {=IFERROR(_FV(Tableau8[[#This Row],[Action]],"industrie"),"")} -> Residential & Commercial REIT | H18: {=_FV(Tableau8[[#This Row],[Action]],"Devise")} -> USD | I18: {=_FV(Tableau8[[#This Row],[Action]],"Prix")} -> 111.13 | K18: 1.08 | L18: =4*Tableau8[[#This Row],[Dividende trimestriel]] -> 4.32 | M18: =Tableau8[[#This Row],[Dividende annuel]]/Tableau8[[#This Row],[Prix actuel]] -> 0.038873392 | N18: 54 | O18: {=IFERROR(_FV(Tableau8[[#This Row],[Action]],"Bêta"),"")} -> 0.9521 | P18: {=_FV(Tableau8[[#This Row],[Action]],"Capitalisation boursière",TRUE)} -> 9600321777 | Q18: {=IFERROR(_FV(Tableau8[[#This Row],[Action]],"Année de constitution",TRUE),"")} -> 2021
B19: Aristocrats | D19: #VALUE! | E19: {=_FV(Tableau8[[#This Row],[Action]],"Code mnémonique",TRUE)} -> QBR.B | F19: {=_FV(Tableau8[[#This Row],[Action]],"Change")} -> Toronto Stock Exchange | G19: {=IFERROR(_FV(Tableau8[[#This Row],[Action]],"industrie"),"")} -> Telecommunications Services | H19: {=_FV(Tableau8[[#This Row],[Action]],"Devise")} -> CAD | I19: {=_FV(Tableau8[[#This Row],[Action]],"Prix")} -> 55.83 | K19: 0.3 | L19: =4*Tableau8[[#This Row],[Dividende trimestriel]] -> 1.2 | M19: =Tableau8[[#This Row],[Dividende annuel]]/Tableau8[[#This Row],[Prix actuel]] -> 0.021493821 | N19: 8 | O19: {=IFERROR(_FV(Tableau8[[#This Row],[Action]],"Bêta"),"")} -> 0.6577 | P19: {=_FV(Tableau8[[#This Row],[Action]],"Capitalisation boursière",TRUE)} -> 12594918603 | Q19: {=IFERROR(_FV(Tableau8[[#This Row],[Action]],"Année de constitution",TRUE),"")} -> 1994
B20: Mes recherches | D20: #VALUE! | E20: {=_FV(Tableau8[[#This Row],[Action]],"Code mnémonique",TRUE)} -> SCHD | F20: {=_FV(Tableau8[[#This Row],[Action]],"Change")} -> NYSE Arca | G20: {=IFERROR(_FV(Tableau8[[#This Row],[Action]],"industrie"),"")} | H20: {=_FV(Tableau8[[#This Row],[Action]],"Devise")} -> USD | I20: {=_FV(Tableau8[[#This Row],[Action]],"Prix")} -> 30.975 | K20: 0.703 | L20: =4*Tableau8[[#This Row],[Dividende trimestriel]] -> 2.812 | M20: =Tableau8[[#This Row],[Dividende annuel]]/Tableau8[[#This Row],[Prix actuel]] -> 0.090782889 | N20: 10 | O20: {=IFERROR(_FV(Tableau8[[#This Row],[Action]],"Bêta"),"")} -> 0.957 | P20: {=_FV(Tableau8[[#This Row],[Action]],"Capitalisation boursière",TRUE)} -> 8.4819998e+10 | Q20: {=IFERROR(_FV(Tableau8[[#This Row],[Action]],"Année de constitution",TRUE),"")}
B21: Aristocrats | D21: #VALUE! | E21: {=_FV(Tableau8[[#This Row],[Action]],"Code mnémonique",TRUE)} -> CTC | F21: {=_FV(Tableau8[[#This Row],[Action]],"Change")} -> Toronto Stock Exchange | G21: {=IFERROR(_FV(Tableau8[[#This Row],[Action]],"industrie"),"")} -> Diversified Retail | H21: {=_FV(Tableau8[[#This Row],[Action]],"Devise")} -> CAD | I21: {=_FV(Tableau8[[#This Row],[Action]],"Prix")} -> 219.99 | K21: 1.75 | L21: =4*Tableau8[[#This Row],[Dividende trimestriel]] -> 7 | M21: =Tableau8[[#This Row],[Dividende annuel]]/Tableau8[[#This Row],[Prix actuel]] -> 0.031819628 | N21: 12 | O21: {=IFERROR(_FV(Tableau8[[#This Row],[Action]],"Bêta"),"")} -> 1.0004 | P21: {=_FV(Tableau8[[#This Row],[Action]],"Capitalisation boursière",TRUE)} -> 11578709471 | Q21: {=IFERROR(_FV(Tableau8[[#This Row],[Action]],"Année de constitution",TRUE),"")} -> 1980
B22: Dividend King | D22: #VALUE! | E22: {=_FV(Tableau8[[#This Row],[Action]],"Code mnémonique",TRUE)} -> FMCB | F22: {=_FV(Tableau8[[#This Row],[Action]],"Change")} -> OTC Markets | G22: {=IFERROR(_FV(Tableau8[[#This Row],[Action]],"industrie"),"")} -> Banking Services | H22: {=_FV(Tableau8[[#This Row],[Action]],"Devise")} -> USD | I22: {=_FV(Tableau8[[#This Row],[Action]],"Prix")} -> 1225 | K22: 8.3 | L22: =4*Tableau8[[#This Row],[Dividende trimestriel]] -> 33.2 | M22: =Tableau8[[#This Row],[Dividende annuel]]/Tableau8[[#This Row],[Prix actuel]] -> 0.027102041 | N22: 58 | O22: {=IFERROR(_FV(Tableau8[[#This Row],[Action]],"Bêta"),"")} -> 0.0637 | P22: {=_FV(Tableau8[[#This Row],[Action]],"Capitalisation boursière",TRUE)} -> 848974000 | Q22: {=IFERROR(_FV(Tableau8[[#This Row],[Action]],"Année de constitution",TRUE),"")} -> 1999
B23: Dividend King | D23: #VALUE! | E23: {=_FV(Tableau8[[#This Row],[Action]],"Code mnémonique",TRUE)} -> HRL | F23: {=_FV(Tableau8[[#This Row],[Action]],"Change")} -> New York Stock Exchange | G23: {=IFERROR(_FV(Tableau8[[#This Row],[Action]],"industrie"),"")} -> Food & Tobacco | H23: {=_FV(Tableau8[[#This Row],[Action]],"Devise")} -> USD | I23: {=_FV(Tableau8[[#This Row],[Action]],"Prix")} -> 21.26 | K23: 0.275 | L23: =4*Tableau8[[#This Row],[Dividende trimestriel]] -> 1.1 | M23: =Tableau8[[#This Row],[Dividende annuel]]/Tableau8[[#This Row],[Prix actuel]] -> 0.051740357 | N23: 21 | O23: {=IFERROR(_FV(Tableau8[[#This Row],[Action]],"Bêta"),"")} -> 0.321 | P23: {=_FV(Tableau8[[#This Row],[Action]],"Capitalisation boursière",TRUE)} -> 11699042092 | Q23: {=IFERROR(_FV(Tableau8[[#This Row],[Action]],"Année de constitution",TRUE),"")} -> 1928
B24: Aristocrats | D24: #VALUE! | E24: {=_FV(Tableau8[[#This Row],[Action]],"Code mnémonique",TRUE)} -> ABX | F24: {=_FV(Tableau8[[#This Row],[Action]],"Change")} -> Toronto Stock Exchange | G24: {=IFERROR(_FV(Tableau8[[#This Row],[Action]],"industrie"),"")} -> Metals & Mining | H24: {=_FV(Tableau8[[#This Row],[Action]],"Devise")} -> CAD | I24: {=_FV(Tableau8[[#This Row],[Action]],"Prix")} -> 55.35 | K24: 0.203 | L24: =4*Tableau8[[#This Row],[Dividende trimestriel]] -> 0.812 | M24: =Tableau8[[#This Row],[Dividende annuel]]/Tableau8[[#This Row],[Prix actuel]] -> 0.01467028 | N24: 1 | O24: {=IFERROR(_FV(Tableau8[[#This Row],[Action]],"Bêta"),"")} -> 1.0917 | P24: {=_FV(Tableau8[[#This Row],[Action]],"Capitalisation boursière",TRUE)} -> 92739367800 | Q24: {=IFERROR(_FV(Tableau8[[#This Row],[Action]],"Année de constitution",TRUE),"")} -> 2018
